Workbook

Sheet Copy of Copy of Backlog
A1: Effort Willing to Visit | B1: What | C1: One Liner | D1: Longer Description | E1: Accessible | F1: Location | G1: Google Maps Link | H1: Location Category | I1: Cache Entry | J1: Address Component Types | K1: Map Content Dynamically Loaded | L1: City is in Location Description | M1: Coordinates Cached | N1: Lat | O1: Long | P1: City | Q1: State / Region | R1: Postal Code | S1: Country | T1: Drive Distance (Miles) | U1: Drive Time | V1: Absolute Distance (Miles) | W1: Requires Hike? | X1: Hike Distance Roundtrip Miles | Y1: Hike Link | Z1: Last Been | AA1: Activity | AB1: Link 1 | AC1: Link 2 | AD1: Link 3 | AE1: Superlative Liner | AF1: Notes
A2: 7 - Bucket List | B2: Torngat Mountains National Park | C2: This dramatic, otherworldly landscape of sweeping peaks and valleys in Newfoundland and Labrador named for the Inuktitut “Tongait” or “place of the spirits” is remote with a capital R, which is why most travelers never make it there. Here’s why you should. | D2: It’s hard to describe the Torngats without gushing. It’s simply superlative. It’s a place of unusual geology created by some of the world’s oldest rocks. Towering glacier-carved mountains in hues of peach, green, and gray rise up dramatically from river-cut valleys and fjords far below like a cinematographer’s flipside take on Mordor. The place feels brooding, uplifting, and spiritual at the same time. Not surprisingly, it was once the stomping grounds of Inuit shamans. Go to get way out there and experience nature at her most unspoiled; for solitude, rugged adventure, to meet the Aboriginals who live there, and to see creatures like polar bears, whales, and caribou in their pristine natural environment. | F2: Torngat Mountains National Park, Canada | G2: =HYPERLINK(CONCAT("https://www.google.com/maps/search/",F2),"Link") -> Link | H2: Nature | I2: =getCacheString(concat("GMPD|",F2)) -> {"distance_from":{"mi":{"driving":{"2116 4th Ave, Seattle, WA, 98121":"GOOGLE_MAPS_ERROR_CACHED - No route found!"},"flying":{"2116 4th Ave, Seattle, WA, 98121":2442.586401879031}}},"address_components":[{"types":[],"long_name":"Torngat Mountains","short_name":""},{"long_name":"Torngat Mountains National Park","types":["establishment","park","point_of_interest","tourist_attraction"],"short_name":"Torngat Mountains National Park"},{"types":["locality","political"],"long_name":"Nain","short_name":"Nain"},{"short_name":"NL","types":["administrative_area_level_1","political"],"long_name":"Newfoundland and Labrador"},{"long_name":"Canada","short_name":"CA","types":["country","political"]},{"long_name":"A0P 1L0","types":["postal_code"],"short_name":"A0P 1L0"},{"types":["plus_code"],"long_name":"97FR62F4+RM","short_name":"97FR62F4+RM"},{"types":["latitude"],"long_name":59.22460509999999,"short_name":59.22460509999999},{"types":["longitude"],"long_name":-63.99337480000001,"short_name":-63.99337480000001}],"duration_from":{"days":{"driving":{"2116 4th Ave, Seattle, WA, 98121":"GOOGLE_MAPS_ERROR_CACHED - No route found!"}}}} | J2: =GOOGLEMAPS_GET_ADDRESS_COMPONENTS_STRING(F2,false) -> [{"types":[],"long_name":"Torngat Mountains","short_name":""},{"long_name":"Torngat Mountains National Park","types":["establishment","park","point_of_interest","tourist_attraction"],"short_name":"Torngat Mountains National Park"},{"types":["locality","political"],"long_name":"Nain","short_name":"Nain"},{"short_name":"NL","types":["administrative_area_level_1","political"],"long_name":"Newfoundland and Labrador"},{"long_name":"Canada","short_name":"CA","types":["country","political"]},{"long_name":"A0P 1L0","types":["postal_code"],"short_name":"A0P 1L0"},{"types":["plus_code"],"long_name":"97FR62F4+RM","short_name":"97FR62F4+RM"},{"types":["latitude"],"long_name":59.22460509999999,"short_name":59.22460509999999},{"types":["longitude"],"long_name":-63.99337480000001,"short_name":-63.99337480000001},{"types":["debug_info","cache_load_result"],"long_name":"hit","short_name":"hit"}] | K2: =NOT(AND(NOT(_xlfn.ISFORMULA(P2)),AND(NOT(_xlfn.ISFORMULA(Q2)),AND(NOT(_xlfn.ISFORMULA(R2)),AND(NOT(_xlfn.ISFORMULA(S2)),AND(NOT(_xlfn.ISFORMULA(T2)),AND(NOT(_xlfn.ISFORMULA(U2)),AND(NOT(_xlfn.ISFORMULA(V2)))))))))) -> TRUE | L2: =iferror(SEARCH(P2,F2),-1)>=0 -> FALSE | M2: TRUE | N2: =GOOGLEMAPS_GET_ADDRESS_LATITUDE(F2,true) -> 59.224605 | O2: =GOOGLEMAPS_GET_ADDRESS_LONGITUDE(F2,true) -> -63.993375 | P2: =GOOGLEMAPS_GET_ADDRESS_CITY(F2,true,false) -> Nain | Q2: =GOOGLEMAPS_GET_ADDRESS_STATE(F2,true,false) -> Newfoundland and Labrador | R2: =GOOGLEMAPS_GET_ADDRESS_POSTAL_CODE(F2,false,false) -> A0P 1L0 | S2: =GOOGLEMAPS_GET_ADDRESS_COUNTRY(F2,true,false) -> Canada | T2: =IFERROR(GOOGLEMAPS_DISTANCE("2116 4th Ave, Seattle, WA, 98121", F2, "driving")+0,"Not Driveable") -> Not Driveable | U2: =iferror(GOOGLEMAPS_DURATION("2116 4th Ave, Seattle, WA, 98121", F2, "driving")+0,"Not Driveable") -> Not Driveable | V2: =GOOGLEMAPS_DISTANCE("2116 4th Ave, Seattle, WA, 98121", F2, "flying")+0 -> 2442.5864 | X2: =if(W2="YES","UNKNOWN","N/A") -> N/A | Z2: N/A | AB2: https://us-keepexploring.canada.travel/things-to-do/bucket-list-guide-torngat-mountains-national-park
A3: 7 - Bucket List | B3: Centralia | C3: Coal mining town with active fire under it | D3: Centralia was yet another victim of the U.S. decline in mining, but not in the same way as the others on this list. A massive underground coal fire ignited beneath the town in 1962 and it’s been burning ever since. The town’s population plummeted from more than 1,000 in 1980 to less than 10 in 2013. Not surprisingly, the town was subsequently condemned. However, some (clearly insane) residents still call the town home. Due to the dangerous air toxicity and high potential for sinkholes, most of it is strictly off limits. However, that hasn’t stopped the hundreds of “ruin porn”-seeking visitors who visit its decaying streets each year. | E3: 1 – Accessible – Freely | F3: Centralia, PA | G3: =HYPERLINK(CONCAT("https://www.google.com/maps/search/",F3),"Link") -> Link | H3: Ghost Town | I3: =getCacheString(concat("GMPD|",F3)) -> {"address_components":[{"short_name":"Centralia","types":["locality","political"],"long_name":"Centralia"},{"long_name":"Columbia County","short_name":"Columbia County","types":["administrative_area_level_2","political"]},{"long_name":"Pennsylvania","types":["administrative_area_level_1","political"],"short_name":"PA"},{"short_name":"US","types":["country","political"],"long_name":"United States"},{"long_name":"422","short_name":"422","types":["street_number"]},{"long_name":"Locust Avenue","types":["route"],"short_name":"Locust Ave"},{"short_name":"Aristes","long_name":"Aristes","types":["locality","political"]},{"short_name":"Columbia County","long_name":"Columbia County","types":["administrative_area_level_2","political"]},{"short_name":"PA","types":["administrative_area_level_1","political"],"long_name":"Pennsylvania"},{"short_name":"US","types":["country","political"],"long_name":"United States"},{"short_name":"17920","types":["postal_code"],"long_name":"17920"},{"types":["latitude"],"long_name":40.8042541,"short_name":40.8042541},{"types":["longitude"],"long_name":-76.3405035,"short_name":-76.3405035}]} | J3: =GOOGLEMAPS_GET_ADDRESS_COMPONENTS_STRING(F3,false) -> [{"short_name":"Centralia","types":["locality","political"],"long_name":"Centralia"},{"long_name":"Columbia County","short_name":"Columbia County","types":["administrative_area_level_2","political"]},{"long_name":"Pennsylvania","types":["administrative_area_level_1","political"],"short_name":"PA"},{"short_name":"US","types":["country","political"],"long_name":"United States"},{"long_name":"422","short_name":"422","types":["street_number"]},{"long_name":"Locust Avenue","types":["route"],"short_name":"Locust Ave"},{"short_name":"Aristes","long_name":"Aristes","types":["locality","political"]},{"short_name":"Columbia County","long_name":"Columbia County","types":["administrative_area_level_2","political"]},{"short_name":"PA","types":["administrative_area_level_1","political"],"long_name":"Pennsylvania"},{"short_name":"US","types":["country","political"],"long_name":"United States"},{"short_name":"17920","types":["postal_code"],"long_name":"17920"},{"types":["latitude"],"long_name":40.8042541,"short_name":40.8042541},{"types":["longitude"],"long_name":-76.3405035,"short_name":-76.3405035},{"types":["debug_info","cache_load_result"],"long_name":"hit","short_name":"hit"}] | K3: =NOT(AND(NOT(_xlfn.ISFORMULA(P3)),AND(NOT(_xlfn.ISFORMULA(Q3)),AND(NOT(_xlfn.ISFORMULA(R3)),AND(NOT(_xlfn.ISFORMULA(S3)),AND(NOT(_xlfn.ISFORMULA(T3)),AND(NOT(_xlfn.ISFORMULA(U3)),AND(NOT(_xlfn.ISFORMULA(V3)),AND(NOT(_xlfn.ISFORMULA(N3)),NOT(_xlfn.ISFORMULA(O3))))))))))) -> FALSE | L3: =iferror(SEARCH(P3,F3),-1)>=0 -> TRUE | M3: TRUE | N3: 40.804254 | O3: -76.340503 | P3: Centralia | Q3: Pennsylvania | R3: 17920 | S3: United States | T3: 2720 | U3: 1.6646759 | V3: 2291.26 | X3: =if(W3="YES","UNKNOWN","N/A") -> N/A | Z3: N/A | AF3: Mining Town that has an Underground Fire
A4: 7 - Bucket List | B4: Lake Maracaibo | C4: Giant lake with frequent lightning | E4: 1 – Accessible – Freely | F4: Lake Maracaibo, Venezuela | G4: =HYPERLINK(CONCAT("https://www.google.com/maps/search/",F4),"Link") -> Link | H4: Nature | I4: =getCacheString(concat("GMPD|",F4)) -> {"distance_from":{"mi":{"flying":{"2116 4th Ave, Seattle, WA, 98121":3920.1623025588133},"driving":{"2116 4th Ave, Seattle, WA, 98121":"GOOGLE_MAPS_ERROR_CACHED - No route found!"}}},"address_components":[{"short_name":"Lake Maracaibo","types":["establishment","natural_feature"],"long_name":"Lake Maracaibo"},{"long_name":"Venezuela","short_name":"VE","types":["country","political"]},{"long_name":"772C2CHF+46","short_name":"772C2CHF+46","types":["plus_code"]},{"types":["latitude"],"long_name":10.0278,"short_name":10.0278},{"types":["longitude"],"long_name":-71.5769,"short_name":-71.5769}],"duration_from":{"days":{"driving":{"2116 4th Ave, Seattle, WA, 98121":"GOOGLE_MAPS_ERROR_CACHED - No route found!"}}}} | J4: =GOOGLEMAPS_GET_ADDRESS_COMPONENTS_STRING(F4,false) -> [{"short_name":"Lake Maracaibo","types":["establishment","natural_feature"],"long_name":"Lake Maracaibo"},{"long_name":"Venezuela","short_name":"VE","types":["country","political"]},{"long_name":"772C2CHF+46","short_name":"772C2CHF+46","types":["plus_code"]},{"types":["latitude"],"long_name":10.0278,"short_name":10.0278},{"types":["longitude"],"long_name":-71.5769,"short_name":-71.5769},{"types":["debug_info","cache_load_result"],"long_name":"hit","short_name":"hit"}] | K4: =NOT(AND(NOT(_xlfn.ISFORMULA(P4)),AND(NOT(_xlfn.ISFORMULA(Q4)),AND(NOT(_xlfn.ISFORMULA(R4)),AND(NOT(_xlfn.ISFORMULA(S4)),AND(NOT(_xlfn.ISFORMULA(T4)),AND(NOT(_xlfn.ISFORMULA(U4)),AND(NOT(_xlfn.ISFORMULA(V4)))))))))) -> TRUE | L4: =iferror(SEARCH(P4,F4),-1)>=0 -> FALSE | M4: TRUE | N4: =GOOGLEMAPS_GET_ADDRESS_LATITUDE(F4,true) -> 10.0278 | O4: =GOOGLEMAPS_GET_ADDRESS_LONGITUDE(F4,true) -> -71.5769 | P4: =GOOGLEMAPS_GET_ADDRESS_CITY(F4,true,false) -> UNDEFINED | Q4: =GOOGLEMAPS_GET_ADDRESS_STATE(F4,true,false) -> UNDEFINED | R4: =GOOGLEMAPS_GET_ADDRESS_POSTAL_CODE(F4,false,false) -> UNDEFINED | S4: =GOOGLEMAPS_GET_ADDRESS_COUNTRY(F4,true,false) -> Venezuela | T4: =IFERROR(GOOGLEMAPS_DISTANCE("2116 4th Ave, Seattle, WA, 98121", F4, "driving")+0,"Not Driveable") -> Not Driveable | U4: =iferror(GOOGLEMAPS_DURATION("2116 4th Ave, Seattle, WA, 98121", F4, "driving")+0,"Not Driveable") -> Not Driveable | V4: =GOOGLEMAPS_DISTANCE("2116 4th Ave, Seattle, WA, 98121", F4, "flying")+0 -> 3920.1623 | X4: =if(W4="YES","UNKNOWN","N/A") -> N/A | Z4: N/A
A5: 7 - Bucket List | B5: Faroe Islands | E5: 1 – Accessible – Freely | F5: Faroe Islands | G5: =HYPERLINK(CONCAT("https://www.google.com/maps/search/",F5),"Link") -> Link | H5: Nature | I5: =getCacheString(concat("GMPD|",F5)) -> {"address_components":[{"long_name":"Faroe Islands","types":["country","political"],"short_name":"FO"},{"short_name":"V3VQ+37","long_name":"V3VQ+37","types":["plus_code"]},{"long_name":"Skopun","types":["locality","political"],"short_name":"Skopun"},{"short_name":"Sandoy","long_name":"Sandoy","types":["administrative_area_level_1","political"]},{"types":["country","political"],"long_name":"Faroe Islands","short_name":"FO"},{"types":["latitude"],"long_name":61.89263500000001,"short_name":61.89263500000001},{"types":["longitude"],"long_name":-6.911805999999999,"short_name":-6.911805999999999}]} | J5: =GOOGLEMAPS_GET_ADDRESS_COMPONENTS_STRING(F5,false) -> [{"long_name":"Faroe Islands","types":["country","political"],"short_name":"FO"},{"short_name":"V3VQ+37","long_name":"V3VQ+37","types":["plus_code"]},{"long_name":"Skopun","types":["locality","political"],"short_name":"Skopun"},{"short_name":"Sandoy","long_name":"Sandoy","types":["administrative_area_level_1","political"]},{"types":["country","political"],"long_name":"Faroe Islands","short_name":"FO"},{"types":["latitude"],"long_name":61.89263500000001,"short_name":61.89263500000001},{"types":["longitude"],"long_name":-6.911805999999999,"short_name":-6.911805999999999},{"types":["debug_info","cache_load_result"],"long_name":"hit","short_name":"hit"}] | K5: =NOT(AND(NOT(_xlfn.ISFORMULA(P5)),AND(NOT(_xlfn.ISFORMULA(Q5)),AND(NOT(_xlfn.ISFORMULA(R5)),AND(NOT(_xlfn.ISFORMULA(S5)),AND(NOT(_xlfn.ISFORMULA(T5)),AND(NOT(_xlfn.ISFORMULA(U5)),AND(NOT(_xlfn.ISFORMULA(V5)),AND(NOT(_xlfn.ISFORMULA(N5)),NOT(_xlfn.ISFORMULA(O5))))))))))) -> FALSE | L5: =iferror(SEARCH(P5,F5),-1)>=0 -> FALSE | M5: TRUE | N5: 61.892635 | O5: -6.911806 | P5: Skopun | Q5: Sandoy | R5: UNDEFINED | S5: Faroe Islands | T5: Not Driveable | U5: Not Driveable | V5: 4076.06 | X5: =if(W5="YES","UNKNOWN","N/A") -> N/A | Z5: N/A
A6: 7 - Bucket List | B6: Isle of Skye | E6: 1 – Accessible – Freely | F6: Isle of Skye, Scotland | G6: =HYPERLINK(CONCAT("https://www.google.com/maps/search/",F6),"Link") -> Link | H6: Nature | I6: =getCacheString(concat("GMPD|",F6)) -> {"address_components":[{"long_name":"Skye","short_name":"Skye","types":["establishment","natural_feature"]},{"short_name":"Highland Council","types":["administrative_area_level_2","political"],"long_name":"Highland Council"},{"short_name":"Scotland","types":["administrative_area_level_1","political"],"long_name":"Scotland"},{"types":["country","political"],"long_name":"United Kingdom","short_name":"GB"},{"types":["plus_code"],"long_name":"7QFM+FQ","short_name":"7QFM+FQ"},{"types":["locality","political"],"long_name":"Sligachan","short_name":"Sligachan"},{"short_name":"Isle of Skye","long_name":"Isle of Skye","types":["postal_town"]},{"long_name":"Highland Council","short_name":"Highland Council","types":["administrative_area_level_2","political"]},{"long_name":"Scotland","short_name":"Scotland","types":["administrative_area_level_1","political"]},{"long_name":"United Kingdom","short_name":"GB","types":["country","political"]},{"long_name":"IV47 8SW","short_name":"IV47 8SW","types":["postal_code"]},{"types":["latitude"],"long_name":57.2736278,"short_name":57.2736278},{"types":["longitude"],"long_name":-6.2155022,"short_name":-6.2155022}],"distance_from":{"mi":{"flying":{"2116 4th Ave, Seattle, WA, 98121":4322.158773161669},"driving":{"2116 4th Ave, Seattle, WA, 98121":"GOOGLE_MAPS_ERROR_CACHED - No route found!"}}},"duration_from":{"days":{"driving":{"2116 4th Ave, Seattle, WA, 98121":"GOOGLE_MAPS_ERROR_CACHED - No route found!"}}}} | J6: =GOOGLEMAPS_GET_ADDRESS_COMPONENTS_STRING(F6,false) -> [{"long_name":"Skye","short_name":"Skye","types":["establishment","natural_feature"]},{"short_name":"Highland Council","types":["administrative_area_level_2","political"],"long_name":"Highland Council"},{"short_name":"Scotland","types":["administrative_area_level_1","political"],"long_name":"Scotland"},{"types":["country","political"],"long_name":"United Kingdom","short_name":"GB"},{"types":["plus_code"],"long_name":"7QFM+FQ","short_name":"7QFM+FQ"},{"types":["locality","political"],"long_name":"Sligachan","short_name":"Sligachan"},{"short_name":"Isle of Skye","long_name":"Isle of Skye","types":["postal_town"]},{"long_name":"Highland Council","short_name":"Highland Council","types":["administrative_area_level_2","political"]},{"long_name":"Scotland","short_name":"Scotland","types":["administrative_area_level_1","political"]},{"long_name":"United Kingdom","short_name":"GB","types":["country","political"]},{"long_name":"IV47 8SW","short_name":"IV47 8SW","types":["postal_code"]},{"types":["latitude"],"long_name":57.2736278,"short_name":57.2736278},{"types":["longitude"],"long_name":-6.2155022,"short_name":-6.2155022},{"types":["debug_info","cache_load_result"],"long_name":"hit","short_name":"hit"}] | K6: =NOT(AND(NOT(_xlfn.ISFORMULA(P6)),AND(NOT(_xlfn.ISFORMULA(Q6)),AND(NOT(_xlfn.ISFORMULA(R6)),AND(NOT(_xlfn.ISFORMULA(S6)),AND(NOT(_xlfn.ISFORMULA(T6)),AND(NOT(_xlfn.ISFORMULA(U6)),AND(NOT(_xlfn.ISFORMULA(V6)))))))))) -> TRUE | L6: =iferror(SEARCH(P6,F6),-1)>=0 -> FALSE | M6: TRUE | N6: =GOOGLEMAPS_GET_ADDRESS_LATITUDE(F6,true) -> 57.273628 | O6: =GOOGLEMAPS_GET_ADDRESS_LONGITUDE(F6,true) -> -6.2155022 | P6: =GOOGLEMAPS_GET_ADDRESS_CITY(F6,true,false) -> Sligachan | Q6: =GOOGLEMAPS_GET_ADDRESS_STATE(F6,true,false) -> Scotland | R6: =GOOGLEMAPS_GET_ADDRESS_POSTAL_CODE(F6,false,false) -> IV47 8SW | S6: =GOOGLEMAPS_GET_ADDRESS_COUNTRY(F6,true,false) -> United Kingdom | T6: =IFERROR(GOOGLEMAPS_DISTANCE("2116 4th Ave, Seattle, WA, 98121", F6, "driving")+0,"Not Driveable") -> Not Driveable | U6: =iferror(GOOGLEMAPS_DURATION("2116 4th Ave, Seattle, WA, 98121", F6, "driving")+0,"Not Driveable") -> Not Driveable | V6: =GOOGLEMAPS_DISTANCE("2116 4th Ave, Seattle, WA, 98121", F6, "flying")+0 -> 4322.1588 | X6: =if(W6="YES","UNKNOWN","N/A") -> N/A | Z6: N/A
A7: 7 - Bucket List | B7: Wistman's Wood | E7: 1 – Accessible – Freely | F7: Two Bridges, Princetown, United Kingdom | G7: =HYPERLINK(CONCAT("https://www.google.com/maps/search/",F7),"Link") -> Link | H7: Nature | I7: =getCacheString(concat("GMPD|",F7)) -> {"address_components":[{"long_name":"Princetown","short_name":"Princetown","types":["locality","political"]},{"long_name":"Yelverton","types":["postal_town"],"short_name":"Yelverton"},{"short_name":"Devon","types":["administrative_area_level_2","political"],"long_name":"Devon"},{"long_name":"England","types":["administrative_area_level_1","political"],"short_name":"England"},{"long_name":"United Kingdom","short_name":"GB","types":["country","political"]},{"short_name":"PL20","types":["postal_code","postal_code_prefix"],"long_name":"PL20"},{"long_name":"Railway Inn","types":["premise"],"short_name":"Railway Inn"},{"types":["route"],"long_name":"Two Bridges Road","short_name":"Two Bridges Rd"},{"short_name":"Princetown","long_name":"Princetown","types":["locality","political"]},{"long_name":"Yelverton","types":["postal_town"],"short_name":"Yelverton"},{"long_name":"Devon","short_name":"Devon","types":["administrative_area_level_2","political"]},{"long_name":"England","short_name":"England","types":["administrative_area_level_1","political"]},{"long_name":"United Kingdom","short_name":"GB","types":["country","political"]},{"long_name":"PL20 6QT","short_name":"PL20 6QT","types":["postal_code"]},{"types":["latitude"],"long_name":50.54412920000001,"short_name":50.54412920000001},{"types":["longitude"],"long_name":-3.9905352,"short_name":-3.9905352}]} | J7: =GOOGLEMAPS_GET_ADDRESS_COMPONENTS_STRING(F7,false) -> [{"long_name":"Princetown","short_name":"Princetown","types":["locality","political"]},{"long_name":"Yelverton","types":["postal_town"],"short_name":"Yelverton"},{"short_name":"Devon","types":["administrative_area_level_2","political"],"long_name":"Devon"},{"long_name":"England","types":["administrative_area_level_1","political"],"short_name":"England"},{"long_name":"United Kingdom","short_name":"GB","types":["country","political"]},{"short_name":"PL20","types":["postal_code","postal_code_prefix"],"long_name":"PL20"},{"long_name":"Railway Inn","types":["premise"],"short_name":"Railway Inn"},{"types":["route"],"long_name":"Two Bridges Road","short_name":"Two Bridges Rd"},{"short_name":"Princetown","long_name":"Princetown","types":["locality","political"]},{"long_name":"Yelverton","types":["postal_town"],"short_name":"Yelverton"},{"long_name":"Devon","short_name":"Devon","types":["administrative_area_level_2","political"]},{"long_name":"England","short_name":"England","types":["administrative_area_level_1","political"]},{"long_name":"United Kingdom","short_name":"GB","types":["country","political"]},{"long_name":"PL20 6QT","short_name":"PL20 6QT","types":["postal_code"]},{"types":["latitude"],"long_name":50.54412920000001,"short_name":50.54412920000001},{"types":["longitude"],"long_name":-3.9905352,"short_name":-3.9905352},{"types":["debug_info","cache_load_result"],"long_name":"hit","short_name":"hit"}] | K7: =NOT(AND(NOT(_xlfn.ISFORMULA(P7)),AND(NOT(_xlfn.ISFORMULA(Q7)),AND(NOT(_xlfn.ISFORMULA(R7)),AND(NOT(_xlfn.ISFORMULA(S7)),AND(NOT(_xlfn.ISFORMULA(T7)),AND(NOT(_xlfn.ISFORMULA(U7)),AND(NOT(_xlfn.ISFORMULA(V7)),AND(NOT(_xlfn.ISFORMULA(N7)),NOT(_xlfn.ISFORMULA(O7))))))))))) -> FALSE | L7: =iferror(SEARCH(P7,F7),-1)>=0 -> TRUE | M7: TRUE | N7: 50.545768 | O7: -3.9883076 | P7: Princetown | Q7: England | R7: PL20 | S7: United Kingdom | T7: Not Driveable | U7: Not Driveable | V7: 4731.31 | X7: =if(W7="YES","UNKNOWN","N/A") -> N/A | Z7: N/A
A8: 7 - Bucket List | B8: The Tumen River | C8: The Tumen River is a gateway between China, North Korea and Russia | D8: The Tumen River makes up part of the boundary between China, North Korea and Russia. Due to the fact that many North Koreans have been caught trying to enter China through the river’s shallow waters, the Tumen River is tightly guarded by the three countries. | E8: 7 – Inaccessible – Government Property / Ban | F8: The Tumen River | G8: =HYPERLINK(CONCAT("https://www.google.com/maps/search/",F8),"Link") -> Link | H8: Nature | I8: =getCacheString(concat("GMPD|",F8)) -> {"address_components":[{"long_name":"Tumen River","types":["establishment","natural_feature"],"short_name":"Tumen River"},{"long_name":"8QJFFHWF+H4","short_name":"8QJFFHWF+H4","types":["plus_code"]},{"types":["latitude"],"long_name":42.49638202036756,"short_name":42.49638202036756},{"types":["longitude"],"long_name":129.5727514781101,"short_name":129.5727514781101}]} | J8: =GOOGLEMAPS_GET_ADDRESS_COMPONENTS_STRING(F8,false) -> [{"long_name":"Tumen River","types":["establishment","natural_feature"],"short_name":"Tumen River"},{"long_name":"8QJFFHWF+H4","short_name":"8QJFFHWF+H4","types":["plus_code"]},{"types":["latitude"],"long_name":42.49638202036756,"short_name":42.49638202036756},{"types":["longitude"],"long_name":129.5727514781101,"short_name":129.5727514781101},{"types":["debug_info","cache_load_result"],"long_name":"hit","short_name":"hit"}] | K8: =NOT(AND(NOT(_xlfn.ISFORMULA(P8)),AND(NOT(_xlfn.ISFORMULA(Q8)),AND(NOT(_xlfn.ISFORMULA(R8)),AND(NOT(_xlfn.ISFORMULA(S8)),AND(NOT(_xlfn.ISFORMULA(T8)),AND(NOT(_xlfn.ISFORMULA(U8)),AND(NOT(_xlfn.ISFORMULA(V8)),AND(NOT(_xlfn.ISFORMULA(N8)),NOT(_xlfn.ISFORMULA(O8))))))))))) -> FALSE | L8: =iferror(SEARCH(P8,F8),-1)>=0 -> FALSE | M8: TRUE | N8: 42.496382 | O8: 129.57275 | P8: UNDEFINED | Q8: UNDEFINED | R8: UNDEFINED | S8: UNDEFINED | T8: Not Driveable | U8: Not Driveable | V8: 4825.36 | X8: =if(W8="YES","UNKNOWN","N/A") -> N/A | Z8: N/A | AB8: https://magazine.lensvid.com/article/fb/1318327108/mysterious-places-in-the-world-that-are-off-limits-to-everyone-and-why/
A9: 7 - Bucket List | B9: Ise Grand Shrine, Japan | C9: Only the Japanese Imperial family is allowed inside the Ise Grand Shrine | D9: Erected in 4 BCE, the Ise Grand Shrine is considered the birthplace of Shinto, Japan’s native belief system. The shrine is so sacred to the Japanese that it receives over six million visitors every year even though access to the site is extremely limited. While only members of the Imperial family are allowed inside the main shrine, the general public can roam the forest around the Ise Grand Shrine. | E9: 7 – Inaccessible – Government Property / Ban | F9: Ise Grand Shrine, Japan | G9: =HYPERLINK(CONCAT("https://www.google.com/maps/search/",F9),"Link") -> Link | H9: Religious Site | I9: =getCacheString(concat("GMPD|",F9)) -> {"address_components":[{"long_name":"1","short_name":"1","types":["premise"]},{"types":["political","sublocality","sublocality_level_2"],"short_name":"Ujitachichō","long_name":"Ujitachichō"},{"types":["locality","political"],"long_name":"Ise","short_name":"Ise"},{"types":["administrative_area_level_1","political"],"short_name":"Mie","long_name":"Mie"},{"long_name":"Japan","types":["country","political"],"short_name":"JP"},{"long_name":"516-0023","types":["postal_code"],"short_name":"516-0023"},{"long_name":"1","short_name":"1","types":["premise"]},{"long_name":"Ujitachichō","short_name":"Ujitachichō","types":["political","sublocality","sublocality_level_2"]},{"types":["locality","political"],"short_name":"Ise","long_name":"Ise"},{"long_name":"Mie","types":["administrative_area_level_1","political"],"short_name":"Mie"},{"long_name":"Japan","types":["country","political"],"short_name":"JP"},{"short_name":"516-0023","long_name":"516-0023","types":["postal_code"]},{"types":["latitude"],"long_name":34.4550038,"short_name":34.4550038},{"types":["longitude"],"long_name":136.7254738,"short_name":136.7254738}]} | J9: =GOOGLEMAPS_GET_ADDRESS_COMPONENTS_STRING(F9,false) -> [{"long_name":"1","short_name":"1","types":["premise"]},{"types":["political","sublocality","sublocality_level_2"],"short_name":"Ujitachichō","long_name":"Ujitachichō"},{"types":["locality","political"],"long_name":"Ise","short_name":"Ise"},{"types":["administrative_area_level_1","political"],"short_name":"Mie","long_name":"Mie"},{"long_name":"Japan","types":["country","political"],"short_name":"JP"},{"long_name":"516-0023","types":["postal_code"],"short_name":"516-0023"},{"long_name":"1","short_name":"1","types":["premise"]},{"long_name":"Ujitachichō","short_name":"Ujitachichō","types":["political","sublocality","sublocality_level_2"]},{"types":["locality","political"],"short_name":"Ise","long_name":"Ise"},{"long_name":"Mie","types":["administrative_area_level_1","political"],"short_name":"Mie"},{"long_name":"Japan","types":["country","political"],"short_name":"JP"},{"short_name":"516-0023","long_name":"516-0023","types":["postal_code"]},{"types":["latitude"],"long_name":34.4550038,"short_name":34.4550038},{"types":["longitude"],"long_name":136.7254738,"short_name":136.7254738},{"types":["debug_info","cache_load_result"],"long_name":"hit","short_name":"hit"}] | K9: =NOT(AND(NOT(_xlfn.ISFORMULA(P9)),AND(NOT(_xlfn.ISFORMULA(Q9)),AND(NOT(_xlfn.ISFORMULA(R9)),AND(NOT(_xlfn.ISFORMULA(S9)),AND(NOT(_xlfn.ISFORMULA(T9)),AND(NOT(_xlfn.ISFORMULA(U9)),AND(NOT(_xlfn.ISFORMULA(V9)),AND(NOT(_xlfn.ISFORMULA(N9)),NOT(_xlfn.ISFORMULA(O9))))))))))) -> FALSE | L9: =iferror(SEARCH(P9,F9),-1)>=0 -> TRUE | M9: TRUE | N9: 34.45501 | O9: 136.72579 | P9: Ise | Q9: Mie | R9: 516-0023 | S9: Japan | T9: Not Driveable | U9: Not Driveable | V9: 4960.38 | X9: =if(W9="YES","UNKNOWN","N/A") -> N/A | Z9: N/A | AB9: https://magazine.lensvid.com/article/fb/1318327108/mysterious-places-in-the-world-that-are-off-limits-to-everyone-and-why/
A10: 7 - Bucket List | B10: Paris Catacombs | C10: The majority of the Catacombs of Paris is off-limits to the public | D10: Originally built as a tunnel network to consolidate the French capital’s ancient mines, the Catacombs of Paris are underground ossuaries that hold the remains of over six million people. A small section of these tunnels is open to the general public, but the majority of the 170-mile-long maze is closed off to prevent visitors from getting lost. | E10: 3 – Accessible – Tour Guide Required | F10: Paris Catacombs | G10: =HYPERLINK(CONCAT("https://www.google.com/maps/search/",F10),"Link") -> Link | I10: =getCacheString(concat("GMPD|",F10)) -> {"address_components":[{"long_name":"1","types":["street_number"],"short_name":"1"},{"types":["route"],"short_name":"Av. du Colonel Henri Rol-Tanguy","long_name":"Avenue du Colonel Henri Rol-Tanguy"},{"long_name":"Paris","types":["locality","political"],"short_name":"Paris"},{"types":["administrative_area_level_2","political"],"short_name":"Paris","long_name":"Paris"},{"long_name":"Île-de-France","short_name":"IDF","types":["administrative_area_level_1","political"]},{"long_name":"France","types":["country","political"],"short_name":"FR"},{"short_name":"75014","types":["postal_code"],"long_name":"75014"},{"types":["street_number"],"long_name":"3","short_name":"3"},{"short_name":"Av. du Colonel Henri Rol-Tanguy","types":["route"],"long_name":"Avenue du Colonel Henri Rol-Tanguy"},{"short_name":"Paris","long_name":"Paris","types":["locality","political"]},{"short_name":"Paris","long_name":"Paris","types":["administrative_area_level_2","political"]},{"short_name":"IDF","types":["administrative_area_level_1","political"],"long_name":"Île-de-France"},{"long_name":"France","types":["country","political"],"short_name":"FR"},{"types":["postal_code"],"short_name":"75014","long_name":"75014"},{"types":["latitude"],"long_name":48.8338325,"short_name":48.8338325},{"types":["longitude"],"long_name":2.3324222,"short_name":2.3324222}]} | J10: =GOOGLEMAPS_GET_ADDRESS_COMPONENTS_STRING(F10,false) -> [{"long_name":"1","types":["street_number"],"short_name":"1"},{"types":["route"],"short_name":"Av. du Colonel Henri Rol-Tanguy","long_name":"Avenue du Colonel Henri Rol-Tanguy"},{"long_name":"Paris","types":["locality","political"],"short_name":"Paris"},{"types":["administrative_area_level_2","political"],"short_name":"Paris","long_name":"Paris"},{"long_name":"Île-de-France","short_name":"IDF","types":["administrative_area_level_1","political"]},{"long_name":"France","types":["country","political"],"short_name":"FR"},{"short_name":"75014","types":["postal_code"],"long_name":"75014"},{"types":["street_number"],"long_name":"3","short_name":"3"},{"short_name":"Av. du Colonel Henri Rol-Tanguy","types":["route"],"long_name":"Avenue du Colonel Henri Rol-Tanguy"},{"short_name":"Paris","long_name":"Paris","types":["locality","political"]},{"short_name":"Paris","long_name":"Paris","types":["administrative_area_level_2","political"]},{"short_name":"IDF","types":["administrative_area_level_1","political"],"long_name":"Île-de-France"},{"long_name":"France","types":["country","political"],"short_name":"FR"},{"types":["postal_code"],"short_name":"75014","long_name":"75014"},{"types":["latitude"],"long_name":48.8338325,"short_name":48.8338325},{"types":["longitude"],"long_name":2.3324222,"short_name":2.3324222},{"types":["debug_info","cache_load_result"],"long_name":"hit","short_name":"hit"}] | K10: =NOT(AND(NOT(_xlfn.ISFORMULA(P10)),AND(NOT(_xlfn.ISFORMULA(Q10)),AND(NOT(_xlfn.ISFORMULA(R10)),AND(NOT(_xlfn.ISFORMULA(S10)),AND(NOT(_xlfn.ISFORMULA(T10)),AND(NOT(_xlfn.ISFORMULA(U10)),AND(NOT(_xlfn.ISFORMULA(V10)),AND(NOT(_xlfn.ISFORMULA(N10)),NOT(_xlfn.ISFORMULA(O10))))))))))) -> FALSE | L10: =iferror(SEARCH(P10,F10),-1)>=0 -> TRUE | M10: TRUE | N10: 48.833832 | O10: 2.3324222 | P10: Paris | Q10: Île-de-France | R10: 75014 | S10: France | T10: Not Driveable | U10: Not Driveable | V10: 4997.29 | X10: =if(W10="YES","UNKNOWN","N/A") -> N/A | Z10: 43120 | AB10: https://magazine.lensvid.com/article/fb/1318327108/mysterious-places-in-the-world-that-are-off-limits-to-everyone-and-why/
A11: 7 - Bucket List | B11: Svalbard | C11: One of the world’s northernmost inhabited areas with the world's northernmost brewery | E11: 1 – Accessible – Freely | F11: Svalbard, Norway | G11: =HYPERLINK(CONCAT("https://www.google.com/maps/search/",F11),"Link") -> Link | H11: Nature | I11: =getCacheString(concat("GMPD|",F11)) -> {"distance_from":{"mi":{"driving":{"2116 4th Ave, Seattle, WA, 98121":"GOOGLE_MAPS_ERROR_CACHED - No route found!"},"flying":{"2116 4th Ave, Seattle, WA, 98121":3628.238284017051}}},"address_components":[{"types":["administrative_area_level_1","political"],"short_name":"Svalbard","long_name":"Svalbard"},{"types":["country","political"],"long_name":"Svalbard and Jan Mayen","short_name":"SJ"},{"short_name":"","long_name":"Ян-Майен, Шпицберген, Улица Олёшивоская","types":[]},{"types":["country","political"],"long_name":"Svalbard and Jan Mayen","short_name":"SJ"},{"types":["administrative_area_level_1","political"],"short_name":"Svalbard","long_name":"Svalbard"},{"types":["postal_code"],"long_name":"9170","short_name":"9170"},{"types":["latitude"],"long_name":77.8749725,"short_name":77.8749725},{"types":["longitude"],"long_name":20.9751822,"short_name":20.9751822}],"duration_from":{"days":{"driving":{"2116 4th Ave, Seattle, WA, 98121":"GOOGLE_MAPS_ERROR_CACHED - No route found!"}}}} | J11: =GOOGLEMAPS_GET_ADDRESS_COMPONENTS_STRING(F11,false) -> [{"types":["administrative_area_level_1","political"],"short_name":"Svalbard","long_name":"Svalbard"},{"types":["country","political"],"long_name":"Svalbard and Jan Mayen","short_name":"SJ"},{"short_name":"","long_name":"Ян-Майен, Шпицберген, Улица Олёшивоская","types":[]},{"types":["country","political"],"long_name":"Svalbard and Jan Mayen","short_name":"SJ"},{"types":["administrative_area_level_1","political"],"short_name":"Svalbard","long_name":"Svalbard"},{"types":["postal_code"],"long_name":"9170","short_name":"9170"},{"types":["latitude"],"long_name":77.8749725,"short_name":77.8749725},{"types":["longitude"],"long_name":20.9751822,"short_name":20.9751822},{"types":["debug_info","cache_load_result"],"long_name":"hit","short_name":"hit"}] | K11: =NOT(AND(NOT(_xlfn.ISFORMULA(P11)),AND(NOT(_xlfn.ISFORMULA(Q11)),AND(NOT(_xlfn.ISFORMULA(R11)),AND(NOT(_xlfn.ISFORMULA(S11)),AND(NOT(_xlfn.ISFORMULA(T11)),AND(NOT(_xlfn.ISFORMULA(U11)),AND(NOT(_xlfn.ISFORMULA(V11)))))))))) -> TRUE | L11: =iferror(SEARCH(P11,F11),-1)>=0 -> FALSE | M11: TRUE | N11: =GOOGLEMAPS_GET_ADDRESS_LATITUDE(F11,true) -> 77.874972 | O11: =GOOGLEMAPS_GET_ADDRESS_LONGITUDE(F11,true) -> 20.975182 | P11: =GOOGLEMAPS_GET_ADDRESS_CITY(F11,true,false) -> Longyearbyen | Q11: =GOOGLEMAPS_GET_ADDRESS_STATE(F11,true,false) -> Svalbard | R11: =GOOGLEMAPS_GET_ADDRESS_POSTAL_CODE(F11,false,false) -> 9170 | S11: =GOOGLEMAPS_GET_ADDRESS_COUNTRY(F11,true,false) -> Svalbard and Jan Mayen | T11: =IFERROR(GOOGLEMAPS_DISTANCE("2116 4th Ave, Seattle, WA, 98121", F11, "driving")+0,"Not Driveable") -> Not Driveable | U11: =iferror(GOOGLEMAPS_DURATION("2116 4th Ave, Seattle, WA, 98121", F11, "driving")+0,"Not Driveable") -> Not Driveable | V11: =GOOGLEMAPS_DISTANCE("2116 4th Ave, Seattle, WA, 98121", F11, "flying")+0 -> 3628.2383 | X11: =if(W11="YES","UNKNOWN","N/A") -> N/A | Z11: N/A | AA11: Have a beer at the northernmost Brewery and experience remote nature | AE11: Northernmost brewery in the world
A12: 7 - Bucket List | B12: Hotel Bareiss | E12: 1 – Accessible – Freely | F12: Hotel Bareiss, Germany | G12: =HYPERLINK(CONCAT("https://www.google.com/maps/search/",F12),"Link") -> Link | H12: Destination Retreat / Getaway | I12: =getCacheString(concat("GMPD|",F12)) -> {"address_components":[{"short_name":"1","long_name":"1","types":["street_number"]},{"short_name":"Hermine-Bareiss-Weg","long_name":"Hermine-Bareiss-Weg","types":["route"]},{"long_name":"Mitteltal","types":["political","sublocality","sublocality_level_1"],"short_name":"Mitteltal"},{"types":["locality","political"],"long_name":"Baiersbronn","short_name":"Baiersbronn"},{"types":["administrative_area_level_3","political"],"long_name":"Landkreis Freudenstadt","short_name":"FDS"},{"short_name":"KA","long_name":"Karlsruhe","types":["administrative_area_level_2","political"]},{"short_name":"BW","long_name":"Baden-Württemberg","types":["administrative_area_level_1","political"]},{"long_name":"Germany","types":["country","political"],"short_name":"DE"},{"types":["postal_code"],"short_name":"72270","long_name":"72270"},{"long_name":"1","types":["street_number"],"short_name":"1"},{"types":["route"],"long_name":"Hermine-Bareiss-Weg","short_name":"Hermine-Bareiss-Weg"},{"short_name":"Mitteltal","types":["political","sublocality","sublocality_level_1"],"long_name":"Mitteltal"},{"long_name":"Baiersbronn","types":["locality","political"],"short_name":"Baiersbronn"},{"types":["administrative_area_level_3","political"],"long_name":"Landkreis Freudenstadt","short_name":"FDS"},{"long_name":"Karlsruhe","types":["administrative_area_level_2","political"],"short_name":"KA"},{"long_name":"Baden-Württemberg","types":["administrative_area_level_1","political"],"short_name":"BW"},{"short_name":"DE","long_name":"Germany","types":["country","political"]},{"types":["postal_code"],"long_name":"72270","short_name":"72270"},{"types":["latitude"],"long_name":48.5203306,"short_name":48.5203306},{"types":["longitude"],"long_name":8.32685,"short_name":8.32685}]} | J12: =GOOGLEMAPS_GET_ADDRESS_COMPONENTS_STRING(F12,false) -> [{"short_name":"1","long_name":"1","types":["street_number"]},{"short_name":"Hermine-Bareiss-Weg","long_name":"Hermine-Bareiss-Weg","types":["route"]},{"long_name":"Mitteltal","types":["political","sublocality","sublocality_level_1"],"short_name":"Mitteltal"},{"types":["locality","political"],"long_name":"Baiersbronn","short_name":"Baiersbronn"},{"types":["administrative_area_level_3","political"],"long_name":"Landkreis Freudenstadt","short_name":"FDS"},{"short_name":"KA","long_name":"Karlsruhe","types":["administrative_area_level_2","political"]},{"short_name":"BW","long_name":"Baden-Württemberg","types":["administrative_area_level_1","political"]},{"long_name":"Germany","types":["country","political"],"short_name":"DE"},{"types":["postal_code"],"short_name":"72270","long_name":"72270"},{"long_name":"1","types":["street_number"],"short_name":"1"},{"types":["route"],"long_name":"Hermine-Bareiss-Weg","short_name":"Hermine-Bareiss-Weg"},{"short_name":"Mitteltal","types":["political","sublocality","sublocality_level_1"],"long_name":"Mitteltal"},{"long_name":"Baiersbronn","types":["locality","political"],"short_name":"Baiersbronn"},{"types":["administrative_area_level_3","political"],"long_name":"Landkreis Freudenstadt","short_name":"FDS"},{"long_name":"Karlsruhe","types":["administrative_area_level_2","political"],"short_name":"KA"},{"long_name":"Baden-Württemberg","types":["administrative_area_level_1","political"],"short_name":"BW"},{"short_name":"DE","long_name":"Germany","types":["country","political"]},{"types":["postal_code"],"long_name":"72270","short_name":"72270"},{"types":["latitude"],"long_name":48.5203306,"short_name":48.5203306},{"types":["longitude"],"long_name":8.32685,"short_name":8.32685},{"types":["debug_info","cache_load_result"],"long_name":"hit","short_name":"hit"}] | K12: =NOT(AND(NOT(_xlfn.ISFORMULA(P12)),AND(NOT(_xlfn.ISFORMULA(Q12)),AND(NOT(_xlfn.ISFORMULA(R12)),AND(NOT(_xlfn.ISFORMULA(S12)),AND(NOT(_xlfn.ISFORMULA(T12)),AND(NOT(_xlfn.ISFORMULA(U12)),AND(NOT(_xlfn.ISFORMULA(V12)),AND(NOT(_xlfn.ISFORMULA(N12)),NOT(_xlfn.ISFORMULA(O12))))))))))) -> FALSE | L12: =iferror(SEARCH(P12,F12),-1)>=0 -> FALSE | M12: TRUE | N12: 48.520331 | O12: 8.32685 | P12: Baiersbronn | Q12: Baden-Württemberg | R12: 72270 | S12: Germany | T12: Not Driveable | U12: Not Driveable | V12: 5167.37 | X12: =if(W12="YES","UNKNOWN","N/A") -> N/A | Z12: N/A | AB12: https://www.bareiss.com/en/ | AF12: Resort and Spa in the Black Forrest
A13: 7 - Bucket List | B13: Chernobyl Exclusion Zone | C13: Exclusion zone around Chernobyl | E13: 8 – Inaccessible – Military Action / Dispute / Unrest | F13: Chernobyl Exclusion Zone, Belarus | G13: =HYPERLINK(CONCAT("https://www.google.com/maps/search/",F13),"Link") -> Link | H13: Ghost Town | I13: =getCacheString(concat("GMPD|",F13)) -> {"address_components":[{"long_name":"Belarus","short_name":"BY","types":["country","political"]},{"long_name":"PX53+W9","short_name":"PX53+W9","types":["plus_code"]},{"short_name":"Golomberg","long_name":"Golomberg","types":["locality","political"]},{"short_name":"Pukhavichy District","types":["administrative_area_level_2","political"],"long_name":"Pukhavichy District"},{"short_name":"Minsk Region","long_name":"Minsk Region","types":["administrative_area_level_1","political"]},{"long_name":"Belarus","short_name":"BY","types":["country","political"]},{"types":["latitude"],"long_name":53.709807,"short_name":53.709807},{"types":["longitude"],"long_name":27.953389,"short_name":27.953389}],"duration_from":{"days":{"driving":{"2116 4th Ave, Seattle, WA, 98121":"GOOGLE_MAPS_ERROR_CACHED - No route found!"}}},"distance_from":{"mi":{"driving":{"2116 4th Ave, Seattle, WA, 98121":"GOOGLE_MAPS_ERROR_CACHED - No route found!"},"flying":{"2116 4th Ave, Seattle, WA, 98121":5223.046714802342}}}} | J13: =GOOGLEMAPS_GET_ADDRESS_COMPONENTS_STRING(F13,false) -> [{"long_name":"Belarus","short_name":"BY","types":["country","political"]},{"long_name":"PX53+W9","short_name":"PX53+W9","types":["plus_code"]},{"short_name":"Golomberg","long_name":"Golomberg","types":["locality","political"]},{"short_name":"Pukhavichy District","types":["administrative_area_level_2","political"],"long_name":"Pukhavichy District"},{"short_name":"Minsk Region","long_name":"Minsk Region","types":["administrative_area_level_1","political"]},{"long_name":"Belarus","short_name":"BY","types":["country","political"]},{"types":["latitude"],"long_name":53.709807,"short_name":53.709807},{"types":["longitude"],"long_name":27.953389,"short_name":27.953389},{"types":["debug_info","cache_load_result"],"long_name":"hit","short_name":"hit"}] | K13: =NOT(AND(NOT(_xlfn.ISFORMULA(P13)),AND(NOT(_xlfn.ISFORMULA(Q13)),AND(NOT(_xlfn.ISFORMULA(R13)),AND(NOT(_xlfn.ISFORMULA(S13)),AND(NOT(_xlfn.ISFORMULA(T13)),AND(NOT(_xlfn.ISFORMULA(U13)),AND(NOT(_xlfn.ISFORMULA(V13)))))))))) -> TRUE | L13: =iferror(SEARCH(P13,F13),-1)>=0 -> FALSE | M13: TRUE | N13: =GOOGLEMAPS_GET_ADDRESS_LATITUDE(F13,true) -> 53.709807 | O13: =GOOGLEMAPS_GET_ADDRESS_LONGITUDE(F13,true) -> 27.953389 | P13: =GOOGLEMAPS_GET_ADDRESS_CITY(F13,true,false) -> Golomberg | Q13: =GOOGLEMAPS_GET_ADDRESS_STATE(F13,true,false) -> Minsk Region | R13: =GOOGLEMAPS_GET_ADDRESS_POSTAL_CODE(F13,false,false) -> UNDEFINED | S13: =GOOGLEMAPS_GET_ADDRESS_COUNTRY(F13,true,false) -> Belarus | T13: =IFERROR(GOOGLEMAPS_DISTANCE("2116 4th Ave, Seattle, WA, 98121", F13, "driving")+0,"Not Driveable") -> Not Driveable | U13: =iferror(GOOGLEMAPS_DURATION("2116 4th Ave, Seattle, WA, 98121", F13, "driving")+0,"Not Driveable") -> Not Driveable | V13: =GOOGLEMAPS_DISTANCE("2116 4th Ave, Seattle, WA, 98121", F13, "flying")+0 -> 5223.0467 | X13: =if(W13="YES","UNKNOWN","N/A") -> N/A | Z13: N/A | AC13: https://www.youtube.com/watch?v=Qk_gx3CmACY | AD13: https://www.youtube.com/watch?v=sSIlZcEWyqg
A14: 7 - Bucket List | B14: Alsace, France | C14: Alsace is one of the most beautiful regions in France. It is known for its Christmas markets, its castles, its wine road and its proximity to Germany. It is also known for its high-quality gastronomy, especially its sauerkraut, its Flammekueche, and its white wines. | E14: 1 – Accessible – Freely | F14: Alsace, France | G14: =HYPERLINK(CONCAT("https://www.google.com/maps/search/",F14),"Link") -> Link | H14: World Class Cities and Lands | I14: =getCacheString(concat("GMPD|",F14)) -> {"address_components":[{"long_name":"Alsace","short_name":"Alsace","types":["colloquial_area","political"]},{"short_name":"Grand Est","types":["administrative_area_level_1","political"],"long_name":"Grand Est"},{"long_name":"France","types":["country","political"],"short_name":"FR"},{"long_name":"21","types":["street_number"],"short_name":"21"},{"long_name":"Rue des Boutons d'Or","short_name":"Rue des Boutons d'Or","types":["route"]},{"long_name":"Dambach-la-Ville","short_name":"Dambach-la-Ville","types":["locality","political"]},{"types":["administrative_area_level_2","political"],"short_name":"Bas-Rhin","long_name":"Bas-Rhin"},{"long_name":"Grand Est","short_name":"Grand Est","types":["administrative_area_level_1","political"]},{"types":["country","political"],"short_name":"FR","long_name":"France"},{"long_name":"67650","short_name":"67650","types":["postal_code"]},{"types":["latitude"],"long_name":48.3181795,"short_name":48.3181795},{"types":["longitude"],"long_name":7.441624099999999,"short_name":7.441624099999999}],"duration_from":{"days":{"driving":{"2116 4th Ave, Seattle, WA, 98121":"GOOGLE_MAPS_ERROR_CACHED - No route found!"}}},"distance_from":{"mi":{"flying":{"2116 4th Ave, Seattle, WA, 98121":5157.514260504307},"driving":{"2116 4th Ave, Seattle, WA, 98121":"GOOGLE_MAPS_ERROR_CACHED - No route found!"}}}} | J14: =GOOGLEMAPS_GET_ADDRESS_COMPONENTS_STRING(F14,false) -> [{"long_name":"Alsace","short_name":"Alsace","types":["colloquial_area","political"]},{"short_name":"Grand Est","types":["administrative_area_level_1","political"],"long_name":"Grand Est"},{"long_name":"France","types":["country","political"],"short_name":"FR"},{"long_name":"21","types":["street_number"],"short_name":"21"},{"long_name":"Rue des Boutons d'Or","short_name":"Rue des Boutons d'Or","types":["route"]},{"long_name":"Dambach-la-Ville","short_name":"Dambach-la-Ville","types":["locality","political"]},{"types":["administrative_area_level_2","political"],"short_name":"Bas-Rhin","long_name":"Bas-Rhin"},{"long_name":"Grand Est","short_name":"Grand Est","types":["administrative_area_level_1","political"]},{"types":["country","political"],"short_name":"FR","long_name":"France"},{"long_name":"67650","short_name":"67650","types":["postal_code"]},{"types":["latitude"],"long_name":48.3181795,"short_name":48.3181795},{"types":["longitude"],"long_name":7.441624099999999,"short_name":7.441624099999999},{"types":["debug_info","cache_load_result"],"long_name":"hit","short_name":"hit"}] | K14: =NOT(AND(NOT(_xlfn.ISFORMULA(P14)),AND(NOT(_xlfn.ISFORMULA(Q14)),AND(NOT(_xlfn.ISFORMULA(R14)),AND(NOT(_xlfn.ISFORMULA(S14)),AND(NOT(_xlfn.ISFORMULA(T14)),AND(NOT(_xlfn.ISFORMULA(U14)),AND(NOT(_xlfn.ISFORMULA(V14)))))))))) -> TRUE | L14: =iferror(SEARCH(P14,F14),-1)>=0 -> FALSE | M14: TRUE | N14: =GOOGLEMAPS_GET_ADDRESS_LATITUDE(F14,true) -> 48.318179 | O14: =GOOGLEMAPS_GET_ADDRESS_LONGITUDE(F14,true) -> 7.4416241 | P14: =GOOGLEMAPS_GET_ADDRESS_CITY(F14,true,false) -> Dambach-la-Ville | Q14: =GOOGLEMAPS_GET_ADDRESS_STATE(F14,true,false) -> Grand Est | R14: =GOOGLEMAPS_GET_ADDRESS_POSTAL_CODE(F14,false,false) -> 67650 | S14: =GOOGLEMAPS_GET_ADDRESS_COUNTRY(F14,true,false) -> France | T14: =IFERROR(GOOGLEMAPS_DISTANCE("2116 4th Ave, Seattle, WA, 98121", F14, "driving")+0,"Not Driveable") -> Not Driveable | U14: =iferror(GOOGLEMAPS_DURATION("2116 4th Ave, Seattle, WA, 98121", F14, "driving")+0,"Not Driveable") -> Not Driveable | V14: =GOOGLEMAPS_DISTANCE("2116 4th Ave, Seattle, WA, 98121", F14, "flying")+0 -> 5157.5143 | X14: =if(W14="YES","UNKNOWN","N/A") -> N/A | Z14: N/A
A15: 7 - Bucket List | B15: Korean Demilitarized Zone, Korean Peninsula | C15: The Korean Demilitarized Zone is so deadly for humans that it became an involuntary nature reserve | D15: The Korean Demilitarized Zone is a border barrier between North and South Korea. Since it is highly militarized on both sides to prevent people from crossing the border, the DMZ region sees very little human activity, accidentally making it a safe haven for wild animals and migratory birds. | E15: 8 – Inaccessible – Military Action / Dispute / Unrest | F15: Korean Demilitarized Zone, Korean Peninsula | G15: =HYPERLINK(CONCAT("https://www.google.com/maps/search/",F15),"Link") -> Link | I15: =getCacheString(concat("GMPD|",F15)) -> {"address_components":[{"types":["country","political"],"short_name":"KR","long_name":"South Korea"},{"types":["premise"],"long_name":"808-3","short_name":"808-3"},{"long_name":"Samgong-ri","types":["political","sublocality","sublocality_level_3"],"short_name":"Samgong-ri"},{"short_name":"Seolcheon-myeon","long_name":"Seolcheon-myeon","types":["political","sublocality","sublocality_level_2"]},{"short_name":"Muju","long_name":"Muju","types":["locality","political"]},{"long_name":"Jeonbuk State","types":["administrative_area_level_1","political"],"short_name":"Jeonbuk State"},{"short_name":"KR","long_name":"South Korea","types":["country","political"]},{"types":["postal_code"],"long_name":"55557","short_name":"55557"},{"types":["latitude"],"long_name":35.907757,"short_name":35.907757},{"types":["longitude"],"long_name":127.766922,"short_name":127.766922}],"distance_from":{"mi":{"flying":{"2116 4th Ave, Seattle, WA, 98121":5228.674487678179},"driving":{"2116 4th Ave, Seattle, WA, 98121":"GOOGLE_MAPS_ERROR_CACHED - No route found!"}}},"duration_from":{"days":{"driving":{"2116 4th Ave, Seattle, WA, 98121":"GOOGLE_MAPS_ERROR_CACHED - No route found!"}}}} | J15: =GOOGLEMAPS_GET_ADDRESS_COMPONENTS_STRING(F15,false) -> [{"types":["country","political"],"short_name":"KR","long_name":"South Korea"},{"types":["premise"],"long_name":"808-3","short_name":"808-3"},{"long_name":"Samgong-ri","types":["political","sublocality","sublocality_level_3"],"short_name":"Samgong-ri"},{"short_name":"Seolcheon-myeon","long_name":"Seolcheon-myeon","types":["political","sublocality","sublocality_level_2"]},{"short_name":"Muju","long_name":"Muju","types":["locality","political"]},{"long_name":"Jeonbuk State","types":["administrative_area_level_1","political"],"short_name":"Jeonbuk State"},{"short_name":"KR","long_name":"South Korea","types":["country","political"]},{"types":["postal_code"],"long_name":"55557","short_name":"55557"},{"types":["latitude"],"long_name":35.907757,"short_name":35.907757},{"types":["longitude"],"long_name":127.766922,"short_name":127.766922},{"types":["debug_info","cache_load_result"],"long_name":"hit","short_name":"hit"}] | K15: =NOT(AND(NOT(_xlfn.ISFORMULA(P15)),AND(NOT(_xlfn.ISFORMULA(Q15)),AND(NOT(_xlfn.ISFORMULA(R15)),AND(NOT(_xlfn.ISFORMULA(S15)),AND(NOT(_xlfn.ISFORMULA(T15)),AND(NOT(_xlfn.ISFORMULA(U15)),AND(NOT(_xlfn.ISFORMULA(V15)))))))))) -> TRUE | L15: =iferror(SEARCH(P15,F15),-1)>=0 -> FALSE | M15: TRUE | N15: =GOOGLEMAPS_GET_ADDRESS_LATITUDE(F15,true) -> 35.907757 | O15: =GOOGLEMAPS_GET_ADDRESS_LONGITUDE(F15,true) -> 127.76692 | P15: =GOOGLEMAPS_GET_ADDRESS_CITY(F15,true,false) -> Muju | Q15: =GOOGLEMAPS_GET_ADDRESS_STATE(F15,true,false) -> Jeonbuk State | R15: =GOOGLEMAPS_GET_ADDRESS_POSTAL_CODE(F15,false,false) -> 55557 | S15: =GOOGLEMAPS_GET_ADDRESS_COUNTRY(F15,true,false) -> South Korea | T15: =IFERROR(GOOGLEMAPS_DISTANCE("2116 4th Ave, Seattle, WA, 98121", F15, "driving")+0,"Not Driveable") -> Not Driveable | U15: =iferror(GOOGLEMAPS_DURATION("2116 4th Ave, Seattle, WA, 98121", F15, "driving")+0,"Not Driveable") -> Not Driveable | V15: =GOOGLEMAPS_DISTANCE("2116 4th Ave, Seattle, WA, 98121", F15, "flying")+0 -> 5228.6745 | X15: =if(W15="YES","UNKNOWN","N/A") -> N/A | Z15: N/A | AB15: https://magazine.lensvid.com/article/fb/1318327108/mysterious-places-in-the-world-that-are-off-limits-to-everyone-and-why/
A16: 7 - Bucket List | B16: Hashima Island | D16: FEW PLACES IN THE WORLD have a history as odd, or as poignant as Gunkanjima’s. The tiny, fortress-like island (also known as “Hashima” or “Battleship Island”) lies just off the coast of Nagasaki. The island is ringed by a seawall, covered in tightly packed buildings, and entirely abandoned - a ghost town that has been completely uninhabited for more than forty years. In the early 1900s, Gunkanjima was developed by the Mitsubishi Corporation, which believed - correctly - that the island was sitting on a rich submarine coal deposit. For almost the next hundred years, the mine grew deeper and longer, stretching out under the seabed to harvest the coal that was powering Japan’s industrial expansion. By 1941, the island, less than one square kilometer in area, was producing 400,000 tonnes of coal per year. And many of those working slavishly in the undersea mine were forced laborers from Korea. Even more remarkable than the mine was the city that had grown up around it. To accommodate the miners, ten-story apartment complexes were built up on the tiny rock - a high-rise maze linked together by courtyards, corridors, and stairs. There were schools, restaurants, and gaming houses, all encircled by the protective seawall. The island became known as “Midori nashi Shima,” the island without green. Amazingly, by the mid-1950s, it housed almost six thousand people, giving it the highest population density the world has ever known. And then the coal ran out. Mitsubishi closed the mine, everyone left, and this island city was abandoned, left to revert back to nature. The apartments began to crumble, and for the first time, in the barren courtyards, green things started to grow. Broken glass and old newspapers blew over the streets. The sea-breeze whistled through the windows. Now, fifty years later, the island is exactly as it was just after Mitsubishi left. A ghost town in the middle of the sea. From 1974 to 2009, the island was officially closed to all visitors, but recently the intriguing site has been re-opened to organized tours. The site was approved for inclusion on the UNESCO World Heritage list on July 5, 2015. | E16: 3 – Accessible – Tour Guide Required | F16: Hashima Island, Japan | G16: =HYPERLINK(CONCAT("https://www.google.com/maps/search/",F16),"Link") -> Link | H16: Ghost Town | I16: =getCacheString(concat("GMPD|",F16)) -> {"address_components":[{"long_name":"Hashima Island","short_name":"Hashima Island","types":["establishment","natural_feature"]},{"long_name":"Takashimamachi","short_name":"Takashimamachi","types":["political","sublocality","sublocality_level_2"]},{"short_name":"Nagasaki","types":["locality","political"],"long_name":"Nagasaki"},{"short_name":"Nagasaki","types":["administrative_area_level_1","political"],"long_name":"Nagasaki"},{"short_name":"JP","types":["country","political"],"long_name":"Japan"},{"types":["postal_code"],"long_name":"851-1315","short_name":"851-1315"},{"long_name":"2","short_name":"2","types":["premise"]},{"types":["political","sublocality","sublocality_level_2"],"long_name":"Takashimamachi","short_name":"Takashimamachi"},{"long_name":"Nagasaki","types":["locality","political"],"short_name":"Nagasaki"},{"short_name":"Nagasaki","types":["administrative_area_level_1","political"],"long_name":"Nagasaki"},{"long_name":"Japan","short_name":"JP","types":["country","political"]},{"long_name":"851-1315","short_name":"851-1315","types":["postal_code"]},{"types":["latitude"],"long_name":32.6276331,"short_name":32.6276331},{"types":["longitude"],"long_name":129.7385256,"short_name":129.7385256}],"distance_from":{"mi":{"flying":{"2116 4th Ave, Seattle, WA, 98121":5325.824250935167},"driving":{"2116 4th Ave, Seattle, WA, 98121":"GOOGLE_MAPS_ERROR_CACHED - No route found!"}}},"duration_from":{"days":{"driving":{"2116 4th Ave, Seattle, WA, 98121":"GOOGLE_MAPS_ERROR_CACHED - No route found!"}}}} | J16: =GOOGLEMAPS_GET_ADDRESS_COMPONENTS_STRING(F16,false) -> [{"long_name":"Hashima Island","short_name":"Hashima Island","types":["establishment","natural_feature"]},{"long_name":"Takashimamachi","short_name":"Takashimamachi","types":["political","sublocality","sublocality_level_2"]},{"short_name":"Nagasaki","types":["locality","political"],"long_name":"Nagasaki"},{"short_name":"Nagasaki","types":["administrative_area_level_1","political"],"long_name":"Nagasaki"},{"short_name":"JP","types":["country","political"],"long_name":"Japan"},{"types":["postal_code"],"long_name":"851-1315","short_name":"851-1315"},{"long_name":"2","short_name":"2","types":["premise"]},{"types":["political","sublocality","sublocality_level_2"],"long_name":"Takashimamachi","short_name":"Takashimamachi"},{"long_name":"Nagasaki","types":["locality","political"],"short_name":"Nagasaki"},{"short_name":"Nagasaki","types":["administrative_area_level_1","political"],"long_name":"Nagasaki"},{"long_name":"Japan","short_name":"JP","types":["country","political"]},{"long_name":"851-1315","short_name":"851-1315","types":["postal_code"]},{"types":["latitude"],"long_name":32.6276331,"short_name":32.6276331},{"types":["longitude"],"long_name":129.7385256,"short_name":129.7385256},{"types":["debug_info","cache_load_result"],"long_name":"hit","short_name":"hit"}] | K16: =NOT(AND(NOT(_xlfn.ISFORMULA(P16)),AND(NOT(_xlfn.ISFORMULA(Q16)),AND(NOT(_xlfn.ISFORMULA(R16)),AND(NOT(_xlfn.ISFORMULA(S16)),AND(NOT(_xlfn.ISFORMULA(T16)),AND(NOT(_xlfn.ISFORMULA(U16)),AND(NOT(_xlfn.ISFORMULA(V16)))))))))) -> TRUE | L16: =iferror(SEARCH(P16,F16),-1)>=0 -> FALSE | M16: TRUE | N16: =GOOGLEMAPS_GET_ADDRESS_LATITUDE(F16,true) -> 32.627633 | O16: =GOOGLEMAPS_GET_ADDRESS_LONGITUDE(F16,true) -> 129.73853 | P16: =GOOGLEMAPS_GET_ADDRESS_CITY(F16,true,false) -> Nagasaki | Q16: =GOOGLEMAPS_GET_ADDRESS_STATE(F16,true,false) -> Nagasaki | R16: =GOOGLEMAPS_GET_ADDRESS_POSTAL_CODE(F16,false,false) -> 851-1315 | S16: =GOOGLEMAPS_GET_ADDRESS_COUNTRY(F16,true,false) -> Japan | T16: =IFERROR(GOOGLEMAPS_DISTANCE("2116 4th Ave, Seattle, WA, 98121", F16, "driving")+0,"Not Driveable") -> Not Driveable | U16: =iferror(GOOGLEMAPS_DURATION("2116 4th Ave, Seattle, WA, 98121", F16, "driving")+0,"Not Driveable") -> Not Driveable | V16: =GOOGLEMAPS_DISTANCE("2116 4th Ave, Seattle, WA, 98121", F16, "flying")+0 -> 5325.8243 | X16: =if(W16="YES","UNKNOWN","N/A") -> N/A | Z16: N/A | AB16: https://www.atlasobscura.com/places/gubkanjima-island | AF16: Eerie sightseeing spot Hashima Island is an abandoned offshore mining facility, also known as Gunkanjima or Battleship Island. Visitors tour its overgrown industrial sites, semi-ruined concrete workers’ quarters, and so-called “stairway to hell.” There’s a quiet Shinto shrine at the center and views across the East China Sea from atop the perimeter wall. The James Bond film “Skyfall” was partly set on the island.
A17: 7 - Bucket List | B17: Pripyat, Ukraine | C17: Ghost town outside of Chernobyl | E17: 8 – Inaccessible – Military Action / Dispute / Unrest | F17: Pripyat, Ukraine | G17: =HYPERLINK(CONCAT("https://www.google.com/maps/search/",F17),"Link") -> Link | H17: Ghost Town | I17: =getCacheString(concat("GMPD|",F17)) -> {"address_components":[{"types":["locality","political"],"long_name":"Pryp'yat'","short_name":"Pryp'yat'"},{"types":["administrative_area_level_2","political"],"long_name":"Ivankivs'kyi district","short_name":"Ivankivs'kyi district"},{"types":["administrative_area_level_1","political"],"long_name":"Kyiv Oblast","short_name":"Kyiv Oblast"},{"short_name":"UA","types":["country","political"],"long_name":"Ukraine"},{"short_name":"1/14","long_name":"1/14","types":["street_number"]},{"short_name":"Serzhanta Lazarieva St","long_name":"Serzhanta Lazarieva Street","types":["route"]},{"types":["locality","political"],"short_name":"Pryp'yat'","long_name":"Pryp'yat'"},{"long_name":"Ivankivs'kyi district","short_name":"Ivankivs'kyi district","types":["administrative_area_level_2","political"]},{"short_name":"Kyivs'ka oblast","long_name":"Kyivs'ka oblast","types":["administrative_area_level_1","political"]},{"types":["country","political"],"long_name":"Ukraine","short_name":"UA"},{"types":["latitude"],"long_name":51.40450320000001,"short_name":51.40450320000001},{"types":["longitude"],"long_name":30.0542331,"short_name":30.0542331}],"duration_from":{"days":{"driving":{"2116 4th Ave, Seattle, WA, 98121":"GOOGLE_MAPS_ERROR_CACHED - No route found!"}}},"distance_from":{"mi":{"flying":{"2116 4th Ave, Seattle, WA, 98121":5402.573725875204},"driving":{"2116 4th Ave, Seattle, WA, 98121":"GOOGLE_MAPS_ERROR_CACHED - No route found!"}}}} | J17: =GOOGLEMAPS_GET_ADDRESS_COMPONENTS_STRING(F17,false) -> [{"types":["locality","political"],"long_name":"Pryp'yat'","short_name":"Pryp'yat'"},{"types":["administrative_area_level_2","political"],"long_name":"Ivankivs'kyi district","short_name":"Ivankivs'kyi district"},{"types":["administrative_area_level_1","political"],"long_name":"Kyiv Oblast","short_name":"Kyiv Oblast"},{"short_name":"UA","types":["country","political"],"long_name":"Ukraine"},{"short_name":"1/14","long_name":"1/14","types":["street_number"]},{"short_name":"Serzhanta Lazarieva St","long_name":"Serzhanta Lazarieva Street","types":["route"]},{"types":["locality","political"],"short_name":"Pryp'yat'","long_name":"Pryp'yat'"},{"long_name":"Ivankivs'kyi district","short_name":"Ivankivs'kyi district","types":["administrative_area_level_2","political"]},{"short_name":"Kyivs'ka oblast","long_name":"Kyivs'ka oblast","types":["administrative_area_level_1","political"]},{"types":["country","political"],"long_name":"Ukraine","short_name":"UA"},{"types":["latitude"],"long_name":51.40450320000001,"short_name":51.40450320000001},{"types":["longitude"],"long_name":30.0542331,"short_name":30.0542331},{"types":["debug_info","cache_load_result"],"long_name":"hit","short_name":"hit"}] | K17: =NOT(AND(NOT(_xlfn.ISFORMULA(P17)),AND(NOT(_xlfn.ISFORMULA(Q17)),AND(NOT(_xlfn.ISFORMULA(R17)),AND(NOT(_xlfn.ISFORMULA(S17)),AND(NOT(_xlfn.ISFORMULA(T17)),AND(NOT(_xlfn.ISFORMULA(U17)),AND(NOT(_xlfn.ISFORMULA(V17)))))))))) -> TRUE | L17: =iferror(SEARCH(P17,F17),-1)>=0 -> FALSE | M17: TRUE | N17: =GOOGLEMAPS_GET_ADDRESS_LATITUDE(F17,true) -> 51.404503 | O17: =GOOGLEMAPS_GET_ADDRESS_LONGITUDE(F17,true) -> 30.054233 | P17: =GOOGLEMAPS_GET_ADDRESS_CITY(F17,true,false) -> Pryp'yat' | Q17: =GOOGLEMAPS_GET_ADDRESS_STATE(F17,true,false) -> Kyiv Oblast | R17: =GOOGLEMAPS_GET_ADDRESS_POSTAL_CODE(F17,false,false) -> UNDEFINED | S17: =GOOGLEMAPS_GET_ADDRESS_COUNTRY(F17,true,false) -> Ukraine | T17: =IFERROR(GOOGLEMAPS_DISTANCE("2116 4th Ave, Seattle, WA, 98121", F17, "driving")+0,"Not Driveable") -> Not Driveable | U17: =iferror(GOOGLEMAPS_DURATION("2116 4th Ave, Seattle, WA, 98121", F17, "driving")+0,"Not Driveable") -> Not Driveable | V17: =GOOGLEMAPS_DISTANCE("2116 4th Ave, Seattle, WA, 98121", F17, "flying")+0 -> 5402.5737 | X17: =if(W17="YES","UNKNOWN","N/A") -> N/A | Z17: N/A | AB17: https://www.youtube.com/watch?v=sSIlZcEWyqg | AF17: Arguably the world’s most infamous ghost town, Pripyat is packed with poignant sights. Mundane artefacts litter its homes, schools, offices and parks, telling of a carefree time just before the devastating Chernobyl disaster turned the community (and the wider world) upside down. Built to house the plant’s scientists and workers, Pripyat has been abandoned since its residents were evacuated 36 hours after the catastrophic meltdown took place in the Soviet power plant in 1986. Due to the radiation all their possessions had to be left behind. Set within the inner nuclear disaster zone, Pripyat's eerie buildings and empty streets were cordoned off from the world until recently. Nature has reclaimed much of the radioactive place: trees have grown unhindered, creeping through into the communist blocks, wildflowers bloom in the spring, and wild animals roam unhindered, including a team of horses that thrived after a few were released into the area to see if animals could survive. The Ukrainian government designated Chernobyl an official tourist attraction in 2019 after the exclusion zone was deemed safe to visit for tourists. Access is still strictly regulated by the government and can only be explored on guided tours. Haunting sights include the deserted school, where books and paper lie scattered on the floor of the classrooms, and a decaying amusement park. The Ferris wheel is a moving symbol of joy extinguished – it was supposed to open four days after the explosion, but never welcomed any guests. See more eerie images of abandoned amusement parks around the world.
A18: 7 - Bucket List | B18: Trinity Site | C18: Home of the first atom bomb test | E18: 3 – Accessible – Tour Guide Required | F18: Trinity Site | G18: =HYPERLINK(CONCAT("https://www.google.com/maps/search/",F18),"Link") -> Link | H18: Military and Heavy Industry | I18: =getCacheString(concat("GMPD|",F18)) -> {"address_components":[{"long_name":"New Mexico","short_name":"NM","types":["administrative_area_level_1","political"]},{"types":["administrative_area_level_2","political"],"long_name":"Socorro County","short_name":"Socorro County"},{"long_name":"United States","short_name":"US","types":["country","political"]},{"long_name":"87102","types":["postal_code"],"short_name":"87102"},{"types":["plus_code"],"long_name":"855MMGGF+WR","short_name":"855MMGGF+WR"},{"types":["latitude"],"long_name":33.677333,"short_name":33.677333},{"types":["longitude"],"long_name":-106.4754025,"short_name":-106.4754025}]} | J18: =GOOGLEMAPS_GET_ADDRESS_COMPONENTS_STRING(F18,false) -> [{"long_name":"New Mexico","short_name":"NM","types":["administrative_area_level_1","political"]},{"types":["administrative_area_level_2","political"],"long_name":"Socorro County","short_name":"Socorro County"},{"long_name":"United States","short_name":"US","types":["country","political"]},{"long_name":"87102","types":["postal_code"],"short_name":"87102"},{"types":["plus_code"],"long_name":"855MMGGF+WR","short_name":"855MMGGF+WR"},{"types":["latitude"],"long_name":33.677333,"short_name":33.677333},{"types":["longitude"],"long_name":-106.4754025,"short_name":-106.4754025},{"types":["debug_info","cache_load_result"],"long_name":"hit","short_name":"hit"}] | K18: =NOT(AND(NOT(_xlfn.ISFORMULA(P18)),AND(NOT(_xlfn.ISFORMULA(Q18)),AND(NOT(_xlfn.ISFORMULA(R18)),AND(NOT(_xlfn.ISFORMULA(S18)),AND(NOT(_xlfn.ISFORMULA(T18)),AND(NOT(_xlfn.ISFORMULA(U18)),AND(NOT(_xlfn.ISFORMULA(V18)),AND(NOT(_xlfn.ISFORMULA(N18)),NOT(_xlfn.ISFORMULA(O18))))))))))) -> FALSE | L18: =iferror(SEARCH(P18,F18),-1)>=0 -> FALSE | M18: TRUE | N18: 33.677293 | O18: -106.47529 | P18: Albuquerque | Q18: New Mexico | R18: 87102 | S18: United States | T18: 1554.2 | U18: 1.0245139 | V18: 1267.39 | X18: =if(W18="YES","UNKNOWN","N/A") -> N/A | Z18: N/A
A19: 7 - Bucket List | B19: Baikonur Cosmodrome | E19: 3 – Accessible – Tour Guide Required | F19: Baikonur Cosmodrome, Kazakhstan | G19: =HYPERLINK(CONCAT("https://www.google.com/maps/search/",F19),"Link") -> Link | H19: Military and Heavy Industry | I19: =getCacheString(concat("GMPD|",F19)) -> {"address_components":[{"short_name":"","types":[],"long_name":"Kazakhstan"},{"short_name":"KZ","long_name":"Kazakhstan","types":["country","political"]},{"short_name":"Қармақшы ауданы","types":["administrative_area_level_2","political"],"long_name":"Қармақшы ауданы"},{"long_name":"Қызылорда облысы","short_name":"Қызылорда облысы","types":["administrative_area_level_1","political"]},{"short_name":"KZ","long_name":"Kazakhstan","types":["country","political"]},{"short_name":"Қармақшы ауданы","types":["administrative_area_level_2","political"],"long_name":"Қармақшы ауданы"},{"long_name":"Қызылорда облысы","short_name":"Қызылорда облысы","types":["administrative_area_level_1","political"]},{"types":["latitude"],"long_name":45.9645851,"short_name":45.9645851},{"types":["longitude"],"long_name":63.30524269999999,"short_name":63.30524269999999}],"distance_from":{"mi":{"flying":{"2116 4th Ave, Seattle, WA, 98121":5962.106826400885},"driving":{"2116 4th Ave, Seattle, WA, 98121":"GOOGLE_MAPS_ERROR_CACHED - No route found!"}}},"duration_from":{"days":{"driving":{"2116 4th Ave, Seattle, WA, 98121":"GOOGLE_MAPS_ERROR_CACHED - No route found!"}}}} | J19: =GOOGLEMAPS_GET_ADDRESS_COMPONENTS_STRING(F19,false) -> [{"short_name":"","types":[],"long_name":"Kazakhstan"},{"short_name":"KZ","long_name":"Kazakhstan","types":["country","political"]},{"short_name":"Қармақшы ауданы","types":["administrative_area_level_2","political"],"long_name":"Қармақшы ауданы"},{"long_name":"Қызылорда облысы","short_name":"Қызылорда облысы","types":["administrative_area_level_1","political"]},{"short_name":"KZ","long_name":"Kazakhstan","types":["country","political"]},{"short_name":"Қармақшы ауданы","types":["administrative_area_level_2","political"],"long_name":"Қармақшы ауданы"},{"long_name":"Қызылорда облысы","short_name":"Қызылорда облысы","types":["administrative_area_level_1","political"]},{"types":["latitude"],"long_name":45.9645851,"short_name":45.9645851},{"types":["longitude"],"long_name":63.30524269999999,"short_name":63.30524269999999},{"types":["debug_info","cache_load_result"],"long_name":"hit","short_name":"hit"}] | K19: =NOT(AND(NOT(_xlfn.ISFORMULA(P19)),AND(NOT(_xlfn.ISFORMULA(Q19)),AND(NOT(_xlfn.ISFORMULA(R19)),AND(NOT(_xlfn.ISFORMULA(S19)),AND(NOT(_xlfn.ISFORMULA(T19)),AND(NOT(_xlfn.ISFORMULA(U19)),AND(NOT(_xlfn.ISFORMULA(V19)))))))))) -> TRUE | L19: =iferror(SEARCH(P19,F19),-1)>=0 -> FALSE | M19: TRUE | N19: =GOOGLEMAPS_GET_ADDRESS_LATITUDE(F19,true) -> 45.964585 | O19: =GOOGLEMAPS_GET_ADDRESS_LONGITUDE(F19,true) -> 63.305243 | P19: =GOOGLEMAPS_GET_ADDRESS_CITY(F19,true,false) -> UNDEFINED | Q19: =GOOGLEMAPS_GET_ADDRESS_STATE(F19,true,false) -> Қызылорда облысы | R19: =GOOGLEMAPS_GET_ADDRESS_POSTAL_CODE(F19,false,false) -> UNDEFINED | S19: =GOOGLEMAPS_GET_ADDRESS_COUNTRY(F19,true,false) -> Kazakhstan | T19: =IFERROR(GOOGLEMAPS_DISTANCE("2116 4th Ave, Seattle, WA, 98121", F19, "driving")+0,"Not Driveable") -> Not Driveable | U19: =iferror(GOOGLEMAPS_DURATION("2116 4th Ave, Seattle, WA, 98121", F19, "driving")+0,"Not Driveable") -> Not Driveable | V19: =GOOGLEMAPS_DISTANCE("2116 4th Ave, Seattle, WA, 98121", F19, "flying")+0 -> 5962.1068 | X19: =if(W19="YES","UNKNOWN","N/A") -> N/A | Z19: N/A
A20: 7 - Bucket List | B20: Cross the Gobi Desert | E20: 1 – Accessible – Freely | F20: Gobi Desert, Mongolia | G20: =HYPERLINK(CONCAT("https://www.google.com/maps/search/",F20),"Link") -> Link | H20: Nature | I20: =getCacheString(concat("GMPD|",F20)) -> {"address_components":[{"types":["establishment","natural_feature"],"long_name":"Gobi Desert","short_name":"Gobi Desert"},{"long_name":"Q2WJ+3W","short_name":"Q2WJ+3W","types":["plus_code"]},{"long_name":"Nomgon","types":["locality","political"],"short_name":"Nomgon"},{"long_name":"Nomgon","short_name":"Nomgon","types":["administrative_area_level_2","political"]},{"types":["administrative_area_level_1","political"],"short_name":"Ömnögovi","long_name":"Ömnögovi"},{"long_name":"Mongolia","types":["country","political"],"short_name":"MN"},{"types":["latitude"],"long_name":42.7951536,"short_name":42.7951536},{"types":["longitude"],"long_name":105.0323635,"short_name":105.0323635}]} | J20: =GOOGLEMAPS_GET_ADDRESS_COMPONENTS_STRING(F20,false) -> [{"types":["establishment","natural_feature"],"long_name":"Gobi Desert","short_name":"Gobi Desert"},{"long_name":"Q2WJ+3W","short_name":"Q2WJ+3W","types":["plus_code"]},{"long_name":"Nomgon","types":["locality","political"],"short_name":"Nomgon"},{"long_name":"Nomgon","short_name":"Nomgon","types":["administrative_area_level_2","political"]},{"types":["administrative_area_level_1","political"],"short_name":"Ömnögovi","long_name":"Ömnögovi"},{"long_name":"Mongolia","types":["country","political"],"short_name":"MN"},{"types":["latitude"],"long_name":42.7951536,"short_name":42.7951536},{"types":["longitude"],"long_name":105.0323635,"short_name":105.0323635},{"types":["debug_info","cache_load_result"],"long_name":"hit","short_name":"hit"}] | K20: =NOT(AND(NOT(_xlfn.ISFORMULA(P20)),AND(NOT(_xlfn.ISFORMULA(Q20)),AND(NOT(_xlfn.ISFORMULA(R20)),AND(NOT(_xlfn.ISFORMULA(S20)),AND(NOT(_xlfn.ISFORMULA(T20)),AND(NOT(_xlfn.ISFORMULA(U20)),AND(NOT(_xlfn.ISFORMULA(V20)),AND(NOT(_xlfn.ISFORMULA(N20)),NOT(_xlfn.ISFORMULA(O20))))))))))) -> FALSE | L20: =iferror(SEARCH(P20,F20),-1)>=0 -> FALSE | M20: TRUE | N20: 42.795154 | O20: 105.03236 | P20: Nomgon | Q20: Ömnögovi | R20: UNDEFINED | S20: Mongolia | T20: Not Driveable | U20: Not Driveable | V20: 5554.92 | X20: =if(W20="YES","UNKNOWN","N/A") -> N/A | Z20: N/A
A21: 7 - Bucket List | B21: See the Wild Horses of Mongolia | C21: Przewalski's horse, also called the takhi, Mongolian wild horse or Dzungarian horse, is a rare and endangered horse originally native to the steppes of Central Asia | E21: 1 – Accessible – Freely | F21: Gobi Desert, Mongolia | G21: =HYPERLINK(CONCAT("https://www.google.com/maps/search/",F21),"Link") -> Link | H21: Nature | I21: =getCacheString(concat("GMPD|",F21)) -> {"address_components":[{"types":["establishment","natural_feature"],"long_name":"Gobi Desert","short_name":"Gobi Desert"},{"long_name":"Q2WJ+3W","short_name":"Q2WJ+3W","types":["plus_code"]},{"long_name":"Nomgon","types":["locality","political"],"short_name":"Nomgon"},{"long_name":"Nomgon","short_name":"Nomgon","types":["administrative_area_level_2","political"]},{"types":["administrative_area_level_1","political"],"short_name":"Ömnögovi","long_name":"Ömnögovi"},{"long_name":"Mongolia","types":["country","political"],"short_name":"MN"},{"types":["latitude"],"long_name":42.7951536,"short_name":42.7951536},{"types":["longitude"],"long_name":105.0323635,"short_name":105.0323635}]} | J21: =GOOGLEMAPS_GET_ADDRESS_COMPONENTS_STRING(F21,false) -> [{"types":["establishment","natural_feature"],"long_name":"Gobi Desert","short_name":"Gobi Desert"},{"long_name":"Q2WJ+3W","short_name":"Q2WJ+3W","types":["plus_code"]},{"long_name":"Nomgon","types":["locality","political"],"short_name":"Nomgon"},{"long_name":"Nomgon","short_name":"Nomgon","types":["administrative_area_level_2","political"]},{"types":["administrative_area_level_1","political"],"short_name":"Ömnögovi","long_name":"Ömnögovi"},{"long_name":"Mongolia","types":["country","political"],"short_name":"MN"},{"types":["latitude"],"long_name":42.7951536,"short_name":42.7951536},{"types":["longitude"],"long_name":105.0323635,"short_name":105.0323635},{"types":["debug_info","cache_load_result"],"long_name":"hit","short_name":"hit"}] | K21: =NOT(AND(NOT(_xlfn.ISFORMULA(P21)),AND(NOT(_xlfn.ISFORMULA(Q21)),AND(NOT(_xlfn.ISFORMULA(R21)),AND(NOT(_xlfn.ISFORMULA(S21)),AND(NOT(_xlfn.ISFORMULA(T21)),AND(NOT(_xlfn.ISFORMULA(U21)),AND(NOT(_xlfn.ISFORMULA(V21)),AND(NOT(_xlfn.ISFORMULA(N21)),NOT(_xlfn.ISFORMULA(O21))))))))))) -> FALSE | L21: =iferror(SEARCH(P21,F21),-1)>=0 -> FALSE | M21: TRUE | N21: 42.795154 | O21: 105.03236 | P21: Nomgon | Q21: Ömnögovi | R21: UNDEFINED | S21: Mongolia | T21: Not Driveable | U21: Not Driveable | V21: 5554.92 | X21: =if(W21="YES","UNKNOWN","N/A") -> N/A | Z21: N/A
A22: 7 - Bucket List | B22: Attu Station | C22: Station on the end of the Aleutians – one of the only pieces of US land captured by Japan in WWII | E22: 4 – Ambiguous / Unknown – Open | F22: Attu Station, Attu Island, AK | G22: =HYPERLINK(CONCAT("https://www.google.com/maps/search/",F22),"Link") -> Link | H22: Abandoned Building | I22: =getCacheString(concat("GMPD|",F22)) -> {"address_components":[{"long_name":"Attu Station","short_name":"Attu Station","types":["locality","political"]},{"types":["administrative_area_level_2","political"],"short_name":"Aleutians West Census Area","long_name":"Aleutians West Census Area"},{"long_name":"Alaska","types":["administrative_area_level_1","political"],"short_name":"AK"},{"short_name":"US","types":["country","political"],"long_name":"United States"},{"long_name":"Beach Road","short_name":"Beach Rd","types":["route"]},{"long_name":"Attu Station","short_name":"Attu Station","types":["locality","political"]},{"short_name":"Aleutians West Census Area","types":["administrative_area_level_2","political"],"long_name":"Aleutians West Census Area"},{"long_name":"Alaska","types":["administrative_area_level_1","political"],"short_name":"AK"},{"long_name":"United States","short_name":"US","types":["country","political"]},{"types":["latitude"],"long_name":52.8468574,"short_name":52.8468574},{"types":["longitude"],"long_name":173.2011444,"short_name":173.2011444}]} | J22: =GOOGLEMAPS_GET_ADDRESS_COMPONENTS_STRING(F22,false) -> [{"long_name":"Attu Station","short_name":"Attu Station","types":["locality","political"]},{"types":["administrative_area_level_2","political"],"short_name":"Aleutians West Census Area","long_name":"Aleutians West Census Area"},{"long_name":"Alaska","types":["administrative_area_level_1","political"],"short_name":"AK"},{"short_name":"US","types":["country","political"],"long_name":"United States"},{"long_name":"Beach Road","short_name":"Beach Rd","types":["route"]},{"long_name":"Attu Station","short_name":"Attu Station","types":["locality","political"]},{"short_name":"Aleutians West Census Area","types":["administrative_area_level_2","political"],"long_name":"Aleutians West Census Area"},{"long_name":"Alaska","types":["administrative_area_level_1","political"],"short_name":"AK"},{"long_name":"United States","short_name":"US","types":["country","political"]},{"types":["latitude"],"long_name":52.8468574,"short_name":52.8468574},{"types":["longitude"],"long_name":173.2011444,"short_name":173.2011444},{"types":["debug_info","cache_load_result"],"long_name":"hit","short_name":"hit"}] | K22: =NOT(AND(NOT(_xlfn.ISFORMULA(P22)),AND(NOT(_xlfn.ISFORMULA(Q22)),AND(NOT(_xlfn.ISFORMULA(R22)),AND(NOT(_xlfn.ISFORMULA(S22)),AND(NOT(_xlfn.ISFORMULA(T22)),AND(NOT(_xlfn.ISFORMULA(U22)),AND(NOT(_xlfn.ISFORMULA(V22)),AND(NOT(_xlfn.ISFORMULA(N22)),NOT(_xlfn.ISFORMULA(O22))))))))))) -> FALSE | L22: =iferror(SEARCH(P22,F22),-1)>=0 -> TRUE | M22: TRUE | N22: 52.846857 | O22: 173.20114 | P22: Attu Station | Q22: Alaska | R22: UNDEFINED | S22: United States | T22: Not Driveable | U22: Not Driveable | V22: 2774.77 | X22: =if(W22="YES","UNKNOWN","N/A") -> N/A | Z22: N/A
A23: 7 - Bucket List | B23: Mongol Rally | C23: The Mongol Rally is an intercontinental car rally that begins in Europe and ends in Ulan-Ude, Russia | E23: 8 – Inaccessible – Military Action / Dispute / Unrest | F23: Gobi Desert, Mongolia | G23: =HYPERLINK(CONCAT("https://www.google.com/maps/search/",F23),"Link") -> Link | H23: Nature | I23: =getCacheString(concat("GMPD|",F23)) -> {"address_components":[{"types":["establishment","natural_feature"],"long_name":"Gobi Desert","short_name":"Gobi Desert"},{"long_name":"Q2WJ+3W","short_name":"Q2WJ+3W","types":["plus_code"]},{"long_name":"Nomgon","types":["locality","political"],"short_name":"Nomgon"},{"long_name":"Nomgon","short_name":"Nomgon","types":["administrative_area_level_2","political"]},{"types":["administrative_area_level_1","political"],"short_name":"Ömnögovi","long_name":"Ömnögovi"},{"long_name":"Mongolia","types":["country","political"],"short_name":"MN"},{"types":["latitude"],"long_name":42.7951536,"short_name":42.7951536},{"types":["longitude"],"long_name":105.0323635,"short_name":105.0323635}]} | J23: =GOOGLEMAPS_GET_ADDRESS_COMPONENTS_STRING(F23,false) -> [{"types":["establishment","natural_feature"],"long_name":"Gobi Desert","short_name":"Gobi Desert"},{"long_name":"Q2WJ+3W","short_name":"Q2WJ+3W","types":["plus_code"]},{"long_name":"Nomgon","types":["locality","political"],"short_name":"Nomgon"},{"long_name":"Nomgon","short_name":"Nomgon","types":["administrative_area_level_2","political"]},{"types":["administrative_area_level_1","political"],"short_name":"Ömnögovi","long_name":"Ömnögovi"},{"long_name":"Mongolia","types":["country","political"],"short_name":"MN"},{"types":["latitude"],"long_name":42.7951536,"short_name":42.7951536},{"types":["longitude"],"long_name":105.0323635,"short_name":105.0323635},{"types":["debug_info","cache_load_result"],"long_name":"hit","short_name":"hit"}] | K23: =NOT(AND(NOT(_xlfn.ISFORMULA(P23)),AND(NOT(_xlfn.ISFORMULA(Q23)),AND(NOT(_xlfn.ISFORMULA(R23)),AND(NOT(_xlfn.ISFORMULA(S23)),AND(NOT(_xlfn.ISFORMULA(T23)),AND(NOT(_xlfn.ISFORMULA(U23)),AND(NOT(_xlfn.ISFORMULA(V23)),AND(NOT(_xlfn.ISFORMULA(N23)),NOT(_xlfn.ISFORMULA(O23))))))))))) -> FALSE | L23: =iferror(SEARCH(P23,F23),-1)>=0 -> FALSE | M23: TRUE | N23: 42.795154 | O23: 105.03236 | P23: Nomgon | Q23: Ömnögovi | R23: UNDEFINED | S23: Mongolia | T23: Not Driveable | U23: Not Driveable | V23: 5554.92 | X23: =if(W23="YES","UNKNOWN","N/A") -> N/A | Z23: N/A
A24: 7 - Bucket List | B24: The Cheyenne Mountain Complex, United States | C24: The Cheyenne Mountain Complex is known as “America’s Fortress” | D24: Originally used as the center for the United States Space Command and the North American Aerospace Defense Command, the Cheyenne Mountain Complex monitored the North American airspace for missiles, space systems, and foreign aircraft. Nowadays, the complex is an Alternate Command Center for NORAD and serves as a training site for crew qualification. | E24: 7 – Inaccessible – Government Property / Ban | F24: The Cheyenne Mountain Complex, Colorado, USA | G24: =HYPERLINK(CONCAT("https://www.google.com/maps/search/",F24),"Link") -> Link | H24: Military and Heavy Industry | I24: =getCacheString(concat("GMPD|",F24)) -> {"address_components":[{"long_name":"Cheyenne Mountain","short_name":"Cheyenne Mountain","types":["establishment","natural_feature"]},{"long_name":"El Paso County","short_name":"El Paso County","types":["administrative_area_level_2","political"]},{"types":["administrative_area_level_1","political"],"long_name":"Colorado","short_name":"CO"},{"types":["country","political"],"long_name":"United States","short_name":"US"},{"short_name":"80926","types":["postal_code"],"long_name":"80926"},{"long_name":"P4P9+VM","short_name":"P4P9+VM","types":["plus_code"]},{"types":["neighborhood","political"],"short_name":"Rock Creek","long_name":"Rock Creek"},{"short_name":"Colorado Springs","types":["locality","political"],"long_name":"Colorado Springs"},{"short_name":"El Paso County","types":["administrative_area_level_2","political"],"long_name":"El Paso County"},{"long_name":"Colorado","short_name":"CO","types":["administrative_area_level_1","political"]},{"long_name":"United States","short_name":"US","types":["country","political"]},{"types":["latitude"],"long_name":38.7372129,"short_name":38.7372129},{"types":["longitude"],"long_name":-104.8808063,"short_name":-104.8808063}],"distance_from":{"mi":{"flying":{"2116 4th Ave, Seattle, WA, 98121":1068.55108305268},"driving":{"2116 4th Ave, Seattle, WA, 98121":1389.0159941342415}}},"duration_from":{"days":{"driving":{"2116 4th Ave, Seattle, WA, 98121":0.8811342592592593}}}} | J24: =GOOGLEMAPS_GET_ADDRESS_COMPONENTS_STRING(F24,false) -> [{"long_name":"Cheyenne Mountain","short_name":"Cheyenne Mountain","types":["establishment","natural_feature"]},{"long_name":"El Paso County","short_name":"El Paso County","types":["administrative_area_level_2","political"]},{"types":["administrative_area_level_1","political"],"long_name":"Colorado","short_name":"CO"},{"types":["country","political"],"long_name":"United States","short_name":"US"},{"short_name":"80926","types":["postal_code"],"long_name":"80926"},{"long_name":"P4P9+VM","short_name":"P4P9+VM","types":["plus_code"]},{"types":["neighborhood","political"],"short_name":"Rock Creek","long_name":"Rock Creek"},{"short_name":"Colorado Springs","types":["locality","political"],"long_name":"Colorado Springs"},{"short_name":"El Paso County","types":["administrative_area_level_2","political"],"long_name":"El Paso County"},{"long_name":"Colorado","short_name":"CO","types":["administrative_area_level_1","political"]},{"long_name":"United States","short_name":"US","types":["country","political"]},{"types":["latitude"],"long_name":38.7372129,"short_name":38.7372129},{"types":["longitude"],"long_name":-104.8808063,"short_name":-104.8808063},{"types":["debug_info","cache_load_result"],"long_name":"hit","short_name":"hit"}] | K24: =NOT(AND(NOT(_xlfn.ISFORMULA(P24)),AND(NOT(_xlfn.ISFORMULA(Q24)),AND(NOT(_xlfn.ISFORMULA(R24)),AND(NOT(_xlfn.ISFORMULA(S24)),AND(NOT(_xlfn.ISFORMULA(T24)),AND(NOT(_xlfn.ISFORMULA(U24)),AND(NOT(_xlfn.ISFORMULA(V24)))))))))) -> TRUE | L24: =iferror(SEARCH(P24,F24),-1)>=0 -> FALSE | M24: TRUE | N24: =GOOGLEMAPS_GET_ADDRESS_LATITUDE(F24,true) -> 38.737213 | O24: =GOOGLEMAPS_GET_ADDRESS_LONGITUDE(F24,true) -> -104.88081 | P24: =GOOGLEMAPS_GET_ADDRESS_CITY(F24,true,false) -> Colorado Springs | Q24: =GOOGLEMAPS_GET_ADDRESS_STATE(F24,true,false) -> Colorado | R24: =GOOGLEMAPS_GET_ADDRESS_POSTAL_CODE(F24,false,false) -> 80926 | S24: =GOOGLEMAPS_GET_ADDRESS_COUNTRY(F24,true,false) -> United States | T24: =IFERROR(GOOGLEMAPS_DISTANCE("2116 4th Ave, Seattle, WA, 98121", F24, "driving")+0,"Not Driveable") -> 1389.016 | U24: =iferror(GOOGLEMAPS_DURATION("2116 4th Ave, Seattle, WA, 98121", F24, "driving")+0,"Not Driveable") -> 0.88113426 | V24: =GOOGLEMAPS_DISTANCE("2116 4th Ave, Seattle, WA, 98121", F24, "flying")+0 -> 1068.5511 | X24: =if(W24="YES","UNKNOWN","N/A") -> N/A | Z24: N/A | AB24: https://magazine.lensvid.com/article/fb/1318327108/mysterious-places-in-the-world-that-are-off-limits-to-everyone-and-why/
A25: 7 - Bucket List | B25: The Vatican Secret Archives, Vatican | C25: The Vatican Secret Archives hold documents dating back to the 8th century | D25: From Martin Luther’s excommunication papers to a letter from Michelangelo to Pope Julius II, the 50 miles of shelving at the Vatican’s secret archives hold artifacts and documents dating back to the eighth century. Since 1881, select scholars are allowed to research the archive, although admittance remains strict to this day. | E25: 9 – Inaccessible – Other | F25: The Vatican Secret Archives, Vatican | G25: =HYPERLINK(CONCAT("https://www.google.com/maps/search/",F25),"Link") -> Link | I25: =getCacheString(concat("GMPD|",F25)) -> {"address_components":[{"long_name":"Cortile del Belvedere","short_name":"Cortile del Belvedere","types":["establishment","point_of_interest"]},{"types":["locality","political"],"long_name":"Città del Vaticano","short_name":"Città del Vaticano"},{"short_name":"VA","long_name":"Vatican City","types":["country","political"]},{"long_name":"00120","types":["postal_code"],"short_name":"00120"},{"short_name":"21","long_name":"21","types":["street_number"]},{"short_name":"Via di Porta Angelica","types":["route"],"long_name":"Via di Porta Angelica"},{"long_name":"Città del Vaticano","types":["locality","political"],"short_name":"Città del Vaticano"},{"short_name":"Roma","types":["administrative_area_level_3","political"],"long_name":"Roma"},{"short_name":"RM","long_name":"Città metropolitana di Roma Capitale","types":["administrative_area_level_2","political"]},{"short_name":"VA","long_name":"Vatican City","types":["country","political"]},{"types":["postal_code"],"long_name":"00193","short_name":"00193"},{"types":["latitude"],"long_name":41.9048842,"short_name":41.9048842},{"types":["longitude"],"long_name":12.4548805,"short_name":12.4548805}],"distance_from":{"mi":{"flying":{"2116 4th Ave, Seattle, WA, 98121":5663.0861098338455},"driving":{"2116 4th Ave, Seattle, WA, 98121":"GOOGLE_MAPS_ERROR_CACHED - No route found!"}}},"duration_from":{"days":{"driving":{"2116 4th Ave, Seattle, WA, 98121":"GOOGLE_MAPS_ERROR_CACHED - No route found!"}}}} | J25: =GOOGLEMAPS_GET_ADDRESS_COMPONENTS_STRING(F25,false) -> [{"long_name":"Cortile del Belvedere","short_name":"Cortile del Belvedere","types":["establishment","point_of_interest"]},{"types":["locality","political"],"long_name":"Città del Vaticano","short_name":"Città del Vaticano"},{"short_name":"VA","long_name":"Vatican City","types":["country","political"]},{"long_name":"00120","types":["postal_code"],"short_name":"00120"},{"short_name":"21","long_name":"21","types":["street_number"]},{"short_name":"Via di Porta Angelica","types":["route"],"long_name":"Via di Porta Angelica"},{"long_name":"Città del Vaticano","types":["locality","political"],"short_name":"Città del Vaticano"},{"short_name":"Roma","types":["administrative_area_level_3","political"],"long_name":"Roma"},{"short_name":"RM","long_name":"Città metropolitana di Roma Capitale","types":["administrative_area_level_2","political"]},{"short_name":"VA","long_name":"Vatican City","types":["country","political"]},{"types":["postal_code"],"long_name":"00193","short_name":"00193"},{"types":["latitude"],"long_name":41.9048842,"short_name":41.9048842},{"types":["longitude"],"long_name":12.4548805,"short_name":12.4548805},{"types":["debug_info","cache_load_result"],"long_name":"hit","short_name":"hit"}] | K25: =NOT(AND(NOT(_xlfn.ISFORMULA(P25)),AND(NOT(_xlfn.ISFORMULA(Q25)),AND(NOT(_xlfn.ISFORMULA(R25)),AND(NOT(_xlfn.ISFORMULA(S25)),AND(NOT(_xlfn.ISFORMULA(T25)),AND(NOT(_xlfn.ISFORMULA(U25)),AND(NOT(_xlfn.ISFORMULA(V25)))))))))) -> TRUE | L25: =iferror(SEARCH(P25,F25),-1)>=0 -> FALSE | M25: TRUE | N25: =GOOGLEMAPS_GET_ADDRESS_LATITUDE(F25,true) -> 41.904884 | O25: =GOOGLEMAPS_GET_ADDRESS_LONGITUDE(F25,true) -> 12.45488 | P25: =GOOGLEMAPS_GET_ADDRESS_CITY(F25,true,false) -> Città del Vaticano | Q25: =GOOGLEMAPS_GET_ADDRESS_STATE(F25,true,false) -> UNDEFINED | R25: =GOOGLEMAPS_GET_ADDRESS_POSTAL_CODE(F25,false,false) -> 00120 | S25: =GOOGLEMAPS_GET_ADDRESS_COUNTRY(F25,true,false) -> Vatican City | T25: =IFERROR(GOOGLEMAPS_DISTANCE("2116 4th Ave, Seattle, WA, 98121", F25, "driving")+0,"Not Driveable") -> Not Driveable | U25: =iferror(GOOGLEMAPS_DURATION("2116 4th Ave, Seattle, WA, 98121", F25, "driving")+0,"Not Driveable") -> Not Driveable | V25: =GOOGLEMAPS_DISTANCE("2116 4th Ave, Seattle, WA, 98121", F25, "flying")+0 -> 5663.0861 | X25: =if(W25="YES","UNKNOWN","N/A") -> N/A | Z25: N/A | AB25: https://magazine.lensvid.com/article/fb/1318327108/mysterious-places-in-the-world-that-are-off-limits-to-everyone-and-why/
A26: 7 - Bucket List | B26: Fishing Village of Houtouwan | E26: 1 – Accessible – Freely | F26: Houtouwan, China | G26: =HYPERLINK(CONCAT("https://www.google.com/maps/search/",F26),"Link") -> Link | H26: Ghost Town | I26: =getCacheString(concat("GMPD|",F26)) -> {"address_components":[{"types":["political","sublocality","sublocality_level_3"],"long_name":"Houtouwan","short_name":"Houtouwan"},{"types":["political","sublocality","sublocality_level_1"],"long_name":"Shengsi County","short_name":"Shengsi County"},{"long_name":"Zhoushan","types":["locality","political"],"short_name":"Zhoushan"},{"long_name":"Zhejiang","short_name":"Zhejiang","types":["administrative_area_level_1","political"]},{"long_name":"China","short_name":"CN","types":["country","political"]},{"short_name":"202457","long_name":"202457","types":["postal_code"]},{"types":["plus_code"],"short_name":"PRFC+PC9","long_name":"PRFC+PC9"},{"short_name":"Shengsi County","long_name":"Shengsi County","types":["political","sublocality","sublocality_level_1"]},{"long_name":"Zhoushan","types":["locality","political"],"short_name":"Zhoushan"},{"short_name":"Zhejiang","types":["administrative_area_level_1","political"],"long_name":"Zhejiang"},{"short_name":"CN","long_name":"China","types":["country","political"]},{"long_name":"202457","types":["postal_code"],"short_name":"202457"},{"types":["latitude"],"long_name":30.72399399999999,"short_name":30.72399399999999},{"types":["longitude"],"long_name":122.822593,"short_name":122.822593}],"distance_from":{"mi":{"flying":{"2116 4th Ave, Seattle, WA, 98121":5686.46960865945},"driving":{"2116 4th Ave, Seattle, WA, 98121":"GOOGLE_MAPS_ERROR_CACHED - No route found!"}}},"duration_from":{"days":{"driving":{"2116 4th Ave, Seattle, WA, 98121":"GOOGLE_MAPS_ERROR_CACHED - No route found!"}}}} | J26: =GOOGLEMAPS_GET_ADDRESS_COMPONENTS_STRING(F26,false) -> [{"types":["political","sublocality","sublocality_level_3"],"long_name":"Houtouwan","short_name":"Houtouwan"},{"types":["political","sublocality","sublocality_level_1"],"long_name":"Shengsi County","short_name":"Shengsi County"},{"long_name":"Zhoushan","types":["locality","political"],"short_name":"Zhoushan"},{"long_name":"Zhejiang","short_name":"Zhejiang","types":["administrative_area_level_1","political"]},{"long_name":"China","short_name":"CN","types":["country","political"]},{"short_name":"202457","long_name":"202457","types":["postal_code"]},{"types":["plus_code"],"short_name":"PRFC+PC9","long_name":"PRFC+PC9"},{"short_name":"Shengsi County","long_name":"Shengsi County","types":["political","sublocality","sublocality_level_1"]},{"long_name":"Zhoushan","types":["locality","political"],"short_name":"Zhoushan"},{"short_name":"Zhejiang","types":["administrative_area_level_1","political"],"long_name":"Zhejiang"},{"short_name":"CN","long_name":"China","types":["country","political"]},{"long_name":"202457","types":["postal_code"],"short_name":"202457"},{"types":["latitude"],"long_name":30.72399399999999,"short_name":30.72399399999999},{"types":["longitude"],"long_name":122.822593,"short_name":122.822593},{"types":["debug_info","cache_load_result"],"long_name":"hit","short_name":"hit"}] | K26: =NOT(AND(NOT(_xlfn.ISFORMULA(P26)),AND(NOT(_xlfn.ISFORMULA(Q26)),AND(NOT(_xlfn.ISFORMULA(R26)),AND(NOT(_xlfn.ISFORMULA(S26)),AND(NOT(_xlfn.ISFORMULA(T26)),AND(NOT(_xlfn.ISFORMULA(U26)),AND(NOT(_xlfn.ISFORMULA(V26)))))))))) -> TRUE | L26: =iferror(SEARCH(P26,F26),-1)>=0 -> FALSE | M26: TRUE | N26: =GOOGLEMAPS_GET_ADDRESS_LATITUDE(F26,true) -> 30.723994 | O26: =GOOGLEMAPS_GET_ADDRESS_LONGITUDE(F26,true) -> 122.82259 | P26: =GOOGLEMAPS_GET_ADDRESS_CITY(F26,true,false) -> Zhoushan | Q26: =GOOGLEMAPS_GET_ADDRESS_STATE(F26,true,false) -> Zhejiang | R26: =GOOGLEMAPS_GET_ADDRESS_POSTAL_CODE(F26,false,false) -> 202457 | S26: =GOOGLEMAPS_GET_ADDRESS_COUNTRY(F26,true,false) -> China | T26: =IFERROR(GOOGLEMAPS_DISTANCE("2116 4th Ave, Seattle, WA, 98121", F26, "driving")+0,"Not Driveable") -> Not Driveable | U26: =iferror(GOOGLEMAPS_DURATION("2116 4th Ave, Seattle, WA, 98121", F26, "driving")+0,"Not Driveable") -> Not Driveable | V26: =GOOGLEMAPS_DISTANCE("2116 4th Ave, Seattle, WA, 98121", F26, "flying")+0 -> 5686.4696 | X26: =if(W26="YES","UNKNOWN","N/A") -> N/A | Z26: N/A | AC26: https://www.youtube.com/watch?v=Qk_gx3CmACY
A27: 7 - Bucket List | B27: The United Nations Buffer Zone, Cyprus | C27: The United Nations Buffer Zone in Cyprus is home to an abandoned airport and decades-old advertisements for products that no longer exist | D27: Due to a civil war between its Greek and Turkish populations, the island of Cyprus became a divided country. To enforce this division after the ceasefire in 1974, the United Nations established a 112-mile demilitarized buffer zone which is off-limits to both communities. The abandoned area within the capital city of Nicosia is home to an abandoned airport, old homes and advertisements for products that don’t even exist anymore. | E27: 8 – Inaccessible – Military Action / Dispute / Unrest | F27: The United Nations Buffer Zone, Cyprus | G27: =HYPERLINK(CONCAT("https://www.google.com/maps/search/",F27),"Link") -> Link | H27: Military and Heavy Industry | I27: =getCacheString(concat("GMPD|",F27)) -> {"distance_from":{"mi":{"driving":{"2116 4th Ave, Seattle, WA, 98121":"GOOGLE_MAPS_ERROR_CACHED - No route found!"},"flying":{"2116 4th Ave, Seattle, WA, 98121":6526.689201784583}}},"address_components":[{"long_name":"Cyprus","types":["country","political"],"short_name":"CY"},{"short_name":"4CGH+HW9","long_name":"4CGH+HW9","types":["plus_code"]},{"long_name":"Geri","types":["locality","political"],"short_name":"Geri"},{"long_name":"2201","types":["postal_code"],"short_name":"2201"},{"types":["latitude"],"long_name":35.126413,"short_name":35.126413},{"types":["longitude"],"long_name":33.429859,"short_name":33.429859}],"duration_from":{"days":{"driving":{"2116 4th Ave, Seattle, WA, 98121":"GOOGLE_MAPS_ERROR_CACHED - No route found!"}}}} | J27: =GOOGLEMAPS_GET_ADDRESS_COMPONENTS_STRING(F27,false) -> [{"long_name":"Cyprus","types":["country","political"],"short_name":"CY"},{"short_name":"4CGH+HW9","long_name":"4CGH+HW9","types":["plus_code"]},{"long_name":"Geri","types":["locality","political"],"short_name":"Geri"},{"long_name":"2201","types":["postal_code"],"short_name":"2201"},{"types":["latitude"],"long_name":35.126413,"short_name":35.126413},{"types":["longitude"],"long_name":33.429859,"short_name":33.429859},{"types":["debug_info","cache_load_result"],"long_name":"hit","short_name":"hit"}] | K27: =NOT(AND(NOT(_xlfn.ISFORMULA(P27)),AND(NOT(_xlfn.ISFORMULA(Q27)),AND(NOT(_xlfn.ISFORMULA(R27)),AND(NOT(_xlfn.ISFORMULA(S27)),AND(NOT(_xlfn.ISFORMULA(T27)),AND(NOT(_xlfn.ISFORMULA(U27)),AND(NOT(_xlfn.ISFORMULA(V27)))))))))) -> TRUE | L27: =iferror(SEARCH(P27,F27),-1)>=0 -> FALSE | M27: TRUE | N27: =GOOGLEMAPS_GET_ADDRESS_LATITUDE(F27,true) -> 35.126413 | O27: =GOOGLEMAPS_GET_ADDRESS_LONGITUDE(F27,true) -> 33.429859 | P27: =GOOGLEMAPS_GET_ADDRESS_CITY(F27,true,false) -> Geri | Q27: =GOOGLEMAPS_GET_ADDRESS_STATE(F27,true,false) -> Nicosia | R27: =GOOGLEMAPS_GET_ADDRESS_POSTAL_CODE(F27,false,false) -> 2201 | S27: =GOOGLEMAPS_GET_ADDRESS_COUNTRY(F27,true,false) -> Cyprus | T27: =IFERROR(GOOGLEMAPS_DISTANCE("2116 4th Ave, Seattle, WA, 98121", F27, "driving")+0,"Not Driveable") -> Not Driveable | U27: =iferror(GOOGLEMAPS_DURATION("2116 4th Ave, Seattle, WA, 98121", F27, "driving")+0,"Not Driveable") -> Not Driveable | V27: =GOOGLEMAPS_DISTANCE("2116 4th Ave, Seattle, WA, 98121", F27, "flying")+0 -> 6526.6892 | X27: =if(W27="YES","UNKNOWN","N/A") -> N/A | Z27: N/A | AB27: https://magazine.lensvid.com/article/fb/1318327108/mysterious-places-in-the-world-that-are-off-limits-to-everyone-and-why/
A28: 7 - Bucket List | B28: Aksai Chin | C28: Despite being the perfect landscape for travelers, Aksai Chin is off-limits to the public | D28: Located in Ladakh, Aksai Chin is a disputed territory between China and India. Although Aksai Chin comprises of beautiful cold desert landscapes, salt planes, and salt lakes, only military personnel and officials are allowed in the region due to its strategic location. | E28: 8 – Inaccessible – Military Action / Dispute / Unrest | F28: Aksai Chin | G28: =HYPERLINK(CONCAT("https://www.google.com/maps/search/",F28),"Link") -> Link | H28: Nature | I28: =getCacheString(concat("GMPD|",F28)) -> {"address_components":[{"short_name":"Aksai Chin","long_name":"Aksai Chin","types":["colloquial_area","political"]},{"short_name":"8J7X24JJ+HR","long_name":"8J7X24JJ+HR","types":["plus_code"]},{"types":["latitude"],"long_name":35.0313898,"short_name":35.0313898},{"types":["longitude"],"long_name":79.1321164,"short_name":79.1321164}]} | J28: =GOOGLEMAPS_GET_ADDRESS_COMPONENTS_STRING(F28,false) -> [{"short_name":"Aksai Chin","long_name":"Aksai Chin","types":["colloquial_area","political"]},{"short_name":"8J7X24JJ+HR","long_name":"8J7X24JJ+HR","types":["plus_code"]},{"types":["latitude"],"long_name":35.0313898,"short_name":35.0313898},{"types":["longitude"],"long_name":79.1321164,"short_name":79.1321164},{"types":["debug_info","cache_load_result"],"long_name":"hit","short_name":"hit"}] | K28: =NOT(AND(NOT(_xlfn.ISFORMULA(P28)),AND(NOT(_xlfn.ISFORMULA(Q28)),AND(NOT(_xlfn.ISFORMULA(R28)),AND(NOT(_xlfn.ISFORMULA(S28)),AND(NOT(_xlfn.ISFORMULA(T28)),AND(NOT(_xlfn.ISFORMULA(U28)),AND(NOT(_xlfn.ISFORMULA(V28)),AND(NOT(_xlfn.ISFORMULA(N28)),NOT(_xlfn.ISFORMULA(O28))))))))))) -> FALSE | L28: =iferror(SEARCH(P28,F28),-1)>=0 -> FALSE | M28: TRUE | N28: 35.03139 | O28: 79.132116 | P28: UNDEFINED | Q28: UNDEFINED | R28: UNDEFINED | S28: UNDEFINED | T28: Not Driveable | U28: Not Driveable | V28: 6573.95 | X28: =if(W28="YES","UNKNOWN","N/A") -> N/A | Z28: N/A | AB28: https://magazine.lensvid.com/article/fb/1318327108/mysterious-places-in-the-world-that-are-off-limits-to-everyone-and-why/
A29: 7 - Bucket List | B29: Sikkim | E29: 1 – Accessible – Freely | F29: Sikkim, India | G29: =HYPERLINK(CONCAT("https://www.google.com/maps/search/",F29),"Link") -> Link | H29: Nature | I29: =getCacheString(concat("GMPD|",F29)) -> {"address_components":[{"long_name":"Sikkim","types":["administrative_area_level_1","political"],"short_name":"SK"},{"long_name":"India","types":["country","political"],"short_name":"IN"},{"short_name":"982F+MH","long_name":"982F+MH","types":["plus_code"]},{"short_name":"Gangyep","long_name":"Gangyep","types":["locality","political"]},{"short_name":"South Sikkim","long_name":"South Sikkim","types":["administrative_area_level_3","political"]},{"long_name":"Sikkim","types":["administrative_area_level_1","political"],"short_name":"SK"},{"short_name":"IN","long_name":"India","types":["country","political"]},{"short_name":"737111","long_name":"737111","types":["postal_code"]},{"types":["latitude"],"long_name":27.3516407,"short_name":27.3516407},{"types":["longitude"],"long_name":88.32393090000001,"short_name":88.32393090000001}],"distance_from":{"mi":{"flying":{"2116 4th Ave, Seattle, WA, 98121":6917.438825854078},"driving":{"2116 4th Ave, Seattle, WA, 98121":"GOOGLE_MAPS_ERROR_CACHED - No route found!"}}},"duration_from":{"days":{"driving":{"2116 4th Ave, Seattle, WA, 98121":"GOOGLE_MAPS_ERROR_CACHED - No route found!"}}}} | J29: =GOOGLEMAPS_GET_ADDRESS_COMPONENTS_STRING(F29,false) -> [{"long_name":"Sikkim","types":["administrative_area_level_1","political"],"short_name":"SK"},{"long_name":"India","types":["country","political"],"short_name":"IN"},{"short_name":"982F+MH","long_name":"982F+MH","types":["plus_code"]},{"short_name":"Gangyep","long_name":"Gangyep","types":["locality","political"]},{"short_name":"South Sikkim","long_name":"South Sikkim","types":["administrative_area_level_3","political"]},{"long_name":"Sikkim","types":["administrative_area_level_1","political"],"short_name":"SK"},{"short_name":"IN","long_name":"India","types":["country","political"]},{"short_name":"737111","long_name":"737111","types":["postal_code"]},{"types":["latitude"],"long_name":27.3516407,"short_name":27.3516407},{"types":["longitude"],"long_name":88.32393090000001,"short_name":88.32393090000001},{"types":["debug_info","cache_load_result"],"long_name":"hit","short_name":"hit"}] | K29: =NOT(AND(NOT(_xlfn.ISFORMULA(P29)),AND(NOT(_xlfn.ISFORMULA(Q29)),AND(NOT(_xlfn.ISFORMULA(R29)),AND(NOT(_xlfn.ISFORMULA(S29)),AND(NOT(_xlfn.ISFORMULA(T29)),AND(NOT(_xlfn.ISFORMULA(U29)),AND(NOT(_xlfn.ISFORMULA(V29)))))))))) -> TRUE | L29: =iferror(SEARCH(P29,F29),-1)>=0 -> FALSE | M29: TRUE | N29: =GOOGLEMAPS_GET_ADDRESS_LATITUDE(F29,true) -> 27.351641 | O29: =GOOGLEMAPS_GET_ADDRESS_LONGITUDE(F29,true) -> 88.323931 | P29: =GOOGLEMAPS_GET_ADDRESS_CITY(F29,true,false) -> Gangyep | Q29: =GOOGLEMAPS_GET_ADDRESS_STATE(F29,true,false) -> Sikkim | R29: =GOOGLEMAPS_GET_ADDRESS_POSTAL_CODE(F29,false,false) -> 737111 | S29: =GOOGLEMAPS_GET_ADDRESS_COUNTRY(F29,true,false) -> India | T29: =IFERROR(GOOGLEMAPS_DISTANCE("2116 4th Ave, Seattle, WA, 98121", F29, "driving")+0,"Not Driveable") -> Not Driveable | U29: =iferror(GOOGLEMAPS_DURATION("2116 4th Ave, Seattle, WA, 98121", F29, "driving")+0,"Not Driveable") -> Not Driveable | V29: =GOOGLEMAPS_DISTANCE("2116 4th Ave, Seattle, WA, 98121", F29, "flying")+0 -> 6917.4388 | X29: =if(W29="YES","UNKNOWN","N/A") -> N/A | Z29: N/A
A30: 7 - Bucket List | B30: Ta Prohm, Angkor Wat | E30: 2 – Accessible – Gated Entry | F30: Ta Prohm, Angkor Wat, Thailand | G30: =HYPERLINK(CONCAT("https://www.google.com/maps/search/",F30),"Link") -> Link | H30: Abandoned Building | I30: =getCacheString(concat("GMPD|",F30)) -> {"distance_from":{"mi":{"flying":{"2116 4th Ave, Seattle, WA, 98121":7299.2997129257965},"driving":{"2116 4th Ave, Seattle, WA, 98121":"GOOGLE_MAPS_ERROR_CACHED - No route found!"}}},"address_components":[{"long_name":"Thailand","short_name":"TH","types":["country","political"]},{"types":["street_number"],"long_name":"413","short_name":"413"},{"long_name":"2","types":["route"],"short_name":"2"},{"long_name":"ต.ทับช้าง","types":["locality","political"],"short_name":"ต.ทับช้าง"},{"types":["administrative_area_level_2","political"],"short_name":"อำเภอเมืองเพชรบูรณ์","long_name":"อำเภอเมืองเพชรบูรณ์"},{"short_name":"จ.เพชรบูรณ์","types":["administrative_area_level_1","political"],"long_name":"Chang Wat Phetchabun"},{"short_name":"TH","long_name":"Thailand","types":["country","political"]},{"types":["postal_code"],"long_name":"67000","short_name":"67000"},{"types":["latitude"],"long_name":15.870032,"short_name":15.870032},{"types":["longitude"],"long_name":100.992541,"short_name":100.992541}],"duration_from":{"days":{"driving":{"2116 4th Ave, Seattle, WA, 98121":"GOOGLE_MAPS_ERROR_CACHED - No route found!"}}}} | J30: =GOOGLEMAPS_GET_ADDRESS_COMPONENTS_STRING(F30,false) -> [{"long_name":"Thailand","short_name":"TH","types":["country","political"]},{"types":["street_number"],"long_name":"413","short_name":"413"},{"long_name":"2","types":["route"],"short_name":"2"},{"long_name":"ต.ทับช้าง","types":["locality","political"],"short_name":"ต.ทับช้าง"},{"types":["administrative_area_level_2","political"],"short_name":"อำเภอเมืองเพชรบูรณ์","long_name":"อำเภอเมืองเพชรบูรณ์"},{"short_name":"จ.เพชรบูรณ์","types":["administrative_area_level_1","political"],"long_name":"Chang Wat Phetchabun"},{"short_name":"TH","long_name":"Thailand","types":["country","political"]},{"types":["postal_code"],"long_name":"67000","short_name":"67000"},{"types":["latitude"],"long_name":15.870032,"short_name":15.870032},{"types":["longitude"],"long_name":100.992541,"short_name":100.992541},{"types":["debug_info","cache_load_result"],"long_name":"hit","short_name":"hit"}] | K30: =NOT(AND(NOT(_xlfn.ISFORMULA(P30)),AND(NOT(_xlfn.ISFORMULA(Q30)),AND(NOT(_xlfn.ISFORMULA(R30)),AND(NOT(_xlfn.ISFORMULA(S30)),AND(NOT(_xlfn.ISFORMULA(T30)),AND(NOT(_xlfn.ISFORMULA(U30)),AND(NOT(_xlfn.ISFORMULA(V30)))))))))) -> TRUE | L30: =iferror(SEARCH(P30,F30),-1)>=0 -> FALSE | M30: TRUE | N30: =GOOGLEMAPS_GET_ADDRESS_LATITUDE(F30,true) -> 15.870032 | O30: =GOOGLEMAPS_GET_ADDRESS_LONGITUDE(F30,true) -> 100.99254 | P30: =GOOGLEMAPS_GET_ADDRESS_CITY(F30,true,false) -> ต.ทับช้าง | Q30: =GOOGLEMAPS_GET_ADDRESS_STATE(F30,true,false) -> Chang Wat Phetchabun | R30: =GOOGLEMAPS_GET_ADDRESS_POSTAL_CODE(F30,false,false) -> 67000 | S30: =GOOGLEMAPS_GET_ADDRESS_COUNTRY(F30,true,false) -> Thailand | T30: =IFERROR(GOOGLEMAPS_DISTANCE("2116 4th Ave, Seattle, WA, 98121", F30, "driving")+0,"Not Driveable") -> Not Driveable | U30: =iferror(GOOGLEMAPS_DURATION("2116 4th Ave, Seattle, WA, 98121", F30, "driving")+0,"Not Driveable") -> Not Driveable | V30: =GOOGLEMAPS_DISTANCE("2116 4th Ave, Seattle, WA, 98121", F30, "flying")+0 -> 7299.2997 | X30: =if(W30="YES","UNKNOWN","N/A") -> N/A | Z30: N/A | AC30: https://www.youtube.com/watch?v=Qk_gx3CmACY
A31: 7 - Bucket List | B31: Mount Fitz Roy | E31: 2 – Accessible – Gated Entry | F31: Mount Fitz Roy, Argentina | G31: =HYPERLINK(CONCAT("https://www.google.com/maps/search/",F31),"Link") -> Link | H31: Nature | I31: =getCacheString(concat("GMPD|",F31)) -> {"address_components":[{"short_name":"Fitz Roy","long_name":"Fitz Roy","types":["establishment","natural_feature"]},{"types":["plus_code"],"short_name":"4728PXH4+GP","long_name":"4728PXH4+GP"},{"types":["latitude"],"long_name":-49.271246,"short_name":-49.271246},{"types":["longitude"],"long_name":-73.04322599999999,"short_name":-73.04322599999999}],"distance_from":{"mi":{"driving":{"2116 4th Ave, Seattle, WA, 98121":"GOOGLE_MAPS_ERROR_CACHED - No route found!"},"flying":{"2116 4th Ave, Seattle, WA, 98121":7312.655498527347}}},"duration_from":{"days":{"driving":{"2116 4th Ave, Seattle, WA, 98121":"GOOGLE_MAPS_ERROR_CACHED - No route found!"}}}} | J31: =GOOGLEMAPS_GET_ADDRESS_COMPONENTS_STRING(F31,false) -> [{"short_name":"Fitz Roy","long_name":"Fitz Roy","types":["establishment","natural_feature"]},{"types":["plus_code"],"short_name":"4728PXH4+GP","long_name":"4728PXH4+GP"},{"types":["latitude"],"long_name":-49.271246,"short_name":-49.271246},{"types":["longitude"],"long_name":-73.04322599999999,"short_name":-73.04322599999999},{"types":["debug_info","cache_load_result"],"long_name":"hit","short_name":"hit"}] | K31: =NOT(AND(NOT(_xlfn.ISFORMULA(P31)),AND(NOT(_xlfn.ISFORMULA(Q31)),AND(NOT(_xlfn.ISFORMULA(R31)),AND(NOT(_xlfn.ISFORMULA(S31)),AND(NOT(_xlfn.ISFORMULA(T31)),AND(NOT(_xlfn.ISFORMULA(U31)),AND(NOT(_xlfn.ISFORMULA(V31)))))))))) -> TRUE | L31: =iferror(SEARCH(P31,F31),-1)>=0 -> FALSE | M31: TRUE | N31: =GOOGLEMAPS_GET_ADDRESS_LATITUDE(F31,true) -> -49.271246 | O31: =GOOGLEMAPS_GET_ADDRESS_LONGITUDE(F31,true) -> -73.043226 | P31: =GOOGLEMAPS_GET_ADDRESS_CITY(F31,true,false) -> UNDEFINED | Q31: =GOOGLEMAPS_GET_ADDRESS_STATE(F31,true,false) -> UNDEFINED | R31: =GOOGLEMAPS_GET_ADDRESS_POSTAL_CODE(F31,false,false) -> UNDEFINED | S31: =GOOGLEMAPS_GET_ADDRESS_COUNTRY(F31,true,false) -> UNDEFINED | T31: =IFERROR(GOOGLEMAPS_DISTANCE("2116 4th Ave, Seattle, WA, 98121", F31, "driving")+0,"Not Driveable") -> Not Driveable | U31: =iferror(GOOGLEMAPS_DURATION("2116 4th Ave, Seattle, WA, 98121", F31, "driving")+0,"Not Driveable") -> Not Driveable | V31: =GOOGLEMAPS_DISTANCE("2116 4th Ave, Seattle, WA, 98121", F31, "flying")+0 -> 7312.6555 | X31: =if(W31="YES","UNKNOWN","N/A") -> N/A | Z31: N/A
A32: 7 - Bucket List | B32: Al Madam Ghost Town | C32: Desert reclaimed ghost town 37 miles from Dubai | E32: 1 – Accessible – Freely | F32: Al Madam, UAE | G32: =HYPERLINK(CONCAT("https://www.google.com/maps/search/",F32),"Link") -> Link | H32: Ghost Town | I32: =getCacheString(concat("GMPD|",F32)) -> {"address_components":[{"short_name":"Al Madam","long_name":"Al Madam","types":["locality","political"]},{"long_name":"Sharjah","types":["administrative_area_level_1","political"],"short_name":"Sharjah"},{"long_name":"United Arab Emirates","short_name":"AE","types":["country","political"]},{"types":["establishment","park","point_of_interest"],"short_name":"Dr. Alfateen bin hussein Albaddad private resort","long_name":"Dr. Alfateen bin hussein Albaddad private resort"},{"long_name":"XQFG+FV9","types":["plus_code"],"short_name":"XQFG+FV9"},{"long_name":"Al Madam","short_name":"Al Madam","types":["political","sublocality","sublocality_level_1"]},{"types":["locality","political"],"long_name":"Al Madam","short_name":"Al Madam"},{"short_name":"Sharjah","long_name":"Sharjah","types":["administrative_area_level_1","political"]},{"long_name":"United Arab Emirates","short_name":"AE","types":["country","political"]},{"types":["latitude"],"long_name":24.973654,"short_name":24.973654},{"types":["longitude"],"long_name":55.777229,"short_name":55.777229}]} | J32: =GOOGLEMAPS_GET_ADDRESS_COMPONENTS_STRING(F32,false) -> [{"short_name":"Al Madam","long_name":"Al Madam","types":["locality","political"]},{"long_name":"Sharjah","types":["administrative_area_level_1","political"],"short_name":"Sharjah"},{"long_name":"United Arab Emirates","short_name":"AE","types":["country","political"]},{"types":["establishment","park","point_of_interest"],"short_name":"Dr. Alfateen bin hussein Albaddad private resort","long_name":"Dr. Alfateen bin hussein Albaddad private resort"},{"long_name":"XQFG+FV9","types":["plus_code"],"short_name":"XQFG+FV9"},{"long_name":"Al Madam","short_name":"Al Madam","types":["political","sublocality","sublocality_level_1"]},{"types":["locality","political"],"long_name":"Al Madam","short_name":"Al Madam"},{"short_name":"Sharjah","long_name":"Sharjah","types":["administrative_area_level_1","political"]},{"long_name":"United Arab Emirates","short_name":"AE","types":["country","political"]},{"types":["latitude"],"long_name":24.973654,"short_name":24.973654},{"types":["longitude"],"long_name":55.777229,"short_name":55.777229},{"types":["debug_info","cache_load_result"],"long_name":"hit","short_name":"hit"}] | K32: =NOT(AND(NOT(_xlfn.ISFORMULA(P32)),AND(NOT(_xlfn.ISFORMULA(Q32)),AND(NOT(_xlfn.ISFORMULA(R32)),AND(NOT(_xlfn.ISFORMULA(S32)),AND(NOT(_xlfn.ISFORMULA(T32)),AND(NOT(_xlfn.ISFORMULA(U32)),AND(NOT(_xlfn.ISFORMULA(V32)),AND(NOT(_xlfn.ISFORMULA(N32)),NOT(_xlfn.ISFORMULA(O32))))))))))) -> FALSE | L32: =iferror(SEARCH(P32,F32),-1)>=0 -> TRUE | M32: TRUE | N32: 24.973666 | O32: 55.77721 | P32: Al Madam | Q32: Sharjah | R32: UNDEFINED | S32: United Arab Emirates | T32: Not Driveable | U32: Not Driveable | V32: 7420.11 | X32: =if(W32="YES","UNKNOWN","N/A") -> N/A | Z32: N/A | AF32: Swallowed by sand—the 'ghost town' of Al Madam in Sharjah, UAE. An inland town in United Arab Emirates (UAE), today known as Al Madam, lives as a ghost town, a place that has long been abandoned, long forgotten!
A33: 7 - Bucket List | B33: Inaccessible Island | E33: 3 – Accessible – Tour Guide Required | F33: Inaccessible Island | G33: =HYPERLINK(CONCAT("https://www.google.com/maps/search/",F33),"Link") -> Link | H33: Nature | I33: =getCacheString(concat("GMPD|",F33)) -> {"address_components":[{"short_name":"Inaccessible Island","types":["establishment","natural_feature"],"long_name":"Inaccessible Island"},{"short_name":"Tristan da Cunha","types":["administrative_area_level_1","political"],"long_name":"Tristan da Cunha"},{"long_name":"Saint Helena, Ascension and Tristan da Cunha","short_name":"SH","types":["country","political"]},{"long_name":"4CJ9M8XG+VM","short_name":"4CJ9M8XG+VM","types":["plus_code"]},{"types":["latitude"],"long_name":-37.3003564,"short_name":-37.3003564},{"types":["longitude"],"long_name":-12.6733009,"short_name":-12.6733009}],"distance_from":{"mi":{"flying":{"2116 4th Ave, Seattle, WA, 98121":8906.784147538743},"driving":{"2116 4th Ave, Seattle, WA, 98121":"GOOGLE_MAPS_ERROR_CACHED - No route found!"}}},"duration_from":{"days":{"driving":{"2116 4th Ave, Seattle, WA, 98121":"GOOGLE_MAPS_ERROR_CACHED - No route found!"}}}} | J33: =GOOGLEMAPS_GET_ADDRESS_COMPONENTS_STRING(F33,false) -> [{"short_name":"Inaccessible Island","types":["establishment","natural_feature"],"long_name":"Inaccessible Island"},{"short_name":"Tristan da Cunha","types":["administrative_area_level_1","political"],"long_name":"Tristan da Cunha"},{"long_name":"Saint Helena, Ascension and Tristan da Cunha","short_name":"SH","types":["country","political"]},{"long_name":"4CJ9M8XG+VM","short_name":"4CJ9M8XG+VM","types":["plus_code"]},{"types":["latitude"],"long_name":-37.3003564,"short_name":-37.3003564},{"types":["longitude"],"long_name":-12.6733009,"short_name":-12.6733009},{"types":["debug_info","cache_load_result"],"long_name":"hit","short_name":"hit"}] | K33: =NOT(AND(NOT(_xlfn.ISFORMULA(P33)),AND(NOT(_xlfn.ISFORMULA(Q33)),AND(NOT(_xlfn.ISFORMULA(R33)),AND(NOT(_xlfn.ISFORMULA(S33)),AND(NOT(_xlfn.ISFORMULA(T33)),AND(NOT(_xlfn.ISFORMULA(U33)),AND(NOT(_xlfn.ISFORMULA(V33)))))))))) -> TRUE | L33: =iferror(SEARCH(P33,F33),-1)>=0 -> FALSE | M33: TRUE | N33: =GOOGLEMAPS_GET_ADDRESS_LATITUDE(F33,true) -> -37.300356 | O33: =GOOGLEMAPS_GET_ADDRESS_LONGITUDE(F33,true) -> -12.673301 | P33: =GOOGLEMAPS_GET_ADDRESS_CITY(F33,true,false) -> UNDEFINED | Q33: =GOOGLEMAPS_GET_ADDRESS_STATE(F33,true,false) -> Tristan da Cunha | R33: =GOOGLEMAPS_GET_ADDRESS_POSTAL_CODE(F33,false,false) -> UNDEFINED | S33: =GOOGLEMAPS_GET_ADDRESS_COUNTRY(F33,true,false) -> Saint Helena, Ascension and Tristan da Cunha | T33: =IFERROR(GOOGLEMAPS_DISTANCE("2116 4th Ave, Seattle, WA, 98121", F33, "driving")+0,"Not Driveable") -> Not Driveable | U33: =iferror(GOOGLEMAPS_DURATION("2116 4th Ave, Seattle, WA, 98121", F33, "driving")+0,"Not Driveable") -> Not Driveable | V33: =GOOGLEMAPS_DISTANCE("2116 4th Ave, Seattle, WA, 98121", F33, "flying")+0 -> 8906.7841 | X33: =if(W33="YES","UNKNOWN","N/A") -> N/A | Z33: N/A
A34: 7 - Bucket List | B34: McMurdo Station, Antarctica | C34: With 1,258 residents, McMurdo Station is the largest community in Antarctica | D34: McMurdo Station is a research station in Antarctica operated by the United States. In the summer, the number of residents in the community can reach 1,258, while in the winter it plummets to less than 250. Access to the facilities is strictly forbidden to tourists and only researchers and support staff are allowed to enter and reside in the community. | E34: 5 – Access Considerably Restricted – Special Process / Circumstance Required | F34: -77.846389, 166.668333 | G34: =HYPERLINK(CONCAT("https://www.google.com/maps/search/",F34),"Link") -> Link | I34: =getCacheString(concat("GMPD|",F34)) -> {"address_components":[{"long_name":"5M39+994","short_name":"5M39+994","types":["plus_code"]},{"long_name":"McMurdo Station","short_name":"McMurdo Station","types":["locality","political"]},{"long_name":"Antarctica","short_name":"AQ","types":["country","political"]},{"long_name":"5M39+994","short_name":"5M39+994","types":["plus_code"]},{"short_name":"McMurdo Station","types":["locality","political"],"long_name":"McMurdo Station"},{"long_name":"Antarctica","short_name":"AQ","types":["country","political"]},{"types":["latitude"],"long_name":-77.84655040000001,"short_name":-77.84655040000001},{"types":["longitude"],"long_name":166.6683954,"short_name":166.6683954}],"distance_from":{"mi":{"driving":{"2116 4th Ave, Seattle, WA, 98121":"GOOGLE_MAPS_ERROR_CACHED - No route found!"},"flying":{"2116 4th Ave, Seattle, WA, 98121":9156.237339530491}}},"duration_from":{"days":{"driving":{"2116 4th Ave, Seattle, WA, 98121":"GOOGLE_MAPS_ERROR_CACHED - No route found!"}}}} | J34: =GOOGLEMAPS_GET_ADDRESS_COMPONENTS_STRING(F34,false) -> [{"long_name":"5M39+994","short_name":"5M39+994","types":["plus_code"]},{"long_name":"McMurdo Station","short_name":"McMurdo Station","types":["locality","political"]},{"long_name":"Antarctica","short_name":"AQ","types":["country","political"]},{"long_name":"5M39+994","short_name":"5M39+994","types":["plus_code"]},{"short_name":"McMurdo Station","types":["locality","political"],"long_name":"McMurdo Station"},{"long_name":"Antarctica","short_name":"AQ","types":["country","political"]},{"types":["latitude"],"long_name":-77.84655040000001,"short_name":-77.84655040000001},{"types":["longitude"],"long_name":166.6683954,"short_name":166.6683954},{"types":["debug_info","cache_load_result"],"long_name":"hit","short_name":"hit"}] | K34: =NOT(AND(NOT(_xlfn.ISFORMULA(P34)),AND(NOT(_xlfn.ISFORMULA(Q34)),AND(NOT(_xlfn.ISFORMULA(R34)),AND(NOT(_xlfn.ISFORMULA(S34)),AND(NOT(_xlfn.ISFORMULA(T34)),AND(NOT(_xlfn.ISFORMULA(U34)),AND(NOT(_xlfn.ISFORMULA(V34)))))))))) -> TRUE | L34: =iferror(SEARCH(P34,F34),-1)>=0 -> FALSE | M34: TRUE | N34: =GOOGLEMAPS_GET_ADDRESS_LATITUDE(F34,true) -> -77.84655 | O34: =GOOGLEMAPS_GET_ADDRESS_LONGITUDE(F34,true) -> 166.6684 | P34: =GOOGLEMAPS_GET_ADDRESS_CITY(F34,true,false) -> McMurdo Station | Q34: =GOOGLEMAPS_GET_ADDRESS_STATE(F34,true,false) -> UNDEFINED | R34: =GOOGLEMAPS_GET_ADDRESS_POSTAL_CODE(F34,false,false) -> UNDEFINED | S34: =GOOGLEMAPS_GET_ADDRESS_COUNTRY(F34,true,false) -> Antarctica | T34: =IFERROR(GOOGLEMAPS_DISTANCE("2116 4th Ave, Seattle, WA, 98121", F34, "driving")+0,"Not Driveable") -> Not Driveable | U34: =iferror(GOOGLEMAPS_DURATION("2116 4th Ave, Seattle, WA, 98121", F34, "driving")+0,"Not Driveable") -> Not Driveable | V34: =GOOGLEMAPS_DISTANCE("2116 4th Ave, Seattle, WA, 98121", F34, "flying")+0 -> 9156.2373 | X34: =if(W34="YES","UNKNOWN","N/A") -> N/A | Z34: N/A | AB34: https://magazine.lensvid.com/article/fb/1318327108/mysterious-places-in-the-world-that-are-off-limits-to-everyone-and-why/
A35: 7 - Bucket List | B35: Kolmanskop | E35: 2 – Accessible – Gated Entry | F35: Kolmanskop, Namibia | G35: =HYPERLINK(CONCAT("https://www.google.com/maps/search/",F35),"Link") -> Link | H35: Ghost Town | I35: =getCacheString(concat("GMPD|",F35)) -> {"address_components":[{"short_name":"Kolmanskop","long_name":"Kolmanskop","types":["locality","political"]},{"long_name":"Karas Region","short_name":"Karas Region","types":["administrative_area_level_1","political"]},{"short_name":"NA","long_name":"Namibia","types":["country","political"]},{"long_name":"76VJ+QMX","short_name":"76VJ+QMX","types":["plus_code"]},{"short_name":"Kolmanskop","long_name":"Kolmanskop","types":["locality","political"]},{"long_name":"Karas Region","short_name":"Karas Region","types":["administrative_area_level_1","political"]},{"types":["country","political"],"short_name":"NA","long_name":"Namibia"},{"types":["latitude"],"long_name":-26.7049924,"short_name":-26.7049924},{"types":["longitude"],"long_name":15.2326454,"short_name":15.2326454}]} | J35: =GOOGLEMAPS_GET_ADDRESS_COMPONENTS_STRING(F35,false) -> [{"short_name":"Kolmanskop","long_name":"Kolmanskop","types":["locality","political"]},{"long_name":"Karas Region","short_name":"Karas Region","types":["administrative_area_level_1","political"]},{"short_name":"NA","long_name":"Namibia","types":["country","political"]},{"long_name":"76VJ+QMX","short_name":"76VJ+QMX","types":["plus_code"]},{"short_name":"Kolmanskop","long_name":"Kolmanskop","types":["locality","political"]},{"long_name":"Karas Region","short_name":"Karas Region","types":["administrative_area_level_1","political"]},{"types":["country","political"],"short_name":"NA","long_name":"Namibia"},{"types":["latitude"],"long_name":-26.7049924,"short_name":-26.7049924},{"types":["longitude"],"long_name":15.2326454,"short_name":15.2326454},{"types":["debug_info","cache_load_result"],"long_name":"hit","short_name":"hit"}] | K35: =NOT(AND(NOT(_xlfn.ISFORMULA(P35)),AND(NOT(_xlfn.ISFORMULA(Q35)),AND(NOT(_xlfn.ISFORMULA(R35)),AND(NOT(_xlfn.ISFORMULA(S35)),AND(NOT(_xlfn.ISFORMULA(T35)),AND(NOT(_xlfn.ISFORMULA(U35)),AND(NOT(_xlfn.ISFORMULA(V35)),AND(NOT(_xlfn.ISFORMULA(N35)),NOT(_xlfn.ISFORMULA(O35))))))))))) -> FALSE | L35: =iferror(SEARCH(P35,F35),-1)>=0 -> TRUE | M35: TRUE | N35: -26.704992 | O35: 15.232645 | P35: Kolmanskop | Q35: Karas Region | R35: UNDEFINED | S35: Namibia | T35: Not Driveable | U35: Not Driveable | V35: 9737.87 | X35: =if(W35="YES","UNKNOWN","N/A") -> N/A | Z35: 44378 | AC35: https://www.youtube.com/watch?v=Qk_gx3CmACY
A36: 6 - Flight Worthy | B36: Yellowstone Snowmobiling | F36: Mammoth Hot Springs, Wyoming | G36: =HYPERLINK(CONCAT("https://www.google.com/maps/search/",F36),"Link") -> Link | H36: Nature | I36: =getCacheString(concat("GMPD|",F36)) -> {"distance_from":{"mi":{"flying":{"2116 4th Ave, Seattle, WA, 98121":584.2469583804541},"driving":{"2116 4th Ave, Seattle, WA, 98121":759.5405569985212}}},"address_components":[{"long_name":"Mammoth","types":["neighborhood","political"],"short_name":"Mammoth"},{"types":["locality","political"],"short_name":"Mammoth","long_name":"Mammoth"},{"long_name":"Park County","types":["administrative_area_level_2","political"],"short_name":"Park County"},{"long_name":"Wyoming","short_name":"WY","types":["administrative_area_level_1","political"]},{"long_name":"United States","types":["country","political"],"short_name":"US"},{"long_name":"82190","short_name":"82190","types":["postal_code"]},{"short_name":"Yellowstone National Park","types":["establishment","point_of_interest"],"long_name":"Yellowstone National Park"},{"short_name":"114","types":["street_number"],"long_name":"114"},{"long_name":"Grand Loop Road","types":["route"],"short_name":"Grand Loop Rd"},{"types":["neighborhood","political"],"short_name":"Mammoth","long_name":"Mammoth"},{"long_name":"Mammoth","types":["locality","political"],"short_name":"Mammoth"},{"long_name":"Park County","short_name":"Park County","types":["administrative_area_level_2","political"]},{"long_name":"Wyoming","types":["administrative_area_level_1","political"],"short_name":"WY"},{"long_name":"United States","types":["country","political"],"short_name":"US"},{"short_name":"82190","types":["postal_code"],"long_name":"82190"},{"types":["latitude"],"long_name":44.9768789,"short_name":44.9768789},{"types":["longitude"],"long_name":-110.6991303,"short_name":-110.6991303}],"duration_from":{"days":{"driving":{"2116 4th Ave, Seattle, WA, 98121":0.4870601851851852}}}} | J36: =GOOGLEMAPS_GET_ADDRESS_COMPONENTS_STRING(F36,false) -> [{"long_name":"Mammoth","types":["neighborhood","political"],"short_name":"Mammoth"},{"types":["locality","political"],"short_name":"Mammoth","long_name":"Mammoth"},{"long_name":"Park County","types":["administrative_area_level_2","political"],"short_name":"Park County"},{"long_name":"Wyoming","short_name":"WY","types":["administrative_area_level_1","political"]},{"long_name":"United States","types":["country","political"],"short_name":"US"},{"long_name":"82190","short_name":"82190","types":["postal_code"]},{"short_name":"Yellowstone National Park","types":["establishment","point_of_interest"],"long_name":"Yellowstone National Park"},{"short_name":"114","types":["street_number"],"long_name":"114"},{"long_name":"Grand Loop Road","types":["route"],"short_name":"Grand Loop Rd"},{"types":["neighborhood","political"],"short_name":"Mammoth","long_name":"Mammoth"},{"long_name":"Mammoth","types":["locality","political"],"short_name":"Mammoth"},{"long_name":"Park County","short_name":"Park County","types":["administrative_area_level_2","political"]},{"long_name":"Wyoming","types":["administrative_area_level_1","political"],"short_name":"WY"},{"long_name":"United States","types":["country","political"],"short_name":"US"},{"short_name":"82190","types":["postal_code"],"long_name":"82190"},{"types":["latitude"],"long_name":44.9768789,"short_name":44.9768789},{"types":["longitude"],"long_name":-110.6991303,"short_name":-110.6991303},{"types":["debug_info","cache_load_result"],"long_name":"hit","short_name":"hit"}] | K36: =NOT(AND(NOT(_xlfn.ISFORMULA(P36)),AND(NOT(_xlfn.ISFORMULA(Q36)),AND(NOT(_xlfn.ISFORMULA(R36)),AND(NOT(_xlfn.ISFORMULA(S36)),AND(NOT(_xlfn.ISFORMULA(T36)),AND(NOT(_xlfn.ISFORMULA(U36)),AND(NOT(_xlfn.ISFORMULA(V36)))))))))) -> TRUE | L36: =iferror(SEARCH(P36,F36),-1)>=0 -> TRUE | M36: TRUE | N36: =GOOGLEMAPS_GET_ADDRESS_LATITUDE(F36,true) -> 44.976879 | O36: =GOOGLEMAPS_GET_ADDRESS_LONGITUDE(F36,true) -> -110.69913 | P36: =GOOGLEMAPS_GET_ADDRESS_CITY(F36,true,false) -> Mammoth | Q36: =GOOGLEMAPS_GET_ADDRESS_STATE(F36,true,false) -> Wyoming | R36: =GOOGLEMAPS_GET_ADDRESS_POSTAL_CODE(F36,false,false) -> 82190 | S36: =GOOGLEMAPS_GET_ADDRESS_COUNTRY(F36,true,false) -> United States | T36: =IFERROR(GOOGLEMAPS_DISTANCE("2116 4th Ave, Seattle, WA, 98121", F36, "driving")+0,"Not Driveable") -> 759.54056 | U36: =iferror(GOOGLEMAPS_DURATION("2116 4th Ave, Seattle, WA, 98121", F36, "driving")+0,"Not Driveable") -> 0.48706019 | V36: =GOOGLEMAPS_DISTANCE("2116 4th Ave, Seattle, WA, 98121", F36, "flying")+0 -> 584.24696 | X36: =if(W36="YES","UNKNOWN","N/A") -> N/A | Z36: N/A
A37: 6 - Flight Worthy | B37: Titan Missile Museum | C37: Titan missile site with a deactivated missle | F37: Titan Missile Museum, AZ | G37: =HYPERLINK(CONCAT("https://www.google.com/maps/search/",F37),"Link") -> Link | H37: Military and Heavy Industry | I37: =getCacheString(concat("GMPD|",F37)) -> {"address_components":[{"long_name":"1580","short_name":"1580","types":["street_number"]},{"long_name":"West Duval Mine Road","types":["route"],"short_name":"W Duval Mine Rd"},{"types":["locality","political"],"long_name":"Green Valley","short_name":"Green Valley"},{"types":["administrative_area_level_2","political"],"long_name":"Pima County","short_name":"Pima County"},{"long_name":"Arizona","types":["administrative_area_level_1","political"],"short_name":"AZ"},{"short_name":"US","long_name":"United States","types":["country","political"]},{"short_name":"85614","long_name":"85614","types":["postal_code"]},{"short_name":"4907","long_name":"4907","types":["postal_code_suffix"]},{"long_name":"1580","types":["street_number"],"short_name":"1580"},{"short_name":"W Duval Mine Rd","long_name":"West Duval Mine Road","types":["route"]},{"long_name":"Green Valley","types":["locality","political"],"short_name":"Green Valley"},{"long_name":"Pima County","types":["administrative_area_level_2","political"],"short_name":"Pima County"},{"long_name":"Arizona","short_name":"AZ","types":["administrative_area_level_1","political"]},{"long_name":"United States","types":["country","political"],"short_name":"US"},{"short_name":"85614","long_name":"85614","types":["postal_code"]},{"long_name":"4907","types":["postal_code_suffix"],"short_name":"4907"},{"types":["latitude"],"long_name":31.9027417,"short_name":31.9027417},{"types":["longitude"],"long_name":-110.9992833,"short_name":-110.9992833}],"distance_from":{"mi":{"driving":{"2116 4th Ave, Seattle, WA, 98121":1563.9404973467385},"flying":{"2116 4th Ave, Seattle, WA, 98121":1238.512682217555}}},"duration_from":{"days":{"driving":{"2116 4th Ave, Seattle, WA, 98121":0.9850694444444444}}}} | J37: =GOOGLEMAPS_GET_ADDRESS_COMPONENTS_STRING(F37,false) -> [{"long_name":"1580","short_name":"1580","types":["street_number"]},{"long_name":"West Duval Mine Road","types":["route"],"short_name":"W Duval Mine Rd"},{"types":["locality","political"],"long_name":"Green Valley","short_name":"Green Valley"},{"types":["administrative_area_level_2","political"],"long_name":"Pima County","short_name":"Pima County"},{"long_name":"Arizona","types":["administrative_area_level_1","political"],"short_name":"AZ"},{"short_name":"US","long_name":"United States","types":["country","political"]},{"short_name":"85614","long_name":"85614","types":["postal_code"]},{"short_name":"4907","long_name":"4907","types":["postal_code_suffix"]},{"long_name":"1580","types":["street_number"],"short_name":"1580"},{"short_name":"W Duval Mine Rd","long_name":"West Duval Mine Road","types":["route"]},{"long_name":"Green Valley","types":["locality","political"],"short_name":"Green Valley"},{"long_name":"Pima County","types":["administrative_area_level_2","political"],"short_name":"Pima County"},{"long_name":"Arizona","short_name":"AZ","types":["administrative_area_level_1","political"]},{"long_name":"United States","types":["country","political"],"short_name":"US"},{"short_name":"85614","long_name":"85614","types":["postal_code"]},{"long_name":"4907","types":["postal_code_suffix"],"short_name":"4907"},{"types":["latitude"],"long_name":31.9027417,"short_name":31.9027417},{"types":["longitude"],"long_name":-110.9992833,"short_name":-110.9992833},{"types":["debug_info","cache_load_result"],"long_name":"hit","short_name":"hit"}] | K37: =NOT(AND(NOT(_xlfn.ISFORMULA(P37)),AND(NOT(_xlfn.ISFORMULA(Q37)),AND(NOT(_xlfn.ISFORMULA(R37)),AND(NOT(_xlfn.ISFORMULA(S37)),AND(NOT(_xlfn.ISFORMULA(T37)),AND(NOT(_xlfn.ISFORMULA(U37)),AND(NOT(_xlfn.ISFORMULA(V37)))))))))) -> TRUE | L37: =iferror(SEARCH(P37,F37),-1)>=0 -> FALSE | M37: TRUE | N37: =GOOGLEMAPS_GET_ADDRESS_LATITUDE(F37,true) -> 31.902742 | O37: =GOOGLEMAPS_GET_ADDRESS_LONGITUDE(F37,true) -> -110.99928 | P37: =GOOGLEMAPS_GET_ADDRESS_CITY(F37,true,false) -> Green Valley | Q37: =GOOGLEMAPS_GET_ADDRESS_STATE(F37,true,false) -> Arizona | R37: =GOOGLEMAPS_GET_ADDRESS_POSTAL_CODE(F37,false,false) -> 85614 | S37: =GOOGLEMAPS_GET_ADDRESS_COUNTRY(F37,true,false) -> United States | T37: =IFERROR(GOOGLEMAPS_DISTANCE("2116 4th Ave, Seattle, WA, 98121", F37, "driving")+0,"Not Driveable") -> 1563.9405 | U37: =iferror(GOOGLEMAPS_DURATION("2116 4th Ave, Seattle, WA, 98121", F37, "driving")+0,"Not Driveable") -> 0.98506944 | V37: =GOOGLEMAPS_DISTANCE("2116 4th Ave, Seattle, WA, 98121", F37, "flying")+0 -> 1238.5127 | X37: =if(W37="YES","UNKNOWN","N/A") -> N/A | Z37: N/A
A38: 6 - Flight Worthy | B38: Sitka, AK | E38: 1 – Accessible – Freely | F38: Sitka, AK | G38: =HYPERLINK(CONCAT("https://www.google.com/maps/search/",F38),"Link") -> Link | H38: Cute Towns | I38: =getCacheString(concat("GMPD|",F38)) -> {"address_components":[{"short_name":"Sitka","types":["locality","political"],"long_name":"Sitka"},{"types":["administrative_area_level_2","political"],"short_name":"Sitka City and Borough","long_name":"Sitka City and Borough"},{"long_name":"Alaska","types":["administrative_area_level_1","political"],"short_name":"AK"},{"short_name":"US","long_name":"United States","types":["country","political"]},{"long_name":"402","types":["street_number"],"short_name":"402"},{"types":["route"],"short_name":"Sawmill Creek Rd","long_name":"Sawmill Creek Road"},{"long_name":"Sitka","types":["locality","political"],"short_name":"Sitka"},{"long_name":"Sitka City and Borough","types":["administrative_area_level_2","political"],"short_name":"Sitka City and Borough"},{"short_name":"AK","long_name":"Alaska","types":["administrative_area_level_1","political"]},{"types":["country","political"],"short_name":"US","long_name":"United States"},{"short_name":"99835","long_name":"99835","types":["postal_code"]},{"types":["latitude"],"long_name":57.05321929999999,"short_name":57.05321929999999},{"types":["longitude"],"long_name":-135.3345513,"short_name":-135.3345513}]} | J38: =GOOGLEMAPS_GET_ADDRESS_COMPONENTS_STRING(F38,false) -> [{"short_name":"Sitka","types":["locality","political"],"long_name":"Sitka"},{"types":["administrative_area_level_2","political"],"short_name":"Sitka City and Borough","long_name":"Sitka City and Borough"},{"long_name":"Alaska","types":["administrative_area_level_1","political"],"short_name":"AK"},{"short_name":"US","long_name":"United States","types":["country","political"]},{"long_name":"402","types":["street_number"],"short_name":"402"},{"types":["route"],"short_name":"Sawmill Creek Rd","long_name":"Sawmill Creek Road"},{"long_name":"Sitka","types":["locality","political"],"short_name":"Sitka"},{"long_name":"Sitka City and Borough","types":["administrative_area_level_2","political"],"short_name":"Sitka City and Borough"},{"short_name":"AK","long_name":"Alaska","types":["administrative_area_level_1","political"]},{"types":["country","political"],"short_name":"US","long_name":"United States"},{"short_name":"99835","long_name":"99835","types":["postal_code"]},{"types":["latitude"],"long_name":57.05321929999999,"short_name":57.05321929999999},{"types":["longitude"],"long_name":-135.3345513,"short_name":-135.3345513},{"types":["debug_info","cache_load_result"],"long_name":"hit","short_name":"hit"}] | K38: =NOT(AND(NOT(_xlfn.ISFORMULA(P38)),AND(NOT(_xlfn.ISFORMULA(Q38)),AND(NOT(_xlfn.ISFORMULA(R38)),AND(NOT(_xlfn.ISFORMULA(S38)),AND(NOT(_xlfn.ISFORMULA(T38)),AND(NOT(_xlfn.ISFORMULA(U38)),AND(NOT(_xlfn.ISFORMULA(V38)),AND(NOT(_xlfn.ISFORMULA(N38)),NOT(_xlfn.ISFORMULA(O38))))))))))) -> FALSE | L38: =iferror(SEARCH(P38,F38),-1)>=0 -> TRUE | M38: TRUE | N38: 57.053219 | O38: -135.33455 | P38: Sitka | Q38: Alaska | R38: 99835 | S38: United States | T38: Not Driveable | U38: Not Driveable | V38: 849.31 | X38: =if(W38="YES","UNKNOWN","N/A") -> N/A | Z38: N/A
A39: 6 - Flight Worthy | B39: The Willows Inn | E39: 1 – Accessible – Freely | F39: 2579 W Shore Dr, Lummi Island, WA 98262 | G39: =HYPERLINK(CONCAT("https://www.google.com/maps/search/",F39),"Link") -> Link | H39: Destination Dining | I39: =getCacheString(concat("GMPD|",F39)) -> {"address_components":[{"long_name":"2579","short_name":"2579","types":["street_number"]},{"long_name":"West Shore Drive","types":["route"],"short_name":"W Shore Dr"},{"short_name":"Lummi Island","long_name":"Lummi Island","types":["locality","political"]},{"long_name":"Whatcom County","types":["administrative_area_level_2","political"],"short_name":"Whatcom County"},{"long_name":"Washington","types":["administrative_area_level_1","political"],"short_name":"WA"},{"short_name":"US","types":["country","political"],"long_name":"United States"},{"long_name":"98262","types":["postal_code"],"short_name":"98262"},{"long_name":"8667","types":["postal_code_suffix"],"short_name":"8667"},{"short_name":"2579","long_name":"2579","types":["street_number"]},{"short_name":"W Shore Dr","long_name":"West Shore Drive","types":["route"]},{"short_name":"Lummi Island","types":["locality","political"],"long_name":"Lummi Island"},{"short_name":"Whatcom County","types":["administrative_area_level_2","political"],"long_name":"Whatcom County"},{"long_name":"Washington","short_name":"WA","types":["administrative_area_level_1","political"]},{"short_name":"US","long_name":"United States","types":["country","political"]},{"short_name":"98262","long_name":"98262","types":["postal_code"]},{"long_name":"8667","types":["postal_code_suffix"],"short_name":"8667"},{"types":["latitude"],"long_name":48.7354072,"short_name":48.7354072},{"types":["longitude"],"long_name":-122.7188042,"short_name":-122.7188042}]} | J39: =GOOGLEMAPS_GET_ADDRESS_COMPONENTS_STRING(F39,false) -> [{"long_name":"2579","short_name":"2579","types":["street_number"]},{"long_name":"West Shore Drive","types":["route"],"short_name":"W Shore Dr"},{"short_name":"Lummi Island","long_name":"Lummi Island","types":["locality","political"]},{"long_name":"Whatcom County","types":["administrative_area_level_2","political"],"short_name":"Whatcom County"},{"long_name":"Washington","types":["administrative_area_level_1","political"],"short_name":"WA"},{"short_name":"US","types":["country","political"],"long_name":"United States"},{"long_name":"98262","types":["postal_code"],"short_name":"98262"},{"long_name":"8667","types":["postal_code_suffix"],"short_name":"8667"},{"short_name":"2579","long_name":"2579","types":["street_number"]},{"short_name":"W Shore Dr","long_name":"West Shore Drive","types":["route"]},{"short_name":"Lummi Island","types":["locality","political"],"long_name":"Lummi Island"},{"short_name":"Whatcom County","types":["administrative_area_level_2","political"],"long_name":"Whatcom County"},{"long_name":"Washington","short_name":"WA","types":["administrative_area_level_1","political"]},{"short_name":"US","long_name":"United States","types":["country","political"]},{"short_name":"98262","long_name":"98262","types":["postal_code"]},{"long_name":"8667","types":["postal_code_suffix"],"short_name":"8667"},{"types":["latitude"],"long_name":48.7354072,"short_name":48.7354072},{"types":["longitude"],"long_name":-122.7188042,"short_name":-122.7188042},{"types":["debug_info","cache_load_result"],"long_name":"hit","short_name":"hit"}] | K39: =NOT(AND(NOT(_xlfn.ISFORMULA(P39)),AND(NOT(_xlfn.ISFORMULA(Q39)),AND(NOT(_xlfn.ISFORMULA(R39)),AND(NOT(_xlfn.ISFORMULA(S39)),AND(NOT(_xlfn.ISFORMULA(T39)),AND(NOT(_xlfn.ISFORMULA(U39)),AND(NOT(_xlfn.ISFORMULA(V39)),AND(NOT(_xlfn.ISFORMULA(N39)),NOT(_xlfn.ISFORMULA(O39))))))))))) -> FALSE | L39: =iferror(SEARCH(P39,F39),-1)>=0 -> TRUE | M39: TRUE | N39: 48.73542 | O39: -122.71879 | P39: Lummi Island | Q39: Washington | R39: 98262 | S39: United States | T39: 109.9 | U39: 0.10614583 | V39: 79.39 | X39: =if(W39="YES","UNKNOWN","N/A") -> N/A | Z39: N/A
A40: 6 - Flight Worthy | B40: Carneros Resort and Spa | E40: 1 – Accessible – Freely | F40: 4048 Sonoma Hwy, Napa, CA 94559 | G40: =HYPERLINK(CONCAT("https://www.google.com/maps/search/",F40),"Link") -> Link | H40: Destination Retreat / Getaway | I40: =getCacheString(concat("GMPD|",F40)) -> {"address_components":[{"long_name":"4048","types":["street_number"],"short_name":"4048"},{"long_name":"Sonoma Highway","short_name":"Sonoma Hwy","types":["route"]},{"long_name":"Napa","short_name":"Napa","types":["locality","political"]},{"long_name":"Napa County","short_name":"Napa County","types":["administrative_area_level_2","political"]},{"short_name":"CA","long_name":"California","types":["administrative_area_level_1","political"]},{"long_name":"United States","types":["country","political"],"short_name":"US"},{"long_name":"94559","types":["postal_code"],"short_name":"94559"},{"long_name":"9749","types":["postal_code_suffix"],"short_name":"9749"},{"types":["street_number"],"long_name":"4048","short_name":"4048"},{"long_name":"Sonoma Highway","short_name":"Sonoma Hwy","types":["route"]},{"long_name":"Napa","types":["locality","political"],"short_name":"Napa"},{"long_name":"Napa County","short_name":"Napa County","types":["administrative_area_level_2","political"]},{"long_name":"California","short_name":"CA","types":["administrative_area_level_1","political"]},{"short_name":"US","types":["country","political"],"long_name":"United States"},{"types":["postal_code"],"long_name":"94559","short_name":"94559"},{"long_name":"9745","short_name":"9745","types":["postal_code_suffix"]},{"types":["latitude"],"long_name":38.2561393,"short_name":38.2561393},{"types":["longitude"],"long_name":-122.3341343,"short_name":-122.3341343}]} | J40: =GOOGLEMAPS_GET_ADDRESS_COMPONENTS_STRING(F40,false) -> [{"long_name":"4048","types":["street_number"],"short_name":"4048"},{"long_name":"Sonoma Highway","short_name":"Sonoma Hwy","types":["route"]},{"long_name":"Napa","short_name":"Napa","types":["locality","political"]},{"long_name":"Napa County","short_name":"Napa County","types":["administrative_area_level_2","political"]},{"short_name":"CA","long_name":"California","types":["administrative_area_level_1","political"]},{"long_name":"United States","types":["country","political"],"short_name":"US"},{"long_name":"94559","types":["postal_code"],"short_name":"94559"},{"long_name":"9749","types":["postal_code_suffix"],"short_name":"9749"},{"types":["street_number"],"long_name":"4048","short_name":"4048"},{"long_name":"Sonoma Highway","short_name":"Sonoma Hwy","types":["route"]},{"long_name":"Napa","types":["locality","political"],"short_name":"Napa"},{"long_name":"Napa County","short_name":"Napa County","types":["administrative_area_level_2","political"]},{"long_name":"California","short_name":"CA","types":["administrative_area_level_1","political"]},{"short_name":"US","types":["country","political"],"long_name":"United States"},{"types":["postal_code"],"long_name":"94559","short_name":"94559"},{"long_name":"9745","short_name":"9745","types":["postal_code_suffix"]},{"types":["latitude"],"long_name":38.2561393,"short_name":38.2561393},{"types":["longitude"],"long_name":-122.3341343,"short_name":-122.3341343},{"types":["debug_info","cache_load_result"],"long_name":"hit","short_name":"hit"}] | K40: =NOT(AND(NOT(_xlfn.ISFORMULA(P40)),AND(NOT(_xlfn.ISFORMULA(Q40)),AND(NOT(_xlfn.ISFORMULA(R40)),AND(NOT(_xlfn.ISFORMULA(S40)),AND(NOT(_xlfn.ISFORMULA(T40)),AND(NOT(_xlfn.ISFORMULA(U40)),AND(NOT(_xlfn.ISFORMULA(V40)),AND(NOT(_xlfn.ISFORMULA(N40)),NOT(_xlfn.ISFORMULA(O40))))))))))) -> FALSE | L40: =iferror(SEARCH(P40,F40),-1)>=0 -> TRUE | M40: TRUE | N40: 38.255411 | O40: -122.33247 | P40: Napa | Q40: California | R40: 94559 | S40: United States | T40: 779.8 | U40: 0.52818287 | V40: 646.64 | X40: =if(W40="YES","UNKNOWN","N/A") -> N/A | Z40: N/A
A41: 6 - Flight Worthy | B41: Kennecott Mining Town | C41: Established in 1903, the copper mine and its town were home to miners and their families until 1938 when the copper ore was depleted and the town abandoned. | D41: Located in the remote Wrangell-St. Elias National Park, Kennecott is one of the best-preserved examples of its kind in the world. Established in 1903, the copper mine and its town were home to miners and their families until 1938 when the copper ore was depleted and the town abandoned. Between 1911 and 1938, the mine processed more than $200 million in copper ore. The mine and its town are now a National Historic Landmark and the site has become one of Alaska’s most visited tourist destinations. A guide is required to explore the iconic red mill building that stands 14 stories tall and overlooks the Kennicott glacier. | F41: Kennecott, AK | G41: =HYPERLINK(CONCAT("https://www.google.com/maps/search/",F41),"Link") -> Link | H41: Ghost Town | I41: =getCacheString(concat("GMPD|",F41)) -> {"address_components":[{"long_name":"Kennicott","short_name":"Kennicott","types":["colloquial_area","political"]},{"short_name":"McCarthy","types":["locality","political"],"long_name":"McCarthy"},{"long_name":"Copper River Census Area","types":["administrative_area_level_2","political"],"short_name":"Copper River Census Area"},{"types":["administrative_area_level_1","political"],"long_name":"Alaska","short_name":"AK"},{"short_name":"US","long_name":"United States","types":["country","political"]},{"short_name":"99566","types":["postal_code"],"long_name":"99566"},{"long_name":"F4P7+HC","short_name":"F4P7+HC","types":["plus_code"]},{"short_name":"McCarthy","long_name":"McCarthy","types":["locality","political"]},{"short_name":"Copper River Census Area","types":["administrative_area_level_2","political"],"long_name":"Copper River Census Area"},{"types":["administrative_area_level_1","political"],"long_name":"Alaska","short_name":"AK"},{"types":["country","political"],"long_name":"United States","short_name":"US"},{"short_name":"99566","types":["postal_code"],"long_name":"99566"},{"types":["latitude"],"long_name":61.48638889999999,"short_name":61.48638889999999},{"types":["longitude"],"long_name":-142.8863888,"short_name":-142.8863888}],"duration_from":{"days":{"driving":{"2116 4th Ave, Seattle, WA, 98121":1.7155439814814815}}},"distance_from":{"mi":{"driving":{"2116 4th Ave, Seattle, WA, 98121":2217.486050182062},"flying":{"2116 4th Ave, Seattle, WA, 98121":1252.4848695738626}}}} | J41: =GOOGLEMAPS_GET_ADDRESS_COMPONENTS_STRING(F41,false) -> [{"long_name":"Kennicott","short_name":"Kennicott","types":["colloquial_area","political"]},{"short_name":"McCarthy","types":["locality","political"],"long_name":"McCarthy"},{"long_name":"Copper River Census Area","types":["administrative_area_level_2","political"],"short_name":"Copper River Census Area"},{"types":["administrative_area_level_1","political"],"long_name":"Alaska","short_name":"AK"},{"short_name":"US","long_name":"United States","types":["country","political"]},{"short_name":"99566","types":["postal_code"],"long_name":"99566"},{"long_name":"F4P7+HC","short_name":"F4P7+HC","types":["plus_code"]},{"short_name":"McCarthy","long_name":"McCarthy","types":["locality","political"]},{"short_name":"Copper River Census Area","types":["administrative_area_level_2","political"],"long_name":"Copper River Census Area"},{"types":["administrative_area_level_1","political"],"long_name":"Alaska","short_name":"AK"},{"types":["country","political"],"long_name":"United States","short_name":"US"},{"short_name":"99566","types":["postal_code"],"long_name":"99566"},{"types":["latitude"],"long_name":61.48638889999999,"short_name":61.48638889999999},{"types":["longitude"],"long_name":-142.8863888,"short_name":-142.8863888},{"types":["debug_info","cache_load_result"],"long_name":"hit","short_name":"hit"}] | K41: =NOT(AND(NOT(_xlfn.ISFORMULA(P41)),AND(NOT(_xlfn.ISFORMULA(Q41)),AND(NOT(_xlfn.ISFORMULA(R41)),AND(NOT(_xlfn.ISFORMULA(S41)),AND(NOT(_xlfn.ISFORMULA(T41)),AND(NOT(_xlfn.ISFORMULA(U41)),AND(NOT(_xlfn.ISFORMULA(V41)))))))))) -> TRUE | L41: =iferror(SEARCH(P41,F41),-1)>=0 -> FALSE | M41: TRUE | N41: =GOOGLEMAPS_GET_ADDRESS_LATITUDE(F41,true) -> 61.486389 | O41: =GOOGLEMAPS_GET_ADDRESS_LONGITUDE(F41,true) -> -142.88639 | P41: =GOOGLEMAPS_GET_ADDRESS_CITY(F41,true,false) -> McCarthy | Q41: =GOOGLEMAPS_GET_ADDRESS_STATE(F41,true,false) -> Alaska | R41: =GOOGLEMAPS_GET_ADDRESS_POSTAL_CODE(F41,false,false) -> 99566 | S41: =GOOGLEMAPS_GET_ADDRESS_COUNTRY(F41,true,false) -> United States | T41: =IFERROR(GOOGLEMAPS_DISTANCE("2116 4th Ave, Seattle, WA, 98121", F41, "driving")+0,"Not Driveable") -> 2217.486 | U41: =iferror(GOOGLEMAPS_DURATION("2116 4th Ave, Seattle, WA, 98121", F41, "driving")+0,"Not Driveable") -> 1.715544 | V41: =GOOGLEMAPS_DISTANCE("2116 4th Ave, Seattle, WA, 98121", F41, "flying")+0 -> 1252.4849 | X41: =if(W41="YES","UNKNOWN","N/A") -> N/A | Z41: N/A | AB41: https://en.wikipedia.org/wiki/Kennecott,_Alaska | AF41: Old Mining Town
A42: 6 - Flight Worthy | B42: Churchill, Canada – Polarbear Town | C42: A Canadian Town for Polar Bears | F42: Churchill, Canada | G42: =HYPERLINK(CONCAT("https://www.google.com/maps/search/",F42),"Link") -> Link | H42: Nature | I42: =getCacheString(concat("GMPD|",F42)) -> {"address_components":[{"long_name":"Churchill","types":["locality","political"],"short_name":"Churchill"},{"long_name":"Churchill","types":["administrative_area_level_2","political"],"short_name":"Churchill"},{"types":["administrative_area_level_1","political"],"short_name":"MB","long_name":"Manitoba"},{"long_name":"Canada","short_name":"CA","types":["country","political"]},{"long_name":"R0B 0E0","short_name":"R0B 0E0","types":["postal_code"]},{"types":["street_number"],"long_name":"268","short_name":"268"},{"short_name":"Kelsey Blvd","long_name":"Kelsey Boulevard","types":["route"]},{"long_name":"Churchill","types":["locality","political"],"short_name":"Churchill"},{"short_name":"Churchill","long_name":"Churchill","types":["administrative_area_level_2","political"]},{"short_name":"MB","types":["administrative_area_level_1","political"],"long_name":"Manitoba"},{"long_name":"Canada","types":["country","political"],"short_name":"CA"},{"long_name":"R0B 0E0","types":["postal_code"],"short_name":"R0B 0E0"},{"types":["latitude"],"long_name":58.7679415,"short_name":58.7679415},{"types":["longitude"],"long_name":-94.1695807,"short_name":-94.1695807}],"duration_from":{"days":{"driving":{"2116 4th Ave, Seattle, WA, 98121":"GOOGLE_MAPS_ERROR_CACHED - No route found!"}}},"distance_from":{"mi":{"driving":{"2116 4th Ave, Seattle, WA, 98121":"GOOGLE_MAPS_ERROR_CACHED - No route found!"},"flying":{"2116 4th Ave, Seattle, WA, 98121":1381.7341270334423}}}} | J42: =GOOGLEMAPS_GET_ADDRESS_COMPONENTS_STRING(F42,false) -> [{"long_name":"Churchill","types":["locality","political"],"short_name":"Churchill"},{"long_name":"Churchill","types":["administrative_area_level_2","political"],"short_name":"Churchill"},{"types":["administrative_area_level_1","political"],"short_name":"MB","long_name":"Manitoba"},{"long_name":"Canada","short_name":"CA","types":["country","political"]},{"long_name":"R0B 0E0","short_name":"R0B 0E0","types":["postal_code"]},{"types":["street_number"],"long_name":"268","short_name":"268"},{"short_name":"Kelsey Blvd","long_name":"Kelsey Boulevard","types":["route"]},{"long_name":"Churchill","types":["locality","political"],"short_name":"Churchill"},{"short_name":"Churchill","long_name":"Churchill","types":["administrative_area_level_2","political"]},{"short_name":"MB","types":["administrative_area_level_1","political"],"long_name":"Manitoba"},{"long_name":"Canada","types":["country","political"],"short_name":"CA"},{"long_name":"R0B 0E0","types":["postal_code"],"short_name":"R0B 0E0"},{"types":["latitude"],"long_name":58.7679415,"short_name":58.7679415},{"types":["longitude"],"long_name":-94.1695807,"short_name":-94.1695807},{"types":["debug_info","cache_load_result"],"long_name":"hit","short_name":"hit"}] | K42: =NOT(AND(NOT(_xlfn.ISFORMULA(P42)),AND(NOT(_xlfn.ISFORMULA(Q42)),AND(NOT(_xlfn.ISFORMULA(R42)),AND(NOT(_xlfn.ISFORMULA(S42)),AND(NOT(_xlfn.ISFORMULA(T42)),AND(NOT(_xlfn.ISFORMULA(U42)),AND(NOT(_xlfn.ISFORMULA(V42)),AND(NOT(_xlfn.ISFORMULA(N42)),NOT(_xlfn.ISFORMULA(O42))))))))))) -> TRUE | L42: =iferror(SEARCH(P42,F42),-1)>=0 -> TRUE | M42: FALSE | N42: =GOOGLEMAPS_GET_ADDRESS_LATITUDE(F42,true) -> 58.767941 | O42: =GOOGLEMAPS_GET_ADDRESS_LONGITUDE(F42,true) -> -94.169581 | P42: =GOOGLEMAPS_GET_ADDRESS_CITY(F42,true,false) -> Churchill | Q42: =GOOGLEMAPS_GET_ADDRESS_CITY(G42,true,false) -> #ERROR! | R42: =GOOGLEMAPS_GET_ADDRESS_POSTAL_CODE(F42,false,false) -> R0B 0E0 | S42: =GOOGLEMAPS_GET_ADDRESS_COUNTRY(F42,true,false) -> Canada | T42: =IFERROR(GOOGLEMAPS_DISTANCE("2116 4th Ave, Seattle, WA, 98121", F42, "driving")+0,"Not Driveable") -> Not Driveable | U42: =iferror(GOOGLEMAPS_DURATION("2116 4th Ave, Seattle, WA, 98121", F42, "driving")+0,"Not Driveable") -> Not Driveable | V42: =GOOGLEMAPS_DISTANCE("2116 4th Ave, Seattle, WA, 98121", F42, "flying")+0 -> 1381.7341 | X42: =if(W42="YES","UNKNOWN","N/A") -> N/A | Z42: N/A
A43: 6 - Flight Worthy | B43: Cave of Crystals | F43: Cave of Crystlas, Mexico | G43: =HYPERLINK(CONCAT("https://www.google.com/maps/search/",F43),"Link") -> Link | H43: Nature | I43: =getCacheString(concat("GMPD|",F43)) -> {"address_components":[{"short_name":"7","types":["street_number"],"long_name":"7"},{"long_name":"Terreros","types":["route"],"short_name":"Terreros"},{"short_name":"Naica","long_name":"Naica","types":["locality","political"]},{"long_name":"Chihuahua","types":["administrative_area_level_1","political"],"short_name":"Chih."},{"types":["country","political"],"long_name":"Mexico","short_name":"MX"},{"long_name":"33640","types":["postal_code"],"short_name":"33640"},{"types":["street_number"],"long_name":"7","short_name":"7"},{"short_name":"Terreros","types":["route"],"long_name":"Terreros"},{"short_name":"Naica","long_name":"Naica","types":["locality","political"]},{"long_name":"Chihuahua","types":["administrative_area_level_1","political"],"short_name":"Chih."},{"short_name":"MX","long_name":"Mexico","types":["country","political"]},{"long_name":"33640","types":["postal_code"],"short_name":"33640"},{"types":["latitude"],"long_name":27.850833,"short_name":27.850833},{"types":["longitude"],"long_name":-105.496389,"short_name":-105.496389}],"distance_from":{"mi":{"flying":{"2116 4th Ave, Seattle, WA, 98121":1638.9159531236407},"driving":{"2116 4th Ave, Seattle, WA, 98121":2014.0181689388198}}},"duration_from":{"days":{"driving":{"2116 4th Ave, Seattle, WA, 98121":1.3024074074074075}}}} | J43: =GOOGLEMAPS_GET_ADDRESS_COMPONENTS_STRING(F43,false) -> [{"short_name":"7","types":["street_number"],"long_name":"7"},{"long_name":"Terreros","types":["route"],"short_name":"Terreros"},{"short_name":"Naica","long_name":"Naica","types":["locality","political"]},{"long_name":"Chihuahua","types":["administrative_area_level_1","political"],"short_name":"Chih."},{"types":["country","political"],"long_name":"Mexico","short_name":"MX"},{"long_name":"33640","types":["postal_code"],"short_name":"33640"},{"types":["street_number"],"long_name":"7","short_name":"7"},{"short_name":"Terreros","types":["route"],"long_name":"Terreros"},{"short_name":"Naica","long_name":"Naica","types":["locality","political"]},{"long_name":"Chihuahua","types":["administrative_area_level_1","political"],"short_name":"Chih."},{"short_name":"MX","long_name":"Mexico","types":["country","political"]},{"long_name":"33640","types":["postal_code"],"short_name":"33640"},{"types":["latitude"],"long_name":27.850833,"short_name":27.850833},{"types":["longitude"],"long_name":-105.496389,"short_name":-105.496389},{"types":["debug_info","cache_load_result"],"long_name":"hit","short_name":"hit"}] | K43: =NOT(AND(NOT(_xlfn.ISFORMULA(P43)),AND(NOT(_xlfn.ISFORMULA(Q43)),AND(NOT(_xlfn.ISFORMULA(R43)),AND(NOT(_xlfn.ISFORMULA(S43)),AND(NOT(_xlfn.ISFORMULA(T43)),AND(NOT(_xlfn.ISFORMULA(U43)),AND(NOT(_xlfn.ISFORMULA(V43)))))))))) -> TRUE | L43: =iferror(SEARCH(P43,F43),-1)>=0 -> FALSE | M43: TRUE | N43: =GOOGLEMAPS_GET_ADDRESS_LATITUDE(F43,true) -> 27.850833 | O43: =GOOGLEMAPS_GET_ADDRESS_LONGITUDE(F43,true) -> -105.49639 | P43: =GOOGLEMAPS_GET_ADDRESS_CITY(F43,true,false) -> Naica | Q43: =GOOGLEMAPS_GET_ADDRESS_STATE(F43,true,false) -> Chihuahua | R43: =GOOGLEMAPS_GET_ADDRESS_POSTAL_CODE(F43,false,false) -> 33640 | S43: =GOOGLEMAPS_GET_ADDRESS_COUNTRY(F43,true,false) -> Mexico | T43: =IFERROR(GOOGLEMAPS_DISTANCE("2116 4th Ave, Seattle, WA, 98121", F43, "driving")+0,"Not Driveable") -> 2014.0182 | U43: =iferror(GOOGLEMAPS_DURATION("2116 4th Ave, Seattle, WA, 98121", F43, "driving")+0,"Not Driveable") -> 1.3024074 | V43: =GOOGLEMAPS_DISTANCE("2116 4th Ave, Seattle, WA, 98121", F43, "flying")+0 -> 1638.916 | X43: =if(W43="YES","UNKNOWN","N/A") -> N/A | Z43: N/A
A44: 6 - Flight Worthy | B44: Carbide Wilson Ruins | F44: Carbide Wilson, Quebec, Canada | G44: =HYPERLINK(CONCAT("https://www.google.com/maps/search/",F44),"Link") -> Link | H44: Ghost Town | I44: =getCacheString(concat("GMPD|",F44)) -> {"address_components":[{"long_name":"639","short_name":"639","types":["street_number"]},{"long_name":"Chemin du Lac-Meech","types":["route"],"short_name":"Chem. du Lac-Meech"},{"short_name":"Chelsea","types":["locality","political"],"long_name":"Chelsea"},{"long_name":"Les Collines-de-l'Outaouais","short_name":"Les Collines-de-l'Outaouais","types":["administrative_area_level_3","political"]},{"long_name":"Outaouais","types":["administrative_area_level_2","political"],"short_name":"Outaouais"},{"long_name":"Québec","types":["administrative_area_level_1","political"],"short_name":"QC"},{"short_name":"CA","types":["country","political"],"long_name":"Canada"},{"long_name":"J9B 1H9","types":["postal_code"],"short_name":"J9B 1H9"},{"short_name":"639","types":["street_number"],"long_name":"639"},{"types":["route"],"long_name":"Chemin du Lac-Meech","short_name":"Chem. du Lac-Meech"},{"long_name":"Chelsea","short_name":"Chelsea","types":["locality","political"]},{"long_name":"Les Collines-de-l'Outaouais","short_name":"Les Collines-de-l'Outaouais","types":["administrative_area_level_3","political"]},{"long_name":"Outaouais","types":["administrative_area_level_2","political"],"short_name":"Outaouais"},{"types":["administrative_area_level_1","political"],"short_name":"QC","long_name":"Québec"},{"long_name":"Canada","short_name":"CA","types":["country","political"]},{"long_name":"J9B 1H9","types":["postal_code"],"short_name":"J9B 1H9"},{"types":["latitude"],"long_name":45.5384189,"short_name":45.5384189},{"types":["longitude"],"long_name":-75.86798619999999,"short_name":-75.86798619999999}],"distance_from":{"mi":{"flying":{"2116 4th Ave, Seattle, WA, 98121":2178.6396908049264},"driving":{"2116 4th Ave, Seattle, WA, 98121":2569.401742329154}}},"duration_from":{"days":{"driving":{"2116 4th Ave, Seattle, WA, 98121":1.7033333333333334}}}} | J44: =GOOGLEMAPS_GET_ADDRESS_COMPONENTS_STRING(F44,false) -> [{"long_name":"639","short_name":"639","types":["street_number"]},{"long_name":"Chemin du Lac-Meech","types":["route"],"short_name":"Chem. du Lac-Meech"},{"short_name":"Chelsea","types":["locality","political"],"long_name":"Chelsea"},{"long_name":"Les Collines-de-l'Outaouais","short_name":"Les Collines-de-l'Outaouais","types":["administrative_area_level_3","political"]},{"long_name":"Outaouais","types":["administrative_area_level_2","political"],"short_name":"Outaouais"},{"long_name":"Québec","types":["administrative_area_level_1","political"],"short_name":"QC"},{"short_name":"CA","types":["country","political"],"long_name":"Canada"},{"long_name":"J9B 1H9","types":["postal_code"],"short_name":"J9B 1H9"},{"short_name":"639","types":["street_number"],"long_name":"639"},{"types":["route"],"long_name":"Chemin du Lac-Meech","short_name":"Chem. du Lac-Meech"},{"long_name":"Chelsea","short_name":"Chelsea","types":["locality","political"]},{"long_name":"Les Collines-de-l'Outaouais","short_name":"Les Collines-de-l'Outaouais","types":["administrative_area_level_3","political"]},{"long_name":"Outaouais","types":["administrative_area_level_2","political"],"short_name":"Outaouais"},{"types":["administrative_area_level_1","political"],"short_name":"QC","long_name":"Québec"},{"long_name":"Canada","short_name":"CA","types":["country","political"]},{"long_name":"J9B 1H9","types":["postal_code"],"short_name":"J9B 1H9"},{"types":["latitude"],"long_name":45.5384189,"short_name":45.5384189},{"types":["longitude"],"long_name":-75.86798619999999,"short_name":-75.86798619999999},{"types":["debug_info","cache_load_result"],"long_name":"hit","short_name":"hit"}] | K44: =NOT(AND(NOT(_xlfn.ISFORMULA(P44)),AND(NOT(_xlfn.ISFORMULA(Q44)),AND(NOT(_xlfn.ISFORMULA(R44)),AND(NOT(_xlfn.ISFORMULA(S44)),AND(NOT(_xlfn.ISFORMULA(T44)),AND(NOT(_xlfn.ISFORMULA(U44)),AND(NOT(_xlfn.ISFORMULA(V44)))))))))) -> TRUE | L44: =iferror(SEARCH(P44,F44),-1)>=0 -> FALSE | M44: TRUE | N44: =GOOGLEMAPS_GET_ADDRESS_LATITUDE(F44,true) -> 45.538419 | O44: =GOOGLEMAPS_GET_ADDRESS_LONGITUDE(F44,true) -> -75.867986 | P44: =GOOGLEMAPS_GET_ADDRESS_CITY(F44,true,false) -> Chelsea | Q44: =GOOGLEMAPS_GET_ADDRESS_STATE(F44,true,false) -> Québec | R44: =GOOGLEMAPS_GET_ADDRESS_POSTAL_CODE(F44,false,false) -> J9B 1H9 | S44: =GOOGLEMAPS_GET_ADDRESS_COUNTRY(F44,true,false) -> Canada | T44: =IFERROR(GOOGLEMAPS_DISTANCE("2116 4th Ave, Seattle, WA, 98121", F44, "driving")+0,"Not Driveable") -> 2569.4017 | U44: =iferror(GOOGLEMAPS_DURATION("2116 4th Ave, Seattle, WA, 98121", F44, "driving")+0,"Not Driveable") -> 1.7033333 | V44: =GOOGLEMAPS_DISTANCE("2116 4th Ave, Seattle, WA, 98121", F44, "flying")+0 -> 2178.6397 | X44: =if(W44="YES","UNKNOWN","N/A") -> N/A | Z44: N/A | AC44: https://www.youtube.com/watch?v=Qk_gx3CmACY
A45: 6 - Flight Worthy | B45: Festival Internacional Cervantino | E45: 1 – Accessible – Freely | F45: Guanajuato, Mexico | G45: =HYPERLINK(CONCAT("https://www.google.com/maps/search/",F45),"Link") -> Link | H45: Festival | I45: =getCacheString(concat("GMPD|",F45)) -> {"address_components":[{"long_name":"Guanajuato","types":["administrative_area_level_1","political"],"short_name":"Gto."},{"types":["country","political"],"long_name":"Mexico","short_name":"MX"},{"long_name":"WR8Q+R8","short_name":"WR8Q+R8","types":["plus_code"]},{"long_name":"Campuzano","types":["locality","political"],"short_name":"Campuzano"},{"long_name":"Guanajuato","short_name":"Gto.","types":["administrative_area_level_1","political"]},{"types":["country","political"],"long_name":"Mexico","short_name":"MX"},{"short_name":"36225","long_name":"36225","types":["postal_code"]},{"types":["latitude"],"long_name":20.9170187,"short_name":20.9170187},{"types":["longitude"],"long_name":-101.1617356,"short_name":-101.1617356}]} | J45: =GOOGLEMAPS_GET_ADDRESS_COMPONENTS_STRING(F45,false) -> [{"long_name":"Guanajuato","types":["administrative_area_level_1","political"],"short_name":"Gto."},{"types":["country","political"],"long_name":"Mexico","short_name":"MX"},{"long_name":"WR8Q+R8","short_name":"WR8Q+R8","types":["plus_code"]},{"long_name":"Campuzano","types":["locality","political"],"short_name":"Campuzano"},{"long_name":"Guanajuato","short_name":"Gto.","types":["administrative_area_level_1","political"]},{"types":["country","political"],"long_name":"Mexico","short_name":"MX"},{"short_name":"36225","long_name":"36225","types":["postal_code"]},{"types":["latitude"],"long_name":20.9170187,"short_name":20.9170187},{"types":["longitude"],"long_name":-101.1617356,"short_name":-101.1617356},{"types":["debug_info","cache_load_result"],"long_name":"hit","short_name":"hit"}] | K45: =NOT(AND(NOT(_xlfn.ISFORMULA(P45)),AND(NOT(_xlfn.ISFORMULA(Q45)),AND(NOT(_xlfn.ISFORMULA(R45)),AND(NOT(_xlfn.ISFORMULA(S45)),AND(NOT(_xlfn.ISFORMULA(T45)),AND(NOT(_xlfn.ISFORMULA(U45)),AND(NOT(_xlfn.ISFORMULA(V45)),AND(NOT(_xlfn.ISFORMULA(N45)),NOT(_xlfn.ISFORMULA(O45))))))))))) -> FALSE | L45: =iferror(SEARCH(P45,F45),-1)>=0 -> TRUE | M45: TRUE | N45: 21.019015 | O45: -101.25736 | P45: Guanajuato | Q45: Guanajuato | R45: 36000 | S45: Mexico | T45: 2652.4 | U45: 1.8015509 | V45: 2180.81 | X45: =if(W45="YES","UNKNOWN","N/A") -> N/A | Z45: N/A | AB45: https://medium.com/@embamexindia/festival-internacional-cervantino-ac9e13b2092a
A46: 6 - Flight Worthy | B46: Skagaway, AK | E46: 1 – Accessible – Freely | F46: Skagway, AK | G46: =HYPERLINK(CONCAT("https://www.google.com/maps/search/",F46),"Link") -> Link | H46: Other | I46: =getCacheString(concat("GMPD|",F46)) -> {"address_components":[{"long_name":"Skagway","types":["locality","political"],"short_name":"Skagway"},{"long_name":"Skagway Municipality","short_name":"Skagway Municipality","types":["administrative_area_level_2","political"]},{"short_name":"AK","long_name":"Alaska","types":["administrative_area_level_1","political"]},{"types":["country","political"],"long_name":"United States","short_name":"US"},{"short_name":"99840","long_name":"99840","types":["postal_code"]},{"short_name":"701","long_name":"701","types":["street_number"]},{"types":["route"],"long_name":"State Street","short_name":"State St"},{"short_name":"Skagway","long_name":"Skagway","types":["locality","political"]},{"long_name":"Skagway Municipality","types":["administrative_area_level_2","political"],"short_name":"Skagway Municipality"},{"long_name":"Alaska","types":["administrative_area_level_1","political"],"short_name":"AK"},{"types":["country","political"],"long_name":"United States","short_name":"US"},{"long_name":"99840","types":["postal_code"],"short_name":"99840"},{"types":["latitude"],"long_name":59.45717800000001,"short_name":59.45717800000001},{"types":["longitude"],"long_name":-135.3145346,"short_name":-135.3145346}]} | J46: =GOOGLEMAPS_GET_ADDRESS_COMPONENTS_STRING(F46,false) -> [{"long_name":"Skagway","types":["locality","political"],"short_name":"Skagway"},{"long_name":"Skagway Municipality","short_name":"Skagway Municipality","types":["administrative_area_level_2","political"]},{"short_name":"AK","long_name":"Alaska","types":["administrative_area_level_1","political"]},{"types":["country","political"],"long_name":"United States","short_name":"US"},{"short_name":"99840","long_name":"99840","types":["postal_code"]},{"short_name":"701","long_name":"701","types":["street_number"]},{"types":["route"],"long_name":"State Street","short_name":"State St"},{"short_name":"Skagway","long_name":"Skagway","types":["locality","political"]},{"long_name":"Skagway Municipality","types":["administrative_area_level_2","political"],"short_name":"Skagway Municipality"},{"long_name":"Alaska","types":["administrative_area_level_1","political"],"short_name":"AK"},{"types":["country","political"],"long_name":"United States","short_name":"US"},{"long_name":"99840","types":["postal_code"],"short_name":"99840"},{"types":["latitude"],"long_name":59.45717800000001,"short_name":59.45717800000001},{"types":["longitude"],"long_name":-135.3145346,"short_name":-135.3145346},{"types":["debug_info","cache_load_result"],"long_name":"hit","short_name":"hit"}] | K46: =NOT(AND(NOT(_xlfn.ISFORMULA(P46)),AND(NOT(_xlfn.ISFORMULA(Q46)),AND(NOT(_xlfn.ISFORMULA(R46)),AND(NOT(_xlfn.ISFORMULA(S46)),AND(NOT(_xlfn.ISFORMULA(T46)),AND(NOT(_xlfn.ISFORMULA(U46)),AND(NOT(_xlfn.ISFORMULA(V46)),AND(NOT(_xlfn.ISFORMULA(N46)),NOT(_xlfn.ISFORMULA(O46))))))))))) -> FALSE | L46: =iferror(SEARCH(P46,F46),-1)>=0 -> TRUE | M46: TRUE | N46: 59.457178 | O46: -135.31453 | P46: Skagway | Q46: Alaska | R46: 99840 | S46: United States | T46: 1605.3 | U46: 1.2384954 | V46: 972.62 | X46: =if(W46="YES","UNKNOWN","N/A") -> N/A | Z46: N/A | AB46: https://en.wikipedia.org/wiki/Skagway,_Alaska | AF46: Old Mining Town w/ Goldrush Buildings
A47: 6 - Flight Worthy | B47: San Juan Parangaricutiro | F47: San Juan Parangaricutiro, Mexico | G47: =HYPERLINK(CONCAT("https://www.google.com/maps/search/",F47),"Link") -> Link | H47: Ghost Town | I47: =getCacheString(concat("GMPD|",F47)) -> {"address_components":[{"types":["locality","political"],"long_name":"San Juan Parangaricutiro","short_name":"San Juan Parangaricutiro"},{"types":["administrative_area_level_1","political"],"long_name":"Michoacán","short_name":"Mich."},{"short_name":"MX","types":["country","political"],"long_name":"Mexico"},{"types":["postal_code"],"long_name":"60243","short_name":"60243"},{"long_name":"JP97+4Q","short_name":"JP97+4Q","types":["plus_code"]},{"types":["locality","political"],"short_name":"San Juan Parangaricutiro","long_name":"San Juan Parangaricutiro"},{"types":["administrative_area_level_1","political"],"long_name":"Michoacán","short_name":"Mich."},{"types":["country","political"],"long_name":"Mexico","short_name":"MX"},{"short_name":"60243","types":["postal_code"],"long_name":"60243"},{"types":["latitude"],"long_name":19.617778,"short_name":19.617778},{"types":["longitude"],"long_name":-102.285556,"short_name":-102.285556}],"distance_from":{"mi":{"flying":{"2116 4th Ave, Seattle, WA, 98121":2237.598021549207},"driving":{"2116 4th Ave, Seattle, WA, 98121":2737.195993388594}}},"duration_from":{"days":{"driving":{"2116 4th Ave, Seattle, WA, 98121":1.8974884259259257}}}} | J47: =GOOGLEMAPS_GET_ADDRESS_COMPONENTS_STRING(F47,false) -> [{"types":["locality","political"],"long_name":"San Juan Parangaricutiro","short_name":"San Juan Parangaricutiro"},{"types":["administrative_area_level_1","political"],"long_name":"Michoacán","short_name":"Mich."},{"short_name":"MX","types":["country","political"],"long_name":"Mexico"},{"types":["postal_code"],"long_name":"60243","short_name":"60243"},{"long_name":"JP97+4Q","short_name":"JP97+4Q","types":["plus_code"]},{"types":["locality","political"],"short_name":"San Juan Parangaricutiro","long_name":"San Juan Parangaricutiro"},{"types":["administrative_area_level_1","political"],"long_name":"Michoacán","short_name":"Mich."},{"types":["country","political"],"long_name":"Mexico","short_name":"MX"},{"short_name":"60243","types":["postal_code"],"long_name":"60243"},{"types":["latitude"],"long_name":19.617778,"short_name":19.617778},{"types":["longitude"],"long_name":-102.285556,"short_name":-102.285556},{"types":["debug_info","cache_load_result"],"long_name":"hit","short_name":"hit"}] | K47: =NOT(AND(NOT(_xlfn.ISFORMULA(P47)),AND(NOT(_xlfn.ISFORMULA(Q47)),AND(NOT(_xlfn.ISFORMULA(R47)),AND(NOT(_xlfn.ISFORMULA(S47)),AND(NOT(_xlfn.ISFORMULA(T47)),AND(NOT(_xlfn.ISFORMULA(U47)),AND(NOT(_xlfn.ISFORMULA(V47)))))))))) -> TRUE | L47: =iferror(SEARCH(P47,F47),-1)>=0 -> TRUE | M47: TRUE | N47: =GOOGLEMAPS_GET_ADDRESS_LATITUDE(F47,true) -> 19.617778 | O47: =GOOGLEMAPS_GET_ADDRESS_LONGITUDE(F47,true) -> -102.28556 | P47: =GOOGLEMAPS_GET_ADDRESS_CITY(F47,true,false) -> San Juan Parangaricutiro | Q47: =GOOGLEMAPS_GET_ADDRESS_STATE(F47,true,false) -> Michoacán | R47: =GOOGLEMAPS_GET_ADDRESS_POSTAL_CODE(F47,false,false) -> 60243 | S47: =GOOGLEMAPS_GET_ADDRESS_COUNTRY(F47,true,false) -> Mexico | T47: =IFERROR(GOOGLEMAPS_DISTANCE("2116 4th Ave, Seattle, WA, 98121", F47, "driving")+0,"Not Driveable") -> 2737.196 | U47: =iferror(GOOGLEMAPS_DURATION("2116 4th Ave, Seattle, WA, 98121", F47, "driving")+0,"Not Driveable") -> 1.8974884 | V47: =GOOGLEMAPS_DISTANCE("2116 4th Ave, Seattle, WA, 98121", F47, "flying")+0 -> 2237.598 | X47: =if(W47="YES","UNKNOWN","N/A") -> N/A | Z47: N/A | AC47: https://www.youtube.com/watch?v=Qk_gx3CmACY | AF47: Ghost Town Destroyed by Volcano
A48: 6 - Flight Worthy | B48: Chichen Itza Pyramid, Mexico | C48: Tourists were banned from climbing the Chichen Itza Pyramid after a woman tumbled off the pyramid in 2006 | D48: One of the Seven Wonders of the World, the Chichen Itza Pyramid receives thousands of visitors every year. Although it is still allowed to visit the site, climbing the Mayan pyramid has been banned since 2006, when a tourist slipped on the steps and fell to the ground. | F48: Chichen Itza Pyramid, Mexico | G48: =HYPERLINK(CONCAT("https://www.google.com/maps/search/",F48),"Link") -> Link | I48: =getCacheString(concat("GMPD|",F48)) -> {"address_components":[{"long_name":"Tinum","types":["locality","political"],"short_name":"Tinum"},{"short_name":"Yuc.","long_name":"Yucatán","types":["administrative_area_level_1","political"]},{"long_name":"Mexico","short_name":"MX","types":["country","political"]},{"short_name":"97751","long_name":"97751","types":["postal_code"]},{"long_name":"MCMJ+5G","types":["plus_code"],"short_name":"MCMJ+5G"},{"short_name":"Chichén-Itzá","long_name":"Chichén-Itzá","types":["locality","political"]},{"long_name":"Yucatan","types":["administrative_area_level_1","political"],"short_name":"Yuc."},{"long_name":"Mexico","short_name":"MX","types":["country","political"]},{"short_name":"97751","types":["postal_code"],"long_name":"97751"},{"types":["latitude"],"long_name":20.6829859,"short_name":20.6829859},{"types":["longitude"],"long_name":-88.5686491,"short_name":-88.5686491}],"duration_from":{"days":{"driving":{"2116 4th Ave, Seattle, WA, 98121":2.554502314814815}}},"distance_from":{"mi":{"driving":{"2116 4th Ave, Seattle, WA, 98121":3685.4766550262843},"flying":{"2116 4th Ave, Seattle, WA, 98121":2644.078939192464}}}} | J48: =GOOGLEMAPS_GET_ADDRESS_COMPONENTS_STRING(F48,false) -> [{"long_name":"Tinum","types":["locality","political"],"short_name":"Tinum"},{"short_name":"Yuc.","long_name":"Yucatán","types":["administrative_area_level_1","political"]},{"long_name":"Mexico","short_name":"MX","types":["country","political"]},{"short_name":"97751","long_name":"97751","types":["postal_code"]},{"long_name":"MCMJ+5G","types":["plus_code"],"short_name":"MCMJ+5G"},{"short_name":"Chichén-Itzá","long_name":"Chichén-Itzá","types":["locality","political"]},{"long_name":"Yucatan","types":["administrative_area_level_1","political"],"short_name":"Yuc."},{"long_name":"Mexico","short_name":"MX","types":["country","political"]},{"short_name":"97751","types":["postal_code"],"long_name":"97751"},{"types":["latitude"],"long_name":20.6829859,"short_name":20.6829859},{"types":["longitude"],"long_name":-88.5686491,"short_name":-88.5686491},{"types":["debug_info","cache_load_result"],"long_name":"hit","short_name":"hit"}] | K48: =NOT(AND(NOT(_xlfn.ISFORMULA(P48)),AND(NOT(_xlfn.ISFORMULA(Q48)),AND(NOT(_xlfn.ISFORMULA(R48)),AND(NOT(_xlfn.ISFORMULA(S48)),AND(NOT(_xlfn.ISFORMULA(T48)),AND(NOT(_xlfn.ISFORMULA(U48)),AND(NOT(_xlfn.ISFORMULA(V48)))))))))) -> TRUE | L48: =iferror(SEARCH(P48,F48),-1)>=0 -> FALSE | M48: TRUE | N48: =GOOGLEMAPS_GET_ADDRESS_LATITUDE(F48,true) -> 20.682986 | O48: =GOOGLEMAPS_GET_ADDRESS_LONGITUDE(F48,true) -> -88.568649 | P48: =GOOGLEMAPS_GET_ADDRESS_CITY(F48,true,false) -> Tinum | Q48: =GOOGLEMAPS_GET_ADDRESS_STATE(F48,true,false) -> Yucatán | R48: =GOOGLEMAPS_GET_ADDRESS_POSTAL_CODE(F48,false,false) -> 97751 | S48: =GOOGLEMAPS_GET_ADDRESS_COUNTRY(F48,true,false) -> Mexico | T48: =IFERROR(GOOGLEMAPS_DISTANCE("2116 4th Ave, Seattle, WA, 98121", F48, "driving")+0,"Not Driveable") -> 3685.4767 | U48: =iferror(GOOGLEMAPS_DURATION("2116 4th Ave, Seattle, WA, 98121", F48, "driving")+0,"Not Driveable") -> 2.5545023 | V48: =GOOGLEMAPS_DISTANCE("2116 4th Ave, Seattle, WA, 98121", F48, "flying")+0 -> 2644.0789 | X48: =if(W48="YES","UNKNOWN","N/A") -> N/A | Z48: N/A | AB48: https://magazine.lensvid.com/article/fb/1318327108/mysterious-places-in-the-world-that-are-off-limits-to-everyone-and-why/
A49: 6 - Flight Worthy | B49: Barrow, Utqiagvik, Alaska | E49: 1 – Accessible – Freely | F49: Utqiagvik, Alaska | G49: =HYPERLINK(CONCAT("https://www.google.com/maps/search/",F49),"Link") -> Link | H49: World Class Cities and Lands | I49: =getCacheString(concat("GMPD|",F49)) -> {"address_components":[{"types":["locality","political"],"short_name":"Utqiagvik","long_name":"Utqiagvik"},{"long_name":"North Slope Borough","short_name":"North Slope Borough","types":["administrative_area_level_2","political"]},{"types":["administrative_area_level_1","political"],"long_name":"Alaska","short_name":"AK"},{"long_name":"United States","short_name":"US","types":["country","political"]},{"types":["postal_code"],"long_name":"99723","short_name":"99723"},{"short_name":"1052","types":["street_number"],"long_name":"1052"},{"long_name":"Kogiak Street","short_name":"Kogiak St","types":["route"]},{"long_name":"Utqiagvik","short_name":"Utqiagvik","types":["locality","political"]},{"short_name":"North Slope Borough","long_name":"North Slope Borough","types":["administrative_area_level_2","political"]},{"long_name":"Alaska","short_name":"AK","types":["administrative_area_level_1","political"]},{"long_name":"United States","short_name":"US","types":["country","political"]},{"long_name":"99723","short_name":"99723","types":["postal_code"]},{"types":["latitude"],"long_name":71.29055559999999,"short_name":71.29055559999999},{"types":["longitude"],"long_name":-156.7886111,"short_name":-156.7886111}]} | J49: =GOOGLEMAPS_GET_ADDRESS_COMPONENTS_STRING(F49,false) -> [{"types":["locality","political"],"short_name":"Utqiagvik","long_name":"Utqiagvik"},{"long_name":"North Slope Borough","short_name":"North Slope Borough","types":["administrative_area_level_2","political"]},{"types":["administrative_area_level_1","political"],"long_name":"Alaska","short_name":"AK"},{"long_name":"United States","short_name":"US","types":["country","political"]},{"types":["postal_code"],"long_name":"99723","short_name":"99723"},{"short_name":"1052","types":["street_number"],"long_name":"1052"},{"long_name":"Kogiak Street","short_name":"Kogiak St","types":["route"]},{"long_name":"Utqiagvik","short_name":"Utqiagvik","types":["locality","political"]},{"short_name":"North Slope Borough","long_name":"North Slope Borough","types":["administrative_area_level_2","political"]},{"long_name":"Alaska","short_name":"AK","types":["administrative_area_level_1","political"]},{"long_name":"United States","short_name":"US","types":["country","political"]},{"long_name":"99723","short_name":"99723","types":["postal_code"]},{"types":["latitude"],"long_name":71.29055559999999,"short_name":71.29055559999999},{"types":["longitude"],"long_name":-156.7886111,"short_name":-156.7886111},{"types":["debug_info","cache_load_result"],"long_name":"hit","short_name":"hit"}] | K49: =NOT(AND(NOT(_xlfn.ISFORMULA(P49)),AND(NOT(_xlfn.ISFORMULA(Q49)),AND(NOT(_xlfn.ISFORMULA(R49)),AND(NOT(_xlfn.ISFORMULA(S49)),AND(NOT(_xlfn.ISFORMULA(T49)),AND(NOT(_xlfn.ISFORMULA(U49)),AND(NOT(_xlfn.ISFORMULA(V49)),AND(NOT(_xlfn.ISFORMULA(N49)),NOT(_xlfn.ISFORMULA(O49))))))))))) -> FALSE | L49: =iferror(SEARCH(P49,F49),-1)>=0 -> TRUE | M49: TRUE | N49: 71.290556 | O49: -156.78861 | P49: Utqiagvik | Q49: Alaska | R49: 99723 | S49: United States | T49: Not Driveable | U49: Not Driveable | V49: 1976.66 | X49: =if(W49="YES","UNKNOWN","N/A") -> N/A | Z49: N/A
A50: 6 - Flight Worthy | B50: Little Diomede Island | E50: 1 – Accessible – Freely | F50: Little Diomede Islands, Alaska | G50: =HYPERLINK(CONCAT("https://www.google.com/maps/search/",F50),"Link") -> Link | H50: World Class Cities and Lands | I50: =getCacheString(concat("GMPD|",F50)) -> {"address_components":[{"short_name":"Little Diomede Island","long_name":"Little Diomede Island","types":["establishment","natural_feature"]},{"long_name":"Nome Census Area","short_name":"Nome Census Area","types":["administrative_area_level_2","political"]},{"long_name":"Alaska","types":["administrative_area_level_1","political"],"short_name":"AK"},{"types":["country","political"],"short_name":"US","long_name":"United States"},{"short_name":"99762","long_name":"99762","types":["postal_code"]},{"types":["plus_code"],"long_name":"Q32G+V7","short_name":"Q32G+V7"},{"short_name":"Diomede","long_name":"Diomede","types":["locality","political"]},{"long_name":"Nome Census Area","types":["administrative_area_level_2","political"],"short_name":"Nome Census Area"},{"types":["administrative_area_level_1","political"],"short_name":"AK","long_name":"Alaska"},{"long_name":"United States","types":["country","political"],"short_name":"US"},{"long_name":"99762","short_name":"99762","types":["postal_code"]},{"types":["latitude"],"long_name":65.7521798,"short_name":65.7521798},{"types":["longitude"],"long_name":-168.924255,"short_name":-168.924255}]} | J50: =GOOGLEMAPS_GET_ADDRESS_COMPONENTS_STRING(F50,false) -> [{"short_name":"Little Diomede Island","long_name":"Little Diomede Island","types":["establishment","natural_feature"]},{"long_name":"Nome Census Area","short_name":"Nome Census Area","types":["administrative_area_level_2","political"]},{"long_name":"Alaska","types":["administrative_area_level_1","political"],"short_name":"AK"},{"types":["country","political"],"short_name":"US","long_name":"United States"},{"short_name":"99762","long_name":"99762","types":["postal_code"]},{"types":["plus_code"],"long_name":"Q32G+V7","short_name":"Q32G+V7"},{"short_name":"Diomede","long_name":"Diomede","types":["locality","political"]},{"long_name":"Nome Census Area","types":["administrative_area_level_2","political"],"short_name":"Nome Census Area"},{"types":["administrative_area_level_1","political"],"short_name":"AK","long_name":"Alaska"},{"long_name":"United States","types":["country","political"],"short_name":"US"},{"long_name":"99762","short_name":"99762","types":["postal_code"]},{"types":["latitude"],"long_name":65.7521798,"short_name":65.7521798},{"types":["longitude"],"long_name":-168.924255,"short_name":-168.924255},{"types":["debug_info","cache_load_result"],"long_name":"hit","short_name":"hit"}] | K50: =NOT(AND(NOT(_xlfn.ISFORMULA(P50)),AND(NOT(_xlfn.ISFORMULA(Q50)),AND(NOT(_xlfn.ISFORMULA(R50)),AND(NOT(_xlfn.ISFORMULA(S50)),AND(NOT(_xlfn.ISFORMULA(T50)),AND(NOT(_xlfn.ISFORMULA(U50)),AND(NOT(_xlfn.ISFORMULA(V50)),AND(NOT(_xlfn.ISFORMULA(N50)),NOT(_xlfn.ISFORMULA(O50))))))))))) -> FALSE | L50: =iferror(SEARCH(P50,F50),-1)>=0 -> TRUE | M50: TRUE | N50: 65.75218 | O50: -168.92425 | P50: Diomede | Q50: Alaska | R50: 99762 | S50: United States | T50: Not Driveable | U50: Not Driveable | V50: 2090.82 | X50: =if(W50="YES","UNKNOWN","N/A") -> N/A | Z50: N/A
A51: 6 - Flight Worthy | B51: Kirovsky, Kamchatka Russia | C51: Abandoned fishing village | F51: Kirovsky, Kamchatka Russia | G51: =HYPERLINK(CONCAT("https://www.google.com/maps/search/",F51),"Link") -> Link | H51: Ghost Town | I51: =getCacheString(concat("GMPD|",F51)) -> {"address_components":[{"types":["locality","political"],"short_name":"Kirovskiy","long_name":"Kirovskiy"},{"long_name":"Sobolevsky District","types":["administrative_area_level_2","political"],"short_name":"Sobolevsky District"},{"long_name":"Kamchatka Krai","short_name":"Kamchatka Krai","types":["administrative_area_level_1","political"]},{"long_name":"Russia","types":["country","political"],"short_name":"RU"},{"short_name":"684200","long_name":"684200","types":["postal_code"]},{"long_name":"7X39+QH","types":["plus_code"],"short_name":"7X39+QH"},{"long_name":"Kirovskiy","short_name":"Kirovskiy","types":["locality","political"]},{"long_name":"Sobolevsky District","short_name":"Sobolevsky District","types":["administrative_area_level_2","political"]},{"types":["administrative_area_level_1","political"],"long_name":"Kamchatka Krai","short_name":"Kamchatka Krai"},{"types":["country","political"],"long_name":"Russia","short_name":"RU"},{"long_name":"684200","types":["postal_code"],"short_name":"684200"},{"types":["latitude"],"long_name":54.254444,"short_name":54.254444},{"types":["longitude"],"long_name":155.968889,"short_name":155.968889}],"distance_from":{"mi":{"driving":{"2116 4th Ave, Seattle, WA, 98121":"GOOGLE_MAPS_ERROR_CACHED - No route found!"},"flying":{"2116 4th Ave, Seattle, WA, 98121":3383.773472355127}}},"duration_from":{"days":{"driving":{"2116 4th Ave, Seattle, WA, 98121":"GOOGLE_MAPS_ERROR_CACHED - No route found!"}}}} | J51: =GOOGLEMAPS_GET_ADDRESS_COMPONENTS_STRING(F51,false) -> [{"types":["locality","political"],"short_name":"Kirovskiy","long_name":"Kirovskiy"},{"long_name":"Sobolevsky District","types":["administrative_area_level_2","political"],"short_name":"Sobolevsky District"},{"long_name":"Kamchatka Krai","short_name":"Kamchatka Krai","types":["administrative_area_level_1","political"]},{"long_name":"Russia","types":["country","political"],"short_name":"RU"},{"short_name":"684200","long_name":"684200","types":["postal_code"]},{"long_name":"7X39+QH","types":["plus_code"],"short_name":"7X39+QH"},{"long_name":"Kirovskiy","short_name":"Kirovskiy","types":["locality","political"]},{"long_name":"Sobolevsky District","short_name":"Sobolevsky District","types":["administrative_area_level_2","political"]},{"types":["administrative_area_level_1","political"],"long_name":"Kamchatka Krai","short_name":"Kamchatka Krai"},{"types":["country","political"],"long_name":"Russia","short_name":"RU"},{"long_name":"684200","types":["postal_code"],"short_name":"684200"},{"types":["latitude"],"long_name":54.254444,"short_name":54.254444},{"types":["longitude"],"long_name":155.968889,"short_name":155.968889},{"types":["debug_info","cache_load_result"],"long_name":"hit","short_name":"hit"}] | K51: =NOT(AND(NOT(_xlfn.ISFORMULA(P51)),AND(NOT(_xlfn.ISFORMULA(Q51)),AND(NOT(_xlfn.ISFORMULA(R51)),AND(NOT(_xlfn.ISFORMULA(S51)),AND(NOT(_xlfn.ISFORMULA(T51)),AND(NOT(_xlfn.ISFORMULA(U51)),AND(NOT(_xlfn.ISFORMULA(V51)))))))))) -> TRUE | L51: =iferror(SEARCH(P51,F51),-1)>=0 -> FALSE | M51: TRUE | N51: =GOOGLEMAPS_GET_ADDRESS_LATITUDE(F51,true) -> 54.254444 | O51: =GOOGLEMAPS_GET_ADDRESS_LONGITUDE(F51,true) -> 155.96889 | P51: =GOOGLEMAPS_GET_ADDRESS_CITY(F51,true,false) -> Kirovskiy | Q51: =GOOGLEMAPS_GET_ADDRESS_STATE(F51,true,false) -> Kamchatka Krai | R51: =GOOGLEMAPS_GET_ADDRESS_POSTAL_CODE(F51,false,false) -> 684200 | S51: =GOOGLEMAPS_GET_ADDRESS_COUNTRY(F51,true,false) -> Russia | T51: =IFERROR(GOOGLEMAPS_DISTANCE("2116 4th Ave, Seattle, WA, 98121", F51, "driving")+0,"Not Driveable") -> Not Driveable | U51: =iferror(GOOGLEMAPS_DURATION("2116 4th Ave, Seattle, WA, 98121", F51, "driving")+0,"Not Driveable") -> Not Driveable | V51: =GOOGLEMAPS_DISTANCE("2116 4th Ave, Seattle, WA, 98121", F51, "flying")+0 -> 3383.7735 | X51: =if(W51="YES","UNKNOWN","N/A") -> N/A | Z51: N/A | AB51: https://www.bbc.co.uk/news/resources/idt-sh/the_town_that_disappeared
A52: 6 - Flight Worthy | B52: Ittoqqortoormiit Greenland Remote Hotel | C52: Could be the most remote hotel on Earth | E52: 1 – Accessible – Freely | F52: Ittoqqortoormiit, Greenland | G52: =HYPERLINK(CONCAT("https://www.google.com/maps/search/",F52),"Link") -> Link | H52: Destination Retreat / Getaway | I52: =getCacheString(concat("GMPD|",F52)) -> {"address_components":[{"long_name":"Ittoqqortoormiit","types":["locality","political"],"short_name":"Ittoqqortoormiit"},{"long_name":"Sermersooq Municipality","types":["administrative_area_level_1","political"],"short_name":"Sermersooq Municipality"},{"types":["country","political"],"long_name":"Greenland","short_name":"GL"},{"short_name":"263","long_name":"263","types":["street_number"]},{"long_name":"Inutsaaip Aqqulaa","types":["route"],"short_name":"Inutsaaip Aqqulaa"},{"types":["locality","political"],"long_name":"Ittoqqortoormiit","short_name":"Ittoqqortoormiit"},{"short_name":"Sermersooq Kommune","long_name":"Sermersooq Kommune","types":["administrative_area_level_1","political"]},{"short_name":"GL","types":["country","political"],"long_name":"Greenland"},{"types":["latitude"],"long_name":70.48556909999999,"short_name":70.48556909999999},{"types":["longitude"],"long_name":-21.9628756,"short_name":-21.9628756}]} | J52: =GOOGLEMAPS_GET_ADDRESS_COMPONENTS_STRING(F52,false) -> [{"long_name":"Ittoqqortoormiit","types":["locality","political"],"short_name":"Ittoqqortoormiit"},{"long_name":"Sermersooq Municipality","types":["administrative_area_level_1","political"],"short_name":"Sermersooq Municipality"},{"types":["country","political"],"long_name":"Greenland","short_name":"GL"},{"short_name":"263","long_name":"263","types":["street_number"]},{"long_name":"Inutsaaip Aqqulaa","types":["route"],"short_name":"Inutsaaip Aqqulaa"},{"types":["locality","political"],"long_name":"Ittoqqortoormiit","short_name":"Ittoqqortoormiit"},{"short_name":"Sermersooq Kommune","long_name":"Sermersooq Kommune","types":["administrative_area_level_1","political"]},{"short_name":"GL","types":["country","political"],"long_name":"Greenland"},{"types":["latitude"],"long_name":70.48556909999999,"short_name":70.48556909999999},{"types":["longitude"],"long_name":-21.9628756,"short_name":-21.9628756},{"types":["debug_info","cache_load_result"],"long_name":"hit","short_name":"hit"}] | K52: =NOT(AND(NOT(_xlfn.ISFORMULA(P52)),AND(NOT(_xlfn.ISFORMULA(Q52)),AND(NOT(_xlfn.ISFORMULA(R52)),AND(NOT(_xlfn.ISFORMULA(S52)),AND(NOT(_xlfn.ISFORMULA(T52)),AND(NOT(_xlfn.ISFORMULA(U52)),AND(NOT(_xlfn.ISFORMULA(V52)),AND(NOT(_xlfn.ISFORMULA(N52)),NOT(_xlfn.ISFORMULA(O52))))))))))) -> FALSE | L52: =iferror(SEARCH(P52,F52),-1)>=0 -> TRUE | M52: TRUE | N52: 70.485569 | O52: -21.962876 | P52: Ittoqqortoormiit | Q52: Sermersooq Municipality | R52: UNDEFINED | S52: Greenland | T52: Not Driveable | U52: Not Driveable | V52: 3387.85 | X52: =if(W52="YES","UNKNOWN","N/A") -> N/A | Z52: N/A | AB52: https://www.cnn.com/travel/article/ittoqqortoormiit-greenland-remote-hotel/index.html | AE52: Most remote hotel on earth
A53: 6 - Flight Worthy | B53: R504 Kolyma Highway – Road of Bones – Bone Highway | F53: R504 Kolyma Highway | G53: =HYPERLINK(CONCAT("https://www.google.com/maps/search/",F53),"Link") -> Link | H53: Military and Heavy Industry | I53: =getCacheString(concat("GMPD|",F53)) -> {"duration_from":{"days":{"driving":{"2116 4th Ave, Seattle, WA, 98121":"GOOGLE_MAPS_ERROR_CACHED - No route found!"}}},"distance_from":{"mi":{"driving":{"2116 4th Ave, Seattle, WA, 98121":"GOOGLE_MAPS_ERROR_CACHED - No route found!"},"flying":{"2116 4th Ave, Seattle, WA, 98121":3587.0282227496987}}},"address_components":[{"long_name":"P-504","types":["route"],"short_name":"P-504"},{"types":["country","political"],"long_name":"Russia","short_name":"RU"},{"long_name":"P-504","short_name":"P-504","types":["route"]},{"short_name":"Tomponskiy Ulus","types":["administrative_area_level_2","political"],"long_name":"Tomponskiy Ulus"},{"long_name":"Respublika Sakha (Yakutiya)","types":["administrative_area_level_1","political"],"short_name":"Respublika Sakha (Yakutiya)"},{"types":["country","political"],"long_name":"Russia","short_name":"RU"},{"short_name":"678640","long_name":"678640","types":["postal_code"]},{"types":["latitude"],"long_name":63.2255969,"short_name":63.2255969},{"types":["longitude"],"long_name":139.5916149,"short_name":139.5916149}]} | J53: =GOOGLEMAPS_GET_ADDRESS_COMPONENTS_STRING(F53,false) -> [{"long_name":"P-504","types":["route"],"short_name":"P-504"},{"types":["country","political"],"long_name":"Russia","short_name":"RU"},{"long_name":"P-504","short_name":"P-504","types":["route"]},{"short_name":"Tomponskiy Ulus","types":["administrative_area_level_2","political"],"long_name":"Tomponskiy Ulus"},{"long_name":"Respublika Sakha (Yakutiya)","types":["administrative_area_level_1","political"],"short_name":"Respublika Sakha (Yakutiya)"},{"types":["country","political"],"long_name":"Russia","short_name":"RU"},{"short_name":"678640","long_name":"678640","types":["postal_code"]},{"types":["latitude"],"long_name":63.2255969,"short_name":63.2255969},{"types":["longitude"],"long_name":139.5916149,"short_name":139.5916149},{"types":["debug_info","cache_load_result"],"long_name":"hit","short_name":"hit"}] | K53: =NOT(AND(NOT(_xlfn.ISFORMULA(P53)),AND(NOT(_xlfn.ISFORMULA(Q53)),AND(NOT(_xlfn.ISFORMULA(R53)),AND(NOT(_xlfn.ISFORMULA(S53)),AND(NOT(_xlfn.ISFORMULA(T53)),AND(NOT(_xlfn.ISFORMULA(U53)),AND(NOT(_xlfn.ISFORMULA(V53)))))))))) -> TRUE | L53: =iferror(SEARCH(P53,F53),-1)>=0 -> FALSE | M53: TRUE | N53: =GOOGLEMAPS_GET_ADDRESS_LATITUDE(F53,true) -> 63.225597 | O53: =GOOGLEMAPS_GET_ADDRESS_LONGITUDE(F53,true) -> 139.59161 | P53: =GOOGLEMAPS_GET_ADDRESS_CITY(F53,true,false) -> UNDEFINED | Q53: =GOOGLEMAPS_GET_ADDRESS_STATE(F53,true,false) -> Respublika Sakha (Yakutiya) | R53: =GOOGLEMAPS_GET_ADDRESS_POSTAL_CODE(F53,false,false) -> 678640 | S53: =GOOGLEMAPS_GET_ADDRESS_COUNTRY(F53,true,false) -> Russia | T53: =IFERROR(GOOGLEMAPS_DISTANCE("2116 4th Ave, Seattle, WA, 98121", F53, "driving")+0,"Not Driveable") -> Not Driveable | U53: =iferror(GOOGLEMAPS_DURATION("2116 4th Ave, Seattle, WA, 98121", F53, "driving")+0,"Not Driveable") -> Not Driveable | V53: =GOOGLEMAPS_DISTANCE("2116 4th Ave, Seattle, WA, 98121", F53, "flying")+0 -> 3587.0282 | X53: =if(W53="YES","UNKNOWN","N/A") -> N/A | Z53: N/A
A54: 6 - Flight Worthy | B54: Cappadocia | E54: 1 – Accessible – Freely | F54: Cappadocia, Turkey | G54: =HYPERLINK(CONCAT("https://www.google.com/maps/search/",F54),"Link") -> Link | H54: World Class Cities and Lands | I54: =getCacheString(concat("GMPD|",F54)) -> {"address_components":[{"short_name":"Cappadocia","long_name":"Cappadocia","types":["colloquial_area","political"]},{"long_name":"Türkiye","short_name":"TR","types":["country","political"]},{"long_name":"کاپادوکیه","types":[],"short_name":""},{"long_name":"Türkiye","short_name":"TR","types":["country","political"]},{"types":["administrative_area_level_4","political"],"short_name":"2. Küme","long_name":"2. Küme"},{"short_name":"Çavuşin","types":["administrative_area_level_3","political"],"long_name":"Çavuşin"},{"types":["administrative_area_level_2","political"],"short_name":"Avanos","long_name":"Avanos"},{"types":["administrative_area_level_1","political"],"long_name":"Nevşehir","short_name":"Nevşehir"},{"types":["postal_code"],"long_name":"50502","short_name":"50502"},{"types":["latitude"],"long_name":38.6586639,"short_name":38.6586639},{"types":["longitude"],"long_name":34.8531604,"short_name":34.8531604}],"distance_from":{"mi":{"driving":{"2116 4th Ave, Seattle, WA, 98121":"GOOGLE_MAPS_ERROR_CACHED - No route found!"},"flying":{"2116 4th Ave, Seattle, WA, 98121":6312.844395839288}}},"duration_from":{"days":{"driving":{"2116 4th Ave, Seattle, WA, 98121":"GOOGLE_MAPS_ERROR_CACHED - No route found!"}}}} | J54: =GOOGLEMAPS_GET_ADDRESS_COMPONENTS_STRING(F54,false) -> [{"short_name":"Cappadocia","long_name":"Cappadocia","types":["colloquial_area","political"]},{"long_name":"Türkiye","short_name":"TR","types":["country","political"]},{"long_name":"کاپادوکیه","types":[],"short_name":""},{"long_name":"Türkiye","short_name":"TR","types":["country","political"]},{"types":["administrative_area_level_4","political"],"short_name":"2. Küme","long_name":"2. Küme"},{"short_name":"Çavuşin","types":["administrative_area_level_3","political"],"long_name":"Çavuşin"},{"types":["administrative_area_level_2","political"],"short_name":"Avanos","long_name":"Avanos"},{"types":["administrative_area_level_1","political"],"long_name":"Nevşehir","short_name":"Nevşehir"},{"types":["postal_code"],"long_name":"50502","short_name":"50502"},{"types":["latitude"],"long_name":38.6586639,"short_name":38.6586639},{"types":["longitude"],"long_name":34.8531604,"short_name":34.8531604},{"types":["debug_info","cache_load_result"],"long_name":"hit","short_name":"hit"}] | K54: =NOT(AND(NOT(_xlfn.ISFORMULA(P54)),AND(NOT(_xlfn.ISFORMULA(Q54)),AND(NOT(_xlfn.ISFORMULA(R54)),AND(NOT(_xlfn.ISFORMULA(S54)),AND(NOT(_xlfn.ISFORMULA(T54)),AND(NOT(_xlfn.ISFORMULA(U54)),AND(NOT(_xlfn.ISFORMULA(V54)))))))))) -> TRUE | L54: =iferror(SEARCH(P54,F54),-1)>=0 -> FALSE | M54: TRUE | N54: =GOOGLEMAPS_GET_ADDRESS_LATITUDE(F54,true) -> 38.658664 | O54: =GOOGLEMAPS_GET_ADDRESS_LONGITUDE(F54,true) -> 34.85316 | P54: =GOOGLEMAPS_GET_ADDRESS_CITY(F54,true,false) -> UNDEFINED | Q54: =GOOGLEMAPS_GET_ADDRESS_STATE(F54,true,false) -> Nevşehir | R54: =GOOGLEMAPS_GET_ADDRESS_POSTAL_CODE(F54,false,false) -> 50502 | S54: =GOOGLEMAPS_GET_ADDRESS_COUNTRY(F54,true,false) -> Türkiye | T54: =IFERROR(GOOGLEMAPS_DISTANCE("2116 4th Ave, Seattle, WA, 98121", F54, "driving")+0,"Not Driveable") -> Not Driveable | U54: =iferror(GOOGLEMAPS_DURATION("2116 4th Ave, Seattle, WA, 98121", F54, "driving")+0,"Not Driveable") -> Not Driveable | V54: =GOOGLEMAPS_DISTANCE("2116 4th Ave, Seattle, WA, 98121", F54, "flying")+0 -> 6312.8444 | X54: =if(W54="YES","UNKNOWN","N/A") -> N/A | Z54: N/A
A55: 6 - Flight Worthy | B55: Chernobyl Exclusion Zone | C55: Over three decades after the Chernobyl disaster, a 1,000-sq-mi exclusion zone remains off-limits | D55: Soon after disaster struck nuclear reactor No. 4 in Chernobyl, the Soviet Army Forces established an Exclusion Zone where radioactive contamination was highest and public access had to be restricted. Today, it remains one of the most radioactive areas in the world and, due to the lack of human activity in the area, it is also a thriving sanctuary for local flora and fauna. | E55: 3 – Accessible – Tour Guide Required | F55: 51.300000, 30.005000 | G55: =HYPERLINK(CONCAT("https://www.google.com/maps/search/",F55),"Link") -> Link | I55: =getCacheString(concat("GMPD|",F55)) -> {"duration_from":{"days":{"driving":{"2116 4th Ave, Seattle, WA, 98121":"GOOGLE_MAPS_ERROR_CACHED - No route found!"}}},"distance_from":{"mi":{"driving":{"2116 4th Ave, Seattle, WA, 98121":"GOOGLE_MAPS_ERROR_CACHED - No route found!"},"flying":{"2116 4th Ave, Seattle, WA, 98121":5408.655722221532}}},"address_components":[{"long_name":"Vulytsya Bez Nazvy","types":["route"],"short_name":"Vulytsya Bez Nazvy"},{"types":["administrative_area_level_2","political"],"long_name":"Ivankivs'kyi district","short_name":"Ivankivs'kyi district"},{"types":["administrative_area_level_1","political"],"short_name":"Kyivs'ka oblast","long_name":"Kyivs'ka oblast"},{"long_name":"Ukraine","types":["country","political"],"short_name":"UA"},{"long_name":"824M+WG","short_name":"824M+WG","types":["plus_code"]},{"types":["locality","political"],"long_name":"Pryp'yat'","short_name":"Pryp'yat'"},{"long_name":"Ivankivs'kyi district","types":["administrative_area_level_2","political"],"short_name":"Ivankivs'kyi district"},{"long_name":"Kyiv Oblast","short_name":"Kyiv Oblast","types":["administrative_area_level_1","political"]},{"long_name":"Ukraine","short_name":"UA","types":["country","political"]},{"types":["latitude"],"long_name":51.3073145,"short_name":51.3073145},{"types":["longitude"],"long_name":30.033789,"short_name":30.033789}]} | J55: =GOOGLEMAPS_GET_ADDRESS_COMPONENTS_STRING(F55,false) -> [{"long_name":"Vulytsya Bez Nazvy","types":["route"],"short_name":"Vulytsya Bez Nazvy"},{"types":["administrative_area_level_2","political"],"long_name":"Ivankivs'kyi district","short_name":"Ivankivs'kyi district"},{"types":["administrative_area_level_1","political"],"short_name":"Kyivs'ka oblast","long_name":"Kyivs'ka oblast"},{"long_name":"Ukraine","types":["country","political"],"short_name":"UA"},{"long_name":"824M+WG","short_name":"824M+WG","types":["plus_code"]},{"types":["locality","political"],"long_name":"Pryp'yat'","short_name":"Pryp'yat'"},{"long_name":"Ivankivs'kyi district","types":["administrative_area_level_2","political"],"short_name":"Ivankivs'kyi district"},{"long_name":"Kyiv Oblast","short_name":"Kyiv Oblast","types":["administrative_area_level_1","political"]},{"long_name":"Ukraine","short_name":"UA","types":["country","political"]},{"types":["latitude"],"long_name":51.3073145,"short_name":51.3073145},{"types":["longitude"],"long_name":30.033789,"short_name":30.033789},{"types":["debug_info","cache_load_result"],"long_name":"hit","short_name":"hit"}] | K55: =NOT(AND(NOT(_xlfn.ISFORMULA(P55)),AND(NOT(_xlfn.ISFORMULA(Q55)),AND(NOT(_xlfn.ISFORMULA(R55)),AND(NOT(_xlfn.ISFORMULA(S55)),AND(NOT(_xlfn.ISFORMULA(T55)),AND(NOT(_xlfn.ISFORMULA(U55)),AND(NOT(_xlfn.ISFORMULA(V55)))))))))) -> TRUE | L55: =iferror(SEARCH(P55,F55),-1)>=0 -> FALSE | M55: TRUE | N55: =GOOGLEMAPS_GET_ADDRESS_LATITUDE(F55,true) -> 51.307314 | O55: =GOOGLEMAPS_GET_ADDRESS_LONGITUDE(F55,true) -> 30.033789 | P55: =GOOGLEMAPS_GET_ADDRESS_CITY(F55,true,false) -> Pryp'yat' | Q55: =GOOGLEMAPS_GET_ADDRESS_STATE(F55,true,false) -> Kyivs'ka oblast | R55: =GOOGLEMAPS_GET_ADDRESS_POSTAL_CODE(F55,false,false) -> UNDEFINED | S55: =GOOGLEMAPS_GET_ADDRESS_COUNTRY(F55,true,false) -> Ukraine | T55: =IFERROR(GOOGLEMAPS_DISTANCE("2116 4th Ave, Seattle, WA, 98121", F55, "driving")+0,"Not Driveable") -> Not Driveable | U55: =iferror(GOOGLEMAPS_DURATION("2116 4th Ave, Seattle, WA, 98121", F55, "driving")+0,"Not Driveable") -> Not Driveable | V55: =GOOGLEMAPS_DISTANCE("2116 4th Ave, Seattle, WA, 98121", F55, "flying")+0 -> 5408.6557 | X55: =if(W55="YES","UNKNOWN","N/A") -> N/A | Z55: N/A | AB55: https://magazine.lensvid.com/article/fb/1318327108/mysterious-places-in-the-world-that-are-off-limits-to-everyone-and-why/
